Workbook
Name Categories: OFFSET(Categories!$J$7,0,0,COUNTIF(Categories!$J$7:$J$44,"<>"&"--"),1)
Name Months: OFFSET(Snapshot!$V$7,0,0,COUNTIF(Snapshot!$V$7:$V$200,"<>"&"--"),1)
Name snapshot_month: Snapshot!$Q$4
Name user_custom_categories: Categories!$C$25:$E$44

Sheet Welcome
A2: Money in Excel
A3: This template helps you see all your financial accounts in one place, make a plan, and reach your financial goals
A4: Automatically import your transactions
A5: Keep a personal record of your finances
A6: Understand your financial habits
A7: Personalize your information for your needs
A9: Did you know?
A10: You must trust the Excel add-in to access Money in Excel. (The add-in is to the right of the spreadsheet.)
A11: Arrow: scroll down to learn more
A13: 1.Add accounts to Money in Excel
A14: 2.Customize your categories to reflect your spending
A15: Arrow: keep scrolling
... A21: 5. See how spending habits add up, make changes, and reach your financial goals

Sheet Instructions
A2: Learn how to get started with Money in Excel
A3: Follow these tips and instructions to get the most out of your workbook
A4: Arrow: scroll down to learn more
A6: Get started
A7: 1 | B7: Make sure the Money in Excel pane is open. If it's not, click the Money in Excel icon in on the upper right corner of your ribbon.
A8: 2 | B8: Trust the add-in
A9: 3 | B9: Sign in with a Microsoft 365 Family or Personal account
A10: 4 | B10: Connect a primary financial account
A11: 5 | B11: Categorize your transactions in the Categories sheet
A12: 6 | B12: Update your workbook to sync your recent transactions
A13: Note: Money in Excel only works on desktop or web, not on mobile
A14: Arrow: keep scrolling
A16: Did you know?
A17: You must trust the Excel add-in to access Money in Excel. (The add-in is to the right of the spreadsheet.)
A19: Save your workbook
A20: 1 | B20: Save your workbook before closing the file
A21: 2 | B21: Name your workbook by selecting "Save as" and renaming the file
A22: 3 | B22: Save your file in a secure location
A23: 4 | B23: Come back to that location when you're ready to use Money in Excel
A24: Note: To share your Money in Excel workbook, the recipient needs to download the Money in Excel template, sign in with your Microsoft account credentials, and have access to your workbook (online or a local copy)
A25: Arrow: keep scrolling
A27: Sheets + Money in Excel pane
A28: 1 | B28: The Money in Excel pane sits to the right of the spreadsheet and is the "brain" of the workbook
A29: 2 | B29: The Money in Excel pane needs to be open in order to update your workbook with new transactions, capture changes you make to your templates, and view personalized insights on your spending
A30: 3 | B30: You can also add new templates from the Money in Excel pane for Recurring Expenses and Net Worth
A31: Arrow: keep scrolling
A33: Transactions sheet
A34: 1 | B34: Your transactions sheet shows transactions from financial accounts you have connected. The Money in Excel pane will tell you when there are new transactions to update. In order for updates to work correctly, you cannot add columns or rows to the table.
A35: 2 | B35: Review your transactions. All transactions have already been categorized, but you can change the Category and Merchant names.
A36: 3 | B36: Do not delete your Transactions spreadsheet as that will affect all of your other sheets
A37: Arrow: keep scrolling
A39: Categories sheet
A40: 1 | B40: There are 18 Default Categories that cannot be changed
A41: 2 | B41: You can add custom categories. Be sure to include a Category Type.
A42: 3 | B42: The categories on this spreadsheet are reflected in "Category" column on "Transactions" spreadsheet
A43: 4 | B43: Do not delete your Categories spreadsheet as that will affect all your other sheets

Sheet Snapshot
C2: Snapshot | Q2: Choose month below
C4: See your spending trends month over month with easy to read graphs. To switch months, click on the blue date box to the right. | Q4: June 2020 | W4: =_xlfn.XLOOKUP(TEXT(Q4,"mmmm yyyy"),$V$7:$V$200,$W$7:$W$200) -> #N/A | Y4: Monthly Summary | AC4: Category | AD4: Count | AE4: Rank | AF4: Order | AG4: Category | AH4: $ | AJ4: Display Axis | AK4: Current Mon. | AL4: $ | AM4: =TEXT(AK6,"MMMM")&" Spending" -> #N/A | AN4: Max Date | AO4: Last Mon. | AP4: $ | AQ4: =TEXT(AO6,"MMMM")&" Spending" -> #N/A | AR4: Max Date | AT4: Merchants | AU4: $ | AV4: Trans Count | AW4: Trans Rank | AX4: $ Rank
V6: Input | W6: Month Filter | Y6: =TEXT(ABS(Z9),"$#,##0")&" "&IF(Z7>Z8,"less was spent compared to last month","more was spent compared to last month") -> $0 more was spent compared to last month | AC6: =IF(Categories!E7="Expense",Categories!D7,"--") -> -- | AD6: =SUMIFS(Table1[Amount $],Table1[Category],Snapshot!AC6,Table1[Amount $],"<"&0,Table1[Month],Snapshot!$W$4)*-1 -> 0 | AE6: =RANK(AD6,$AD$6:$AD$35,0)+COUNTIF(AD6:$AD$6,AD6)-1 -> 1 | AF6: 1 | AG6: {=IF(INDEX($AD$6:$AD$35,MATCH(AF6,$AE$6:$AE$35,0),0)=0,"",INDEX($AC$6:$AC$35,MATCH(AF6,$AE$6:$AE$35,0),0))} | AH6: {=IF(INDEX($AD$6:$AD$35,MATCH(AF6,$AE$6:$AE$35,0),0)=0,0,INDEX($AD$6:$AD$35,MATCH(AF6,$AE$6:$AE$35,0),0))} -> 0 | AJ6: =DATE(2000,1,1) -> 36526 | AK6: =DATE(YEAR(W4),MONTH(W4),DAY(W4)) -> #N/A | AL6: =SUMIFS(Table1[Amount $],Table1[Amount $],"<"&0,Table1[Category Type],"Expense",Table1[Date],Snapshot!AK6)*-1 -> 0 | AM6: =IF(AK6>TODAY(),NA(),SUM(AL6:$AL$6)) -> #N/A | AN6: =IF(OR(AK6=EOMONTH($AK$6,0),AK6=TODAY()),AM6,NA()) -> #N/A | AO6: =DATE(YEAR(AK6),MONTH(AK6)-1,DAY(AK6)) -> #N/A | AP6: =SUMIFS(Table1[Amount $],Table1[Amount $],"<"&0,Table1[Category Type],"Expense",Table1[Date],Snapshot!AO6)*-1 -> 0 | AQ6: =IF(AO6<=EOMONTH($AO$6,0),SUM(AP$6:$AP6),NA()) -> #N/A | AR6: =IF(AO6=EOMONTH($AO$6,0),AQ6,NA()) -> #N/A | AT6: {=_xlfn.UNIQUE(_xlfn._xlws.FILTER(Table1[Merchant],(Table1[Merchant]<>"")*(Table1[Amount $]<0)*(Table1[Month]=Snapshot!$W$4)*(Table1[Category Type]="Expense")))} -> #N/A | AU6: =IF(ISBLANK(AT6),"",SUMIFS(Table1[Amount $],Table1[Amount $],"<"&0,Table1[Merchant],Snapshot!AT6,Table1[Month],Snapshot!$W$4)*-1) -> 0 | AV6: =IF(ISBLANK(AT6),"",COUNTIFS(Table1[Merchant],Snapshot!AT6,Table1[Month],Snapshot!$W$4)) -> 0 | AW6: =IFERROR(RANK(AV6,$AV$6:$AV$200)+COUNTIF($AV$6:AV6,AV6)-1,"") -> 1 | AX6: =IFERROR(RANK(AU6,$AU$6:$AU$200)+COUNTIF($AU$6:AU6,AU6)-1,"") -> 1
D7: Current vs. previous month spending | M7: This month's top spending categories | V7: =IF(ISBLANK(W7),"--",TEXT(W7,"mmmm")&" "&TEXT(W7,"YYYY")) -> #VALUE! | W7: {=_xlfn._xlws.SORT(_xlfn.UNIQUE(_xlfn._xlws.FILTER(Table1[Month],Table1[Month]<>"",)),1,-1)} -> #VALUE! | Y7: =IFERROR(TEXT(AO6,"mmmm"),"--") -> -- | Z7: =SUMIFS(Table1[Amount $],Table1[Category Type],"Expense",Table1[Amount $],"<"&0,Table1[Month],DATE(YEAR(Snapshot!$W$4),MONTH(Snapshot!$W$4)-1,DAY(Snapshot!$W$4)))*-1 -> 0 | AC7: =IF(Categories!E8="Expense",Categories!D8,"--") -> -- | AD7: =SUMIFS(Table1[Amount $],Table1[Category],Snapshot!AC7,Table1[Amount $],"<"&0,Table1[Month],Snapshot!$W$4)*-1 -> 0 | AE7: =RANK(AD7,$AD$6:$AD$35,0)+COUNTIF(AD$6:$AD7,AD7)-1 -> 2 | AF7: 2 | AG7: {=IF(INDEX($AD$6:$AD$35,MATCH(AF7,$AE$6:$AE$35,0),0)=0,"",INDEX($AC$6:$AC$35,MATCH(AF7,$AE$6:$AE$35,0),0))} | AH7: {=IF(INDEX($AD$6:$AD$35,MATCH(AF7,$AE$6:$AE$35,0),0)=0,0,INDEX($AD$6:$AD$35,MATCH(AF7,$AE$6:$AE$35,0),0))} -> 0 | AJ7: =DATE(YEAR(AJ6),MONTH(AJ6),DAY(AJ6)+1) -> 36527 | AK7: =IF(MONTH(AK6)=MONTH(DATE(YEAR(AK6),MONTH(AK6),DAY(AK6)+1)),DATE(YEAR(AK6),MONTH(AK6),DAY(AK6)+1),NA()) -> #N/A | AL7: =SUMIFS(Table1[Amount $],Table1[Amount $],"<"&0,Table1[Category Type],"Expense",Table1[Date],Snapshot!AK7)*-1 -> 0 | AM7: =IF(AK7>TODAY(),NA(),SUM(AL$6:$AL7)) -> #N/A | AN7: =IF(OR(AK7=EOMONTH($AK$6,0),AK7=TODAY()),AM7,NA()) -> #N/A | AO7: =IF(MONTH(AO6)=MONTH(DATE(YEAR(AO6),MONTH(AO6),DAY(AO6)+1)),DATE(YEAR(AO6),MONTH(AO6),DAY(AO6)+1),NA()) -> #N/A | AP7: =SUMIFS(Table1[Amount $],Table1[Amount $],"<"&0,Table1[Category Type],"Expense",Table1[Date],Snapshot!AO7)*-1 -> 0 | AQ7: =IF(AO7<=EOMONTH($AO$6,0),SUM(AP$6:$AP7),NA()) -> #N/A | AR7: =IF(AO7=EOMONTH($AO$6,0),AQ7,NA()) -> #N/A | AU7: =IF(ISBLANK(AT7),"",SUMIFS(Table1[Amount $],Table1[Amount $],"<"&0,Table1[Merchant],Snapshot!AT7,Table1[Month],Snapshot!$W$4)*-1) | AV7: =IF(ISBLANK(AT7),"",COUNTIFS(Table1[Merchant],Snapshot!AT7,Table1[Month],Snapshot!$W$4)) | AW7: =IFERROR(RANK(AV7,$AV$6:$AV$200)+COUNTIF($AV$6:AV7,AV7)-1,"") | AX7: =IFERROR(RANK(AU7,$AU$6:$AU$200)+COUNTIF($AU$6:AU7,AU7)-1,"")
D8: =Y6 -> $0 more was spent compared to last month | M8: =Q10&" accounts for "&TEXT(S10/S22,"0%")&" of money spent this month" -> #DIV/0! | V8: =IF(ISBLANK(W8),"--",TEXT(W8,"mmmm")&" "&TEXT(W8,"YYYY")) -> -- | Y8: =IFERROR(TEXT(AK6,"mmmm"),"--") -> -- | Z8: =SUMIFS(Table1[Amount $],Table1[Category Type],"Expense",Table1[Amount $],"<"&0,Table1[Month],Snapshot!$W$4)*-1 -> 0 | AC8: =IF(Categories!E9="Expense",Categories!D9,"--") -> -- | AD8: =SUMIFS(Table1[Amount $],Table1[Category],Snapshot!AC8,Table1[Amount $],"<"&0,Table1[Month],Snapshot!$W$4)*-1 -> 0 | AE8: =RANK(AD8,$AD$6:$AD$35,0)+COUNTIF(AD$6:$AD8,AD8)-1 -> 3 | AF8: 3 | AG8: {=IF(INDEX($AD$6:$AD$35,MATCH(AF8,$AE$6:$AE$35,0),0)=0,"",INDEX($AC$6:$AC$35,MATCH(AF8,$AE$6:$AE$35,0),0))} | AH8: {=IF(INDEX($AD$6:$AD$35,MATCH(AF8,$AE$6:$AE$35,0),0)=0,0,INDEX($AD$6:$AD$35,MATCH(AF8,$AE$6:$AE$35,0),0))} -> 0 | AJ8: =DATE(YEAR(AJ7),MONTH(AJ7),DAY(AJ7)+1) -> 36528 | AK8: =IF(MONTH(AK7)=MONTH(DATE(YEAR(AK7),MONTH(AK7),DAY(AK7)+1)),DATE(YEAR(AK7),MONTH(AK7),DAY(AK7)+1),NA()) -> #N/A | AL8: =SUMIFS(Table1[Amount $],Table1[Amount $],"<"&0,Table1[Category Type],"Expense",Table1[Date],Snapshot!AK8)*-1 -> 0 | AM8: =IF(AK8>TODAY(),NA(),SUM(AL$6:$AL8)) -> #N/A | AN8: =IF(OR(AK8=EOMONTH($AK$6,0),AK8=TODAY()),AM8,NA()) -> #N/A | AO8: =IF(MONTH(AO7)=MONTH(DATE(YEAR(AO7),MONTH(AO7),DAY(AO7)+1)),DATE(YEAR(AO7),MONTH(AO7),DAY(AO7)+1),NA()) -> #N/A | AP8: =SUMIFS(Table1[Amount $],Table1[Amount $],"<"&0,Table1[Category Type],"Expense",Table1[Date],Snapshot!AO8)*-1 -> 0 | AQ8: =IF(AO8<=EOMONTH($AO$6,0),SUM(AP$6:$AP8),NA()) -> #N/A | AR8: =IF(AO8=EOMONTH($AO$6,0),AQ8,NA()) -> #N/A | AU8: =IF(ISBLANK(AT8),"",SUMIFS(Table1[Amount $],Table1[Amount $],"<"&0,Table1[Merchant],Snapshot!AT8,Table1[Month],Snapshot!$W$4)*-1) | AV8: =IF(ISBLANK(AT8),"",COUNTIFS(Table1[Merchant],Snapshot!AT8,Table1[Month],Snapshot!$W$4)) | AW8: =IFERROR(RANK(AV8,$AV$6:$AV$200)+COUNTIF($AV$6:AV8,AV8)-1,"") | AX8: =IFERROR(RANK(AU8,$AU$6:$AU$200)+COUNTIF($AU$6:AU8,AU8)-1,"")
V9: =IF(ISBLANK(W9),"--",TEXT(W9,"mmmm")&" "&TEXT(W9,"YYYY")) -> -- | Y9: Difference | Z9: =Z8-Z7 -> 0 | AC9: =IF(Categories!E10="Expense",Categories!D10,"--") -> Auto/Transport | AD9: =SUMIFS(Table1[Amount $],Table1[Category],Snapshot!AC9,Table1[Amount $],"<"&0,Table1[Month],Snapshot!$W$4)*-1 -> 0 | AE9: =RANK(AD9,$AD$6:$AD$35,0)+COUNTIF(AD$6:$AD9,AD9)-1 -> 4 | AF9: 4 | AG9: {=IF(INDEX($AD$6:$AD$35,MATCH(AF9,$AE$6:$AE$35,0),0)=0,"",INDEX($AC$6:$AC$35,MATCH(AF9,$AE$6:$AE$35,0),0))} | AH9: {=IF(INDEX($AD$6:$AD$35,MATCH(AF9,$AE$6:$AE$35,0),0)=0,0,INDEX($AD$6:$AD$35,MATCH(AF9,$AE$6:$AE$35,0),0))} -> 0 | AJ9: =DATE(YEAR(AJ8),MONTH(AJ8),DAY(AJ8)+1) -> 36529 | AK9: =IF(MONTH(AK8)=MONTH(DATE(YEAR(AK8),MONTH(AK8),DAY(AK8)+1)),DATE(YEAR(AK8),MONTH(AK8),DAY(AK8)+1),NA()) -> #N/A | AL9: =SUMIFS(Table1[Amount $],Table1[Amount $],"<"&0,Table1[Category Type],"Expense",Table1[Date],Snapshot!AK9)*-1 -> 0 | AM9: =IF(AK9>TODAY(),NA(),SUM(AL$6:$AL9)) -> #N/A | AN9: =IF(OR(AK9=EOMONTH($AK$6,0),AK9=TODAY()),AM9,NA()) -> #N/A | AO9: =IF(MONTH(AO8)=MONTH(DATE(YEAR(AO8),MONTH(AO8),DAY(AO8)+1)),DATE(YEAR(AO8),MONTH(AO8),DAY(AO8)+1),NA()) -> #N/A | AP9: =SUMIFS(Table1[Amount $],Table1[Amount $],"<"&0,Table1[Category Type],"Expense",Table1[Date],Snapshot!AO9)*-1 -> 0 | AQ9: =IF(AO9<=EOMONTH($AO$6,0),SUM(AP$6:$AP9),NA()) -> #N/A | AR9: =IF(AO9=EOMONTH($AO$6,0),AQ9,NA()) -> #N/A | AU9: =IF(ISBLANK(AT9),"",SUMIFS(Table1[Amount $],Table1[Amount $],"<"&0,Table1[Merchant],Snapshot!AT9,Table1[Month],Snapshot!$W$4)*-1) | AV9: =IF(ISBLANK(AT9),"",COUNTIFS(Table1[Merchant],Snapshot!AT9,Table1[Month],Snapshot!$W$4)) | AW9: =IFERROR(RANK(AV9,$AV$6:$AV$200)+COUNTIF($AV$6:AV9,AV9)-1,"") | AX9: =IFERROR(RANK(AU9,$AU$6:$AU$200)+COUNTIF($AU$6:AU9,AU9)-1,"")
Q10: {=INDEX($AG$6:$AG$11,MATCH(1,$AF$6:$AF$11,0),0)} | S10: {=INDEX($AH$6:$AH$11,MATCH(1,$AF$6:$AF$11,0),0)} -> 0 | V10: =IF(ISBLANK(W10),"--",TEXT(W10,"mmmm")&" "&TEXT(W10,"YYYY")) -> -- | AC10: =IF(Categories!E11="Expense",Categories!D11,"--") -> Bills/Utilities | AD10: =SUMIFS(Table1[Amount $],Table1[Category],Snapshot!AC10,Table1[Amount $],"<"&0,Table1[Month],Snapshot!$W$4)*-1 -> 0 | AE10: =RANK(AD10,$AD$6:$AD$35,0)+COUNTIF(AD$6:$AD10,AD10)-1 -> 5 | AF10: 5 | AG10: {=IF(INDEX($AD$6:$AD$35,MATCH(AF10,$AE$6:$AE$35,0),0)=0,"",INDEX($AC$6:$AC$35,MATCH(AF10,$AE$6:$AE$35,0),0))} | AH10: {=IF(INDEX($AD$6:$AD$35,MATCH(AF10,$AE$6:$AE$35,0),0)=0,0,INDEX($AD$6:$AD$35,MATCH(AF10,$AE$6:$AE$35,0),0))} -> 0 | AJ10: =DATE(YEAR(AJ9),MONTH(AJ9),DAY(AJ9)+1) -> 36530 | AK10: =IF(MONTH(AK9)=MONTH(DATE(YEAR(AK9),MONTH(AK9),DAY(AK9)+1)),DATE(YEAR(AK9),MONTH(AK9),DAY(AK9)+1),NA()) -> #N/A | AL10: =SUMIFS(Table1[Amount $],Table1[Amount $],"<"&0,Table1[Category Type],"Expense",Table1[Date],Snapshot!AK10)*-1 -> 0 | AM10: =IF(AK10>TODAY(),NA(),SUM(AL$6:$AL10)) -> #N/A | AN10: =IF(OR(AK10=EOMONTH($AK$6,0),AK10=TODAY()),AM10,NA()) -> #N/A | AO10: =IF(MONTH(AO9)=MONTH(DATE(YEAR(AO9),MONTH(AO9),DAY(AO9)+1)),DATE(YEAR(AO9),MONTH(AO9),DAY(AO9)+1),NA()) -> #N/A | AP10: =SUMIFS(Table1[Amount $],Table1[Amount $],"<"&0,Table1[Category Type],"Expense",Table1[Date],Snapshot!AO10)*-1 -> 0 | AQ10: =IF(AO10<=EOMONTH($AO$6,0),SUM(AP$6:$AP10),NA()) -> #N/A | AR10: =IF(AO10=EOMONTH($AO$6,0),AQ10,NA()) -> #N/A | AU10: =IF(ISBLANK(AT10),"",SUMIFS(Table1[Amount $],Table1[Amount $],"<"&0,Table1[Merchant],Snapshot!AT10,Table1[Month],Snapshot!$W$4)*-1) | AV10: =IF(ISBLANK(AT10),"",COUNTIFS(Table1[Merchant],Snapshot!AT10,Table1[Month],Snapshot!$W$4)) | AW10: =IFERROR(RANK(AV10,$AV$6:$AV$200)+COUNTIF($AV$6:AV10,AV10)-1,"") | AX10: =IFERROR(RANK(AU10,$AU$6:$AU$200)+COUNTIF($AU$6:AU10,AU10)-1,"")
V11: =IF(ISBLANK(W11),"--",TEXT(W11,"mmmm")&" "&TEXT(W11,"YYYY")) -> -- | AC11: =IF(Categories!E12="Expense",Categories!D12,"--") -> Entertainment | AD11: =SUMIFS(Table1[Amount $],Table1[Category],Snapshot!AC11,Table1[Amount $],"<"&0,Table1[Month],Snapshot!$W$4)*-1 -> 0 | AE11: =RANK(AD11,$AD$6:$AD$35,0)+COUNTIF(AD$6:$AD11,AD11)-1 -> 6 | AF11: 6 | AG11: =IF(SUM(AH6:AH10)=SUM(AD6:AD35),"","All Other Categories") | AH11: =SUM(AD6:AD35)-SUM(AH6:AH10) -> 0 | AJ11: =DATE(YEAR(AJ10),MONTH(AJ10),DAY(AJ10)+1) -> 36531 | AK11: =IF(MONTH(AK10)=MONTH(DATE(YEAR(AK10),MONTH(AK10),DAY(AK10)+1)),DATE(YEAR(AK10),MONTH(AK10),DAY(AK10)+1),NA()) -> #N/A | AL11: =SUMIFS(Table1[Amount $],Table1[Amount $],"<"&0,Table1[Category Type],"Expense",Table1[Date],Snapshot!AK11)*-1 -> 0 | AM11: =IF(AK11>TODAY(),NA(),SUM(AL$6:$AL11)) -> #N/A | AN11: =IF(OR(AK11=EOMONTH($AK$6,0),AK11=TODAY()),AM11,NA()) -> #N/A | AO11: =IF(MONTH(AO10)=MONTH(DATE(YEAR(AO10),MONTH(AO10),DAY(AO10)+1)),DATE(YEAR(AO10),MONTH(AO10),DAY(AO10)+1),NA()) -> #N/A | AP11: =SUMIFS(Table1[Amount $],Table1[Amount $],"<"&0,Table1[Category Type],"Expense",Table1[Date],Snapshot!AO11)*-1 -> 0 | AQ11: =IF(AO11<=EOMONTH($AO$6,0),SUM(AP$6:$AP11),NA()) -> #N/A | AR11: =IF(AO11=EOMONTH($AO$6,0),AQ11,NA()) -> #N/A | AU11: =IF(ISBLANK(AT11),"",SUMIFS(Table1[Amount $],Table1[Amount $],"<"&0,Table1[Merchant],Snapshot!AT11,Table1[Month],Snapshot!$W$4)*-1) | AV11: =IF(ISBLANK(AT11),"",COUNTIFS(Table1[Merchant],Snapshot!AT11,Table1[Month],Snapshot!$W$4)) | AW11: =IFERROR(RANK(AV11,$AV$6:$AV$200)+COUNTIF($AV$6:AV11,AV11)-1,"") | AX11: =IFERROR(RANK(AU11,$AU$6:$AU$200)+COUNTIF($AU$6:AU11,AU11)-1,"")
Q12: {=INDEX($AG$6:$AG$11,MATCH(2,$AF$6:$AF$11,0),0)} | S12: {=INDEX($AH$6:$AH$11,MATCH(2,$AF$6:$AF$11,0),0)} -> 0 | V12: =IF(ISBLANK(W12),"--",TEXT(W12,"mmmm")&" "&TEXT(W12,"YYYY")) -> -- | AC12: =IF(Categories!E13="Expense",Categories!D13,"--") -> Fees/Charges | AD12: =SUMIFS(Table1[Amount $],Table1[Category],Snapshot!AC12,Table1[Amount $],"<"&0,Table1[Month],Snapshot!$W$4)*-1 -> 0 | AE12: =RANK(AD12,$AD$6:$AD$35,0)+COUNTIF(AD$6:$AD12,AD12)-1 -> 7 | AG12: Total | AH12: =SUM(AH6:AH11) -> 0 | AJ12: =DATE(YEAR(AJ11),MONTH(AJ11),DAY(AJ11)+1) -> 36532 | AK12: =IF(MONTH(AK11)=MONTH(DATE(YEAR(AK11),MONTH(AK11),DAY(AK11)+1)),DATE(YEAR(AK11),MONTH(AK11),DAY(AK11)+1),NA()) -> #N/A | AL12: =SUMIFS(Table1[Amount $],Table1[Amount $],"<"&0,Table1[Category Type],"Expense",Table1[Date],Snapshot!AK12)*-1 -> 0 | AM12: =IF(AK12>TODAY(),NA(),SUM(AL$6:$AL12)) -> #N/A | AN12: =IF(OR(AK12=EOMONTH($AK$6,0),AK12=TODAY()),AM12,NA()) -> #N/A | AO12: =IF(MONTH(AO11)=MONTH(DATE(YEAR(AO11),MONTH(AO11),DAY(AO11)+1)),DATE(YEAR(AO11),MONTH(AO11),DAY(AO11)+1),NA()) -> #N/A | AP12: =SUMIFS(Table1[Amount $],Table1[Amount $],"<"&0,Table1[Category Type],"Expense",Table1[Date],Snapshot!AO12)*-1 -> 0 | AQ12: =IF(AO12<=EOMONTH($AO$6,0),SUM(AP$6:$AP12),NA()) -> #N/A | AR12: =IF(AO12=EOMONTH($AO$6,0),AQ12,NA()) -> #N/A | AU12: =IF(ISBLANK(AT12),"",SUMIFS(Table1[Amount $],Table1[Amount $],"<"&0,Table1[Merchant],Snapshot!AT12,Table1[Month],Snapshot!$W$4)*-1) | AV12: =IF(ISBLANK(AT12),"",COUNTIFS(Table1[Merchant],Snapshot!AT12,Table1[Month],Snapshot!$W$4)) | AW12: =IFERROR(RANK(AV12,$AV$6:$AV$200)+COUNTIF($AV$6:AV12,AV12)-1,"") | AX12: =IFERROR(RANK(AU12,$AU$6:$AU$200)+COUNTIF($AU$6:AU12,AU12)-1,"")
V13: =IF(ISBLANK(W13),"--",TEXT(W13,"mmmm")&" "&TEXT(W13,"YYYY")) -> -- | AC13: =IF(Categories!E14="Expense",Categories!D14,"--") -> Groceries | AD13: =SUMIFS(Table1[Amount $],Table1[Category],Snapshot!AC13,Table1[Amount $],"<"&0,Table1[Month],Snapshot!$W$4)*-1 -> 0 | AE13: =RANK(AD13,$AD$6:$AD$35,0)+COUNTIF(AD$6:$AD13,AD13)-1 -> 8 | AJ13: =DATE(YEAR(AJ12),MONTH(AJ12),DAY(AJ12)+1) -> 36533 | AK13: =IF(MONTH(AK12)=MONTH(DATE(YEAR(AK12),MONTH(AK12),DAY(AK12)+1)),DATE(YEAR(AK12),MONTH(AK12),DAY(AK12)+1),NA()) -> #N/A | AL13: =SUMIFS(Table1[Amount $],Table1[Amount $],"<"&0,Table1[Category Type],"Expense",Table1[Date],Snapshot!AK13)*-1 -> 0 | AM13: =IF(AK13>TODAY(),NA(),SUM(AL$6:$AL13)) -> #N/A | AN13: =IF(OR(AK13=EOMONTH($AK$6,0),AK13=TODAY()),AM13,NA()) -> #N/A | AO13: =IF(MONTH(AO12)=MONTH(DATE(YEAR(AO12),MONTH(AO12),DAY(AO12)+1)),DATE(YEAR(AO12),MONTH(AO12),DAY(AO12)+1),NA()) -> #N/A | AP13: =SUMIFS(Table1[Amount $],Table1[Amount $],"<"&0,Table1[Category Type],"Expense",Table1[Date],Snapshot!AO13)*-1 -> 0 | AQ13: =IF(AO13<=EOMONTH($AO$6,0),SUM(AP$6:$AP13),NA()) -> #N/A | AR13: =IF(AO13=EOMONTH($AO$6,0),AQ13,NA()) -> #N/A | AU13: =IF(ISBLANK(AT13),"",SUMIFS(Table1[Amount $],Table1[Amount $],"<"&0,Table1[Merchant],Snapshot!AT13,Table1[Month],Snapshot!$W$4)*-1) | AV13: =IF(ISBLANK(AT13),"",COUNTIFS(Table1[Merchant],Snapshot!AT13,Table1[Month],Snapshot!$W$4)) | AW13: =IFERROR(RANK(AV13,$AV$6:$AV$200)+COUNTIF($AV$6:AV13,AV13)-1,"") | AX13: =IFERROR(RANK(AU13,$AU$6:$AU$200)+COUNTIF($AU$6:AU13,AU13)-1,"")
Q14: {=INDEX($AG$6:$AG$11,MATCH(3,$AF$6:$AF$11,0),0)} | S14: {=INDEX($AH$6:$AH$11,MATCH(3,$AF$6:$AF$11,0),0)} -> 0 | V14: =IF(ISBLANK(W14),"--",TEXT(W14,"mmmm")&" "&TEXT(W14,"YYYY")) -> -- | AC14: =IF(Categories!E15="Expense",Categories!D15,"--") -> Health/Fitness | AD14: =SUMIFS(Table1[Amount $],Table1[Category],Snapshot!AC14,Table1[Amount $],"<"&0,Table1[Month],Snapshot!$W$4)*-1 -> 0 | AE14: =RANK(AD14,$AD$6:$AD$35,0)+COUNTIF(AD$6:$AD14,AD14)-1 -> 9 | AJ14: =DATE(YEAR(AJ13),MONTH(AJ13),DAY(AJ13)+1) -> 36534 | AK14: =IF(MONTH(AK13)=MONTH(DATE(YEAR(AK13),MONTH(AK13),DAY(AK13)+1)),DATE(YEAR(AK13),MONTH(AK13),DAY(AK13)+1),NA()) -> #N/A | AL14: =SUMIFS(Table1[Amount $],Table1[Amount $],"<"&0,Table1[Category Type],"Expense",Table1[Date],Snapshot!AK14)*-1 -> 0 | AM14: =IF(AK14>TODAY(),NA(),SUM(AL$6:$AL14)) -> #N/A | AN14: =IF(OR(AK14=EOMONTH($AK$6,0),AK14=TODAY()),AM14,NA()) -> #N/A | AO14: =IF(MONTH(AO13)=MONTH(DATE(YEAR(AO13),MONTH(AO13),DAY(AO13)+1)),DATE(YEAR(AO13),MONTH(AO13),DAY(AO13)+1),NA()) -> #N/A | AP14: =SUMIFS(Table1[Amount $],Table1[Amount $],"<"&0,Table1[Category Type],"Expense",Table1[Date],Snapshot!AO14)*-1 -> 0 | AQ14: =IF(AO14<=EOMONTH($AO$6,0),SUM(AP$6:$AP14),NA()) -> #N/A | AR14: =IF(AO14=EOMONTH($AO$6,0),AQ14,NA()) -> #N/A | AU14: =IF(ISBLANK(AT14),"",SUMIFS(Table1[Amount $],Table1[Amount $],"<"&0,Table1[Merchant],Snapshot!AT14,Table1[Month],Snapshot!$W$4)*-1) | AV14: =IF(ISBLANK(AT14),"",COUNTIFS(Table1[Merchant],Snapshot!AT14,Table1[Month],Snapshot!$W$4)) | AW14: =IFERROR(RANK(AV14,$AV$6:$AV$200)+COUNTIF($AV$6:AV14,AV14)-1,"") | AX14: =IFERROR(RANK(AU14,$AU$6:$AU$200)+COUNTIF($AU$6:AU14,AU14)-1,"")
V15: =IF(ISBLANK(W15),"--",TEXT(W15,"mmmm")&" "&TEXT(W15,"YYYY")) -> -- | AC15: =IF(Categories!E16="Expense",Categories!D16,"--") -> Home | AD15: =SUMIFS(Table1[Amount $],Table1[Category],Snapshot!AC15,Table1[Amount $],"<"&0,Table1[Month],Snapshot!$W$4)*-1 -> 0 | AE15: =RANK(AD15,$AD$6:$AD$35,0)+COUNTIF(AD$6:$AD15,AD15)-1 -> 10 | AJ15: =DATE(YEAR(AJ14),MONTH(AJ14),DAY(AJ14)+1) -> 36535 | AK15: =IF(MONTH(AK14)=MONTH(DATE(YEAR(AK14),MONTH(AK14),DAY(AK14)+1)),DATE(YEAR(AK14),MONTH(AK14),DAY(AK14)+1),NA()) -> #N/A | AL15: =SUMIFS(Table1[Amount $],Table1[Amount $],"<"&0,Table1[Category Type],"Expense",Table1[Date],Snapshot!AK15)*-1 -> 0 | AM15: =IF(AK15>TODAY(),NA(),SUM(AL$6:$AL15)) -> #N/A | AN15: =IF(OR(AK15=EOMONTH($AK$6,0),AK15=TODAY()),AM15,NA()) -> #N/A | AO15: =IF(MONTH(AO14)=MONTH(DATE(YEAR(AO14),MONTH(AO14),DAY(AO14)+1)),DATE(YEAR(AO14),MONTH(AO14),DAY(AO14)+1),NA()) -> #N/A | AP15: =SUMIFS(Table1[Amount $],Table1[Amount $],"<"&0,Table1[Category Type],"Expense",Table1[Date],Snapshot!AO15)*-1 -> 0 | AQ15: =IF(AO15<=EOMONTH($AO$6,0),SUM(AP$6:$AP15),NA()) -> #N/A | AR15: =IF(AO15=EOMONTH($AO$6,0),AQ15,NA()) -> #N/A | AU15: =IF(ISBLANK(AT15),"",SUMIFS(Table1[Amount $],Table1[Amount $],"<"&0,Table1[Merchant],Snapshot!AT15,Table1[Month],Snapshot!$W$4)*-1) | AV15: =IF(ISBLANK(AT15),"",COUNTIFS(Table1[Merchant],Snapshot!AT15,Table1[Month],Snapshot!$W$4)) | AW15: =IFERROR(RANK(AV15,$AV$6:$AV$200)+COUNTIF($AV$6:AV15,AV15)-1,"") | AX15: =IFERROR(RANK(AU15,$AU$6:$AU$200)+COUNTIF($AU$6:AU15,AU15)-1,"")
Q16: {=INDEX($AG$6:$AG$11,MATCH(4,$AF$6:$AF$11,0),0)} | S16: {=INDEX($AH$6:$AH$11,MATCH(4,$AF$6:$AF$11,0),0)} -> 0 | V16: =IF(ISBLANK(W16),"--",TEXT(W16,"mmmm")&" "&TEXT(W16,"YYYY")) -> -- | AC16: =IF(Categories!E17="Expense",Categories!D17,"--") -> Misc | AD16: =SUMIFS(Table1[Amount $],Table1[Category],Snapshot!AC16,Table1[Amount $],"<"&0,Table1[Month],Snapshot!$W$4)*-1 -> 0 | AE16: =RANK(AD16,$AD$6:$AD$35,0)+COUNTIF(AD$6:$AD16,AD16)-1 -> 11 | AJ16: =DATE(YEAR(AJ15),MONTH(AJ15),DAY(AJ15)+1) -> 36536 | AK16: =IF(MONTH(AK15)=MONTH(DATE(YEAR(AK15),MONTH(AK15),DAY(AK15)+1)),DATE(YEAR(AK15),MONTH(AK15),DAY(AK15)+1),NA()) -> #N/A | AL16: =SUMIFS(Table1[Amount $],Table1[Amount $],"<"&0,Table1[Category Type],"Expense",Table1[Date],Snapshot!AK16)*-1 -> 0 | AM16: =IF(AK16>TODAY(),NA(),SUM(AL$6:$AL16)) -> #N/A | AN16: =IF(OR(AK16=EOMONTH($AK$6,0),AK16=TODAY()),AM16,NA()) -> #N/A | AO16: =IF(MONTH(AO15)=MONTH(DATE(YEAR(AO15),MONTH(AO15),DAY(AO15)+1)),DATE(YEAR(AO15),MONTH(AO15),DAY(AO15)+1),NA()) -> #N/A | AP16: =SUMIFS(Table1[Amount $],Table1[Amount $],"<"&0,Table1[Category Type],"Expense",Table1[Date],Snapshot!AO16)*-1 -> 0 | AQ16: =IF(AO16<=EOMONTH($AO$6,0),SUM(AP$6:$AP16),NA()) -> #N/A | AR16: =IF(AO16=EOMONTH($AO$6,0),AQ16,NA()) -> #N/A | AU16: =IF(ISBLANK(AT16),"",SUMIFS(Table1[Amount $],Table1[Amount $],"<"&0,Table1[Merchant],Snapshot!AT16,Table1[Month],Snapshot!$W$4)*-1) | AV16: =IF(ISBLANK(AT16),"",COUNTIFS(Table1[Merchant],Snapshot!AT16,Table1[Month],Snapshot!$W$4)) | AW16: =IFERROR(RANK(AV16,$AV$6:$AV$200)+COUNTIF($AV$6:AV16,AV16)-1,"") | AX16: =IFERROR(RANK(AU16,$AU$6:$AU$200)+COUNTIF($AU$6:AU16,AU16)-1,"")
V17: =IF(ISBLANK(W17),"--",TEXT(W17,"mmmm")&" "&TEXT(W17,"YYYY")) -> -- | AC17: =IF(Categories!E18="Expense",Categories!D18,"--") -> Mortgage/Rent | AD17: =SUMIFS(Table1[Amount $],Table1[Category],Snapshot!AC17,Table1[Amount $],"<"&0,Table1[Month],Snapshot!$W$4)*-1 -> 0 | AE17: =RANK(AD17,$AD$6:$AD$35,0)+COUNTIF(AD$6:$AD17,AD17)-1 -> 12 | AJ17: =DATE(YEAR(AJ16),MONTH(AJ16),DAY(AJ16)+1) -> 36537 | AK17: =IF(MONTH(AK16)=MONTH(DATE(YEAR(AK16),MONTH(AK16),DAY(AK16)+1)),DATE(YEAR(AK16),MONTH(AK16),DAY(AK16)+1),NA()) -> #N/A | AL17: =SUMIFS(Table1[Amount $],Table1[Amount $],"<"&0,Table1[Category Type],"Expense",Table1[Date],Snapshot!AK17)*-1 -> 0 | AM17: =IF(AK17>TODAY(),NA(),SUM(AL$6:$AL17)) -> #N/A | AN17: =IF(OR(AK17=EOMONTH($AK$6,0),AK17=TODAY()),AM17,NA()) -> #N/A | AO17: =IF(MONTH(AO16)=MONTH(DATE(YEAR(AO16),MONTH(AO16),DAY(AO16)+1)),DATE(YEAR(AO16),MONTH(AO16),DAY(AO16)+1),NA()) -> #N/A | AP17: =SUMIFS(Table1[Amount $],Table1[Amount $],"<"&0,Table1[Category Type],"Expense",Table1[Date],Snapshot!AO17)*-1 -> 0 | AQ17: =IF(AO17<=EOMONTH($AO$6,0),SUM(AP$6:$AP17),NA()) -> #N/A | AR17: =IF(AO17=EOMONTH($AO$6,0),AQ17,NA()) -> #N/A | AU17: =IF(ISBLANK(AT17),"",SUMIFS(Table1[Amount $],Table1[Amount $],"<"&0,Table1[Merchant],Snapshot!AT17,Table1[Month],Snapshot!$W$4)*-1) | AV17: =IF(ISBLANK(AT17),"",COUNTIFS(Table1[Merchant],Snapshot!AT17,Table1[Month],Snapshot!$W$4)) | AW17: =IFERROR(RANK(AV17,$AV$6:$AV$200)+COUNTIF($AV$6:AV17,AV17)-1,"") | AX17: =IFERROR(RANK(AU17,$AU$6:$AU$200)+COUNTIF($AU$6:AU17,AU17)-1,"")
Q18: {=INDEX($AG$6:$AG$11,MATCH(5,$AF$6:$AF$11,0),0)} | S18: {=INDEX($AH$6:$AH$11,MATCH(5,$AF$6:$AF$11,0),0)} -> 0 | V18: =IF(ISBLANK(W18),"--",TEXT(W18,"mmmm")&" "&TEXT(W18,"YYYY")) -> -- | AC18: =IF(Categories!E19="Expense",Categories!D19,"--") -> Payment | AD18: =SUMIFS(Table1[Amount $],Table1[Category],Snapshot!AC18,Table1[Amount $],"<"&0,Table1[Month],Snapshot!$W$4)*-1 -> 0 | AE18: =RANK(AD18,$AD$6:$AD$35,0)+COUNTIF(AD$6:$AD18,AD18)-1 -> 13 | AJ18: =DATE(YEAR(AJ17),MONTH(AJ17),DAY(AJ17)+1) -> 36538 | AK18: =IF(MONTH(AK17)=MONTH(DATE(YEAR(AK17),MONTH(AK17),DAY(AK17)+1)),DATE(YEAR(AK17),MONTH(AK17),DAY(AK17)+1),NA()) -> #N/A | AL18: =SUMIFS(Table1[Amount $],Table1[Amount $],"<"&0,Table1[Category Type],"Expense",Table1[Date],Snapshot!AK18)*-1 -> 0 | AM18: =IF(AK18>TODAY(),NA(),SUM(AL$6:$AL18)) -> #N/A | AN18: =IF(OR(AK18=EOMONTH($AK$6,0),AK18=TODAY()),AM18,NA()) -> #N/A | AO18: =IF(MONTH(AO17)=MONTH(DATE(YEAR(AO17),MONTH(AO17),DAY(AO17)+1)),DATE(YEAR(AO17),MONTH(AO17),DAY(AO17)+1),NA()) -> #N/A | AP18: =SUMIFS(Table1[Amount $],Table1[Amount $],"<"&0,Table1[Category Type],"Expense",Table1[Date],Snapshot!AO18)*-1 -> 0 | AQ18: =IF(AO18<=EOMONTH($AO$6,0),SUM(AP$6:$AP18),NA()) -> #N/A | AR18: =IF(AO18=EOMONTH($AO$6,0),AQ18,NA()) -> #N/A | AU18: =IF(ISBLANK(AT18),"",SUMIFS(Table1[Amount $],Table1[Amount $],"<"&0,Table1[Merchant],Snapshot!AT18,Table1[Month],Snapshot!$W$4)*-1) | AV18: =IF(ISBLANK(AT18),"",COUNTIFS(Table1[Merchant],Snapshot!AT18,Table1[Month],Snapshot!$W$4)) | AW18: =IFERROR(RANK(AV18,$AV$6:$AV$200)+COUNTIF($AV$6:AV18,AV18)-1,"") | AX18: =IFERROR(RANK(AU18,$AU$6:$AU$200)+COUNTIF($AU$6:AU18,AU18)-1,"")
V19: =IF(ISBLANK(W19),"--",TEXT(W19,"mmmm")&" "&TEXT(W19,"YYYY")) -> -- | AC19: =IF(Categories!E20="Expense",Categories!D20,"--") -> Professional Services | AD19: =SUMIFS(Table1[Amount $],Table1[Category],Snapshot!AC19,Table1[Amount $],"<"&0,Table1[Month],Snapshot!$W$4)*-1 -> 0 | AE19: =RANK(AD19,$AD$6:$AD$35,0)+COUNTIF(AD$6:$AD19,AD19)-1 -> 14 | AJ19: =DATE(YEAR(AJ18),MONTH(AJ18),DAY(AJ18)+1) -> 36539 | AK19: =IF(MONTH(AK18)=MONTH(DATE(YEAR(AK18),MONTH(AK18),DAY(AK18)+1)),DATE(YEAR(AK18),MONTH(AK18),DAY(AK18)+1),NA()) -> #N/A | AL19: =SUMIFS(Table1[Amount $],Table1[Amount $],"<"&0,Table1[Category Type],"Expense",Table1[Date],Snapshot!AK19)*-1 -> 0 | AM19: =IF(AK19>TODAY(),NA(),SUM(AL$6:$AL19)) -> #N/A | AN19: =IF(OR(AK19=EOMONTH($AK$6,0),AK19=TODAY()),AM19,NA()) -> #N/A | AO19: =IF(MONTH(AO18)=MONTH(DATE(YEAR(AO18),MONTH(AO18),DAY(AO18)+1)),DATE(YEAR(AO18),MONTH(AO18),DAY(AO18)+1),NA()) -> #N/A | AP19: =SUMIFS(Table1[Amount $],Table1[Amount $],"<"&0,Table1[Category Type],"Expense",Table1[Date],Snapshot!AO19)*-1 -> 0 | AQ19: =IF(AO19<=EOMONTH($AO$6,0),SUM(AP$6:$AP19),NA()) -> #N/A | AR19: =IF(AO19=EOMONTH($AO$6,0),AQ19,NA()) -> #N/A | AU19: =IF(ISBLANK(AT19),"",SUMIFS(Table1[Amount $],Table1[Amount $],"<"&0,Table1[Merchant],Snapshot!AT19,Table1[Month],Snapshot!$W$4)*-1) | AV19: =IF(ISBLANK(AT19),"",COUNTIFS(Table1[Merchant],Snapshot!AT19,Table1[Month],Snapshot!$W$4)) | AW19: =IFERROR(RANK(AV19,$AV$6:$AV$200)+COUNTIF($AV$6:AV19,AV19)-1,"") | AX19: =IFERROR(RANK(AU19,$AU$6:$AU$200)+COUNTIF($AU$6:AU19,AU19)-1,"")
Q20: {=INDEX($AG$6:$AG$11,MATCH(6,$AF$6:$AF$11,0),0)} | S20: {=INDEX($AH$6:$AH$11,MATCH(6,$AF$6:$AF$11,0),0)} -> 0 | V20: =IF(ISBLANK(W20),"--",TEXT(W20,"mmmm")&" "&TEXT(W20,"YYYY")) -> -- | AC20: =IF(Categories!E21="Expense",Categories!D21,"--") -> Restaurants/Dining | AD20: =SUMIFS(Table1[Amount $],Table1[Category],Snapshot!AC20,Table1[Amount $],"<"&0,Table1[Month],Snapshot!$W$4)*-1 -> 0 | AE20: =RANK(AD20,$AD$6:$AD$35,0)+COUNTIF(AD$6:$AD20,AD20)-1 -> 15 | AJ20: =DATE(YEAR(AJ19),MONTH(AJ19),DAY(AJ19)+1) -> 36540 | AK20: =IF(MONTH(AK19)=MONTH(DATE(YEAR(AK19),MONTH(AK19),DAY(AK19)+1)),DATE(YEAR(AK19),MONTH(AK19),DAY(AK19)+1),NA()) -> #N/A | AL20: =SUMIFS(Table1[Amount $],Table1[Amount $],"<"&0,Table1[Category Type],"Expense",Table1[Date],Snapshot!AK20)*-1 -> 0 | AM20: =IF(AK20>TODAY(),NA(),SUM(AL$6:$AL20)) -> #N/A | AN20: =IF(OR(AK20=EOMONTH($AK$6,0),AK20=TODAY()),AM20,NA()) -> #N/A | AO20: =IF(MONTH(AO19)=MONTH(DATE(YEAR(AO19),MONTH(AO19),DAY(AO19)+1)),DATE(YEAR(AO19),MONTH(AO19),DAY(AO19)+1),NA()) -> #N/A | AP20: =SUMIFS(Table1[Amount $],Table1[Amount $],"<"&0,Table1[Category Type],"Expense",Table1[Date],Snapshot!AO20)*-1 -> 0 | AQ20: =IF(AO20<=EOMONTH($AO$6,0),SUM(AP$6:$AP20),NA()) -> #N/A | AR20: =IF(AO20=EOMONTH($AO$6,0),AQ20,NA()) -> #N/A | AU20: =IF(ISBLANK(AT20),"",SUMIFS(Table1[Amount $],Table1[Amount $],"<"&0,Table1[Merchant],Snapshot!AT20,Table1[Month],Snapshot!$W$4)*-1) | AV20: =IF(ISBLANK(AT20),"",COUNTIFS(Table1[Merchant],Snapshot!AT20,Table1[Month],Snapshot!$W$4)) | AW20: =IFERROR(RANK(AV20,$AV$6:$AV$200)+COUNTIF($AV$6:AV20,AV20)-1,"") | AX20: =IFERROR(RANK(AU20,$AU$6:$AU$200)+COUNTIF($AU$6:AU20,AU20)-1,"")
V21: =IF(ISBLANK(W21),"--",TEXT(W21,"mmmm")&" "&TEXT(W21,"YYYY")) -> -- | AC21: =IF(Categories!E22="Expense",Categories!D22,"--") -> Shopping | AD21: =SUMIFS(Table1[Amount $],Table1[Category],Snapshot!AC21,Table1[Amount $],"<"&0,Table1[Month],Snapshot!$W$4)*-1 -> 0 | AE21: =RANK(AD21,$AD$6:$AD$35,0)+COUNTIF(AD$6:$AD21,AD21)-1 -> 16 | AJ21: =DATE(YEAR(AJ20),MONTH(AJ20),DAY(AJ20)+1) -> 36541 | AK21: =IF(MONTH(AK20)=MONTH(DATE(YEAR(AK20),MONTH(AK20),DAY(AK20)+1)),DATE(YEAR(AK20),MONTH(AK20),DAY(AK20)+1),NA()) -> #N/A | AL21: =SUMIFS(Table1[Amount $],Table1[Amount $],"<"&0,Table1[Category Type],"Expense",Table1[Date],Snapshot!AK21)*-1 -> 0 | AM21: =IF(AK21>TODAY(),NA(),SUM(AL$6:$AL21)) -> #N/A | AN21: =IF(OR(AK21=EOMONTH($AK$6,0),AK21=TODAY()),AM21,NA()) -> #N/A | AO21: =IF(MONTH(AO20)=MONTH(DATE(YEAR(AO20),MONTH(AO20),DAY(AO20)+1)),DATE(YEAR(AO20),MONTH(AO20),DAY(AO20)+1),NA()) -> #N/A | AP21: =SUMIFS(Table1[Amount $],Table1[Amount $],"<"&0,Table1[Category Type],"Expense",Table1[Date],Snapshot!AO21)*-1 -> 0 | AQ21: =IF(AO21<=EOMONTH($AO$6,0),SUM(AP$6:$AP21),NA()) -> #N/A | AR21: =IF(AO21=EOMONTH($AO$6,0),AQ21,NA()) -> #N/A | AU21: =IF(ISBLANK(AT21),"",SUMIFS(Table1[Amount $],Table1[Amount $],"<"&0,Table1[Merchant],Snapshot!AT21,Table1[Month],Snapshot!$W$4)*-1) | AV21: =IF(ISBLANK(AT21),"",COUNTIFS(Table1[Merchant],Snapshot!AT21,Table1[Month],Snapshot!$W$4)) | AW21: =IFERROR(RANK(AV21,$AV$6:$AV$200)+COUNTIF($AV$6:AV21,AV21)-1,"") | AX21: =IFERROR(RANK(AU21,$AU$6:$AU$200)+COUNTIF($AU$6:AU21,AU21)-1,"")
P22: Total spending | S22: =S10+S12+S14+S16+S18+S20 -> 0 | V22: =IF(ISBLANK(W22),"--",TEXT(W22,"mmmm")&" "&TEXT(W22,"YYYY")) -> -- | AC22: =IF(Categories!E23="Expense",Categories!D23,"--") -> Travel | AD22: =SUMIFS(Table1[Amount $],Table1[Category],Snapshot!AC22,Table1[Amount $],"<"&0,Table1[Month],Snapshot!$W$4)*-1 -> 0 | AE22: =RANK(AD22,$AD$6:$AD$35,0)+COUNTIF(AD$6:$AD22,AD22)-1 -> 17 | AJ22: =DATE(YEAR(AJ21),MONTH(AJ21),DAY(AJ21)+1) -> 36542 | AK22: =IF(MONTH(AK21)=MONTH(DATE(YEAR(AK21),MONTH(AK21),DAY(AK21)+1)),DATE(YEAR(AK21),MONTH(AK21),DAY(AK21)+1),NA()) -> #N/A | AL22: =SUMIFS(Table1[Amount $],Table1[Amount $],"<"&0,Table1[Category Type],"Expense",Table1[Date],Snapshot!AK22)*-1 -> 0 | AM22: =IF(AK22>TODAY(),NA(),SUM(AL$6:$AL22)) -> #N/A | AN22: =IF(OR(AK22=EOMONTH($AK$6,0),AK22=TODAY()),AM22,NA()) -> #N/A | AO22: =IF(MONTH(AO21)=MONTH(DATE(YEAR(AO21),MONTH(AO21),DAY(AO21)+1)),DATE(YEAR(AO21),MONTH(AO21),DAY(AO21)+1),NA()) -> #N/A | AP22: =SUMIFS(Table1[Amount $],Table1[Amount $],"<"&0,Table1[Category Type],"Expense",Table1[Date],Snapshot!AO22)*-1 -> 0 | AQ22: =IF(AO22<=EOMONTH($AO$6,0),SUM(AP$6:$AP22),NA()) -> #N/A | AR22: =IF(AO22=EOMONTH($AO$6,0),AQ22,NA()) -> #N/A | AU22: =IF(ISBLANK(AT22),"",SUMIFS(Table1[Amount $],Table1[Amount $],"<"&0,Table1[Merchant],Snapshot!AT22,Table1[Month],Snapshot!$W$4)*-1) | AV22: =IF(ISBLANK(AT22),"",COUNTIFS(Table1[Merchant],Snapshot!AT22,Table1[Month],Snapshot!$W$4)) | AW22: =IFERROR(RANK(AV22,$AV$6:$AV$200)+COUNTIF($AV$6:AV22,AV22)-1,"") | AX22: =IFERROR(RANK(AU22,$AU$6:$AU$200)+COUNTIF($AU$6:AU22,AU22)-1,"")
V23: =IF(ISBLANK(W23),"--",TEXT(W23,"mmmm")&" "&TEXT(W23,"YYYY")) -> -- | AC23: =IF(Categories!E24="Expense",Categories!D24,"--") -> Uncategorized | AD23: =SUMIFS(Table1[Amount $],Table1[Category],Snapshot!AC23,Table1[Amount $],"<"&0,Table1[Month],Snapshot!$W$4)*-1 -> 0 | AE23: =RANK(AD23,$AD$6:$AD$35,0)+COUNTIF(AD$6:$AD23,AD23)-1 -> 18 | AJ23: =DATE(YEAR(AJ22),MONTH(AJ22),DAY(AJ22)+1) -> 36543 | AK23: =IF(MONTH(AK22)=MONTH(DATE(YEAR(AK22),MONTH(AK22),DAY(AK22)+1)),DATE(YEAR(AK22),MONTH(AK22),DAY(AK22)+1),NA()) -> #N/A | AL23: =SUMIFS(Table1[Amount $],Table1[Amount $],"<"&0,Table1[Category Type],"Expense",Table1[Date],Snapshot!AK23)*-1 -> 0 | AM23: =IF(AK23>TODAY(),NA(),SUM(AL$6:$AL23)) -> #N/A | AN23: =IF(OR(AK23=EOMONTH($AK$6,0),AK23=TODAY()),AM23,NA()) -> #N/A | AO23: =IF(MONTH(AO22)=MONTH(DATE(YEAR(AO22),MONTH(AO22),DAY(AO22)+1)),DATE(YEAR(AO22),MONTH(AO22),DAY(AO22)+1),NA()) -> #N/A | AP23: =SUMIFS(Table1[Amount $],Table1[Amount $],"<"&0,Table1[Category Type],"Expense",Table1[Date],Snapshot!AO23)*-1 -> 0 | AQ23: =IF(AO23<=EOMONTH($AO$6,0),SUM(AP$6:$AP23),NA()) -> #N/A | AR23: =IF(AO23=EOMONTH($AO$6,0),AQ23,NA()) -> #N/A | AU23: =IF(ISBLANK(AT23),"",SUMIFS(Table1[Amount $],Table1[Amount $],"<"&0,Table1[Merchant],Snapshot!AT23,Table1[Month],Snapshot!$W$4)*-1) | AV23: =IF(ISBLANK(AT23),"",COUNTIFS(Table1[Merchant],Snapshot!AT23,Table1[Month],Snapshot!$W$4)) | AW23: =IFERROR(RANK(AV23,$AV$6:$AV$200)+COUNTIF($AV$6:AV23,AV23)-1,"") | AX23: =IFERROR(RANK(AU23,$AU$6:$AU$200)+COUNTIF($AU$6:AU23,AU23)-1,"")
V24: =IF(ISBLANK(W24),"--",TEXT(W24,"mmmm")&" "&TEXT(W24,"YYYY")) -> -- | AC24: =IF(Categories!E25="Expense",Categories!D25,"--") -> -- | AD24: =SUMIFS(Table1[Amount $],Table1[Category],Snapshot!AC24,Table1[Amount $],"<"&0,Table1[Month],Snapshot!$W$4)*-1 -> 0 | AE24: =RANK(AD24,$AD$6:$AD$35,0)+COUNTIF(AD$6:$AD24,AD24)-1 -> 19 | AJ24: =DATE(YEAR(AJ23),MONTH(AJ23),DAY(AJ23)+1) -> 36544 | AK24: =IF(MONTH(AK23)=MONTH(DATE(YEAR(AK23),MONTH(AK23),DAY(AK23)+1)),DATE(YEAR(AK23),MONTH(AK23),DAY(AK23)+1),NA()) -> #N/A | AL24: =SUMIFS(Table1[Amount $],Table1[Amount $],"<"&0,Table1[Category Type],"Expense",Table1[Date],Snapshot!AK24)*-1 -> 0 | AM24: =IF(AK24>TODAY(),NA(),SUM(AL$6:$AL24)) -> #N/A | AN24: =IF(OR(AK24=EOMONTH($AK$6,0),AK24=TODAY()),AM24,NA()) -> #N/A | AO24: =IF(MONTH(AO23)=MONTH(DATE(YEAR(AO23),MONTH(AO23),DAY(AO23)+1)),DATE(YEAR(AO23),MONTH(AO23),DAY(AO23)+1),NA()) -> #N/A | AP24: =SUMIFS(Table1[Amount $],Table1[Amount $],"<"&0,Table1[Category Type],"Expense",Table1[Date],Snapshot!AO24)*-1 -> 0 | AQ24: =IF(AO24<=EOMONTH($AO$6,0),SUM(AP$6:$AP24),NA()) -> #N/A | AR24: =IF(AO24=EOMONTH($AO$6,0),AQ24,NA()) -> #N/A | AU24: =IF(ISBLANK(AT24),"",SUMIFS(Table1[Amount $],Table1[Amount $],"<"&0,Table1[Merchant],Snapshot!AT24,Table1[Month],Snapshot!$W$4)*-1) | AV24: =IF(ISBLANK(AT24),"",COUNTIFS(Table1[Merchant],Snapshot!AT24,Table1[Month],Snapshot!$W$4)) | AW24: =IFERROR(RANK(AV24,$AV$6:$AV$200)+COUNTIF($AV$6:AV24,AV24)-1,"") | AX24: =IFERROR(RANK(AU24,$AU$6:$AU$200)+COUNTIF($AU$6:AU24,AU24)-1,"")
V25: =IF(ISBLANK(W25),"--",TEXT(W25,"mmmm")&" "&TEXT(W25,"YYYY")) -> -- | AC25: =IF(Categories!E26="Expense",Categories!D26,"--") -> -- | AD25: =SUMIFS(Table1[Amount $],Table1[Category],Snapshot!AC25,Table1[Amount $],"<"&0,Table1[Month],Snapshot!$W$4)*-1 -> 0 | AE25: =RANK(AD25,$AD$6:$AD$35,0)+COUNTIF(AD$6:$AD25,AD25)-1 -> 20 | AJ25: =DATE(YEAR(AJ24),MONTH(AJ24),DAY(AJ24)+1) -> 36545 | AK25: =IF(MONTH(AK24)=MONTH(DATE(YEAR(AK24),MONTH(AK24),DAY(AK24)+1)),DATE(YEAR(AK24),MONTH(AK24),DAY(AK24)+1),NA()) -> #N/A | AL25: =SUMIFS(Table1[Amount $],Table1[Amount $],"<"&0,Table1[Category Type],"Expense",Table1[Date],Snapshot!AK25)*-1 -> 0 | AM25: =IF(AK25>TODAY(),NA(),SUM(AL$6:$AL25)) -> #N/A | AN25: =IF(OR(AK25=EOMONTH($AK$6,0),AK25=TODAY()),AM25,NA()) -> #N/A | AO25: =IF(MONTH(AO24)=MONTH(DATE(YEAR(AO24),MONTH(AO24),DAY(AO24)+1)),DATE(YEAR(AO24),MONTH(AO24),DAY(AO24)+1),NA()) -> #N/A | AP25: =SUMIFS(Table1[Amount $],Table1[Amount $],"<"&0,Table1[Category Type],"Expense",Table1[Date],Snapshot!AO25)*-1 -> 0 | AQ25: =IF(AO25<=EOMONTH($AO$6,0),SUM(AP$6:$AP25),NA()) -> #N/A | AR25: =IF(AO25=EOMONTH($AO$6,0),AQ25,NA()) -> #N/A | AU25: =IF(ISBLANK(AT25),"",SUMIFS(Table1[Amount $],Table1[Amount $],"<"&0,Table1[Merchant],Snapshot!AT25,Table1[Month],Snapshot!$W$4)*-1) | AV25: =IF(ISBLANK(AT25),"",COUNTIFS(Table1[Merchant],Snapshot!AT25,Table1[Month],Snapshot!$W$4)) | AW25: =IFERROR(RANK(AV25,$AV$6:$AV$200)+COUNTIF($AV$6:AV25,AV25)-1,"") | AX25: =IFERROR(RANK(AU25,$AU$6:$AU$200)+COUNTIF($AU$6:AU25,AU25)-1,"")
V26: =IF(ISBLANK(W26),"--",TEXT(W26,"mmmm")&" "&TEXT(W26,"YYYY")) -> -- | AC26: =IF(Categories!E27="Expense",Categories!D27,"--") -> -- | AD26: =SUMIFS(Table1[Amount $],Table1[Category],Snapshot!AC26,Table1[Amount $],"<"&0,Table1[Month],Snapshot!$W$4)*-1 -> 0 | AE26: =RANK(AD26,$AD$6:$AD$35,0)+COUNTIF(AD$6:$AD26,AD26)-1 -> 21 | AJ26: =DATE(YEAR(AJ25),MONTH(AJ25),DAY(AJ25)+1) -> 36546 | AK26: =IF(MONTH(AK25)=MONTH(DATE(YEAR(AK25),MONTH(AK25),DAY(AK25)+1)),DATE(YEAR(AK25),MONTH(AK25),DAY(AK25)+1),NA()) -> #N/A | AL26: =SUMIFS(Table1[Amount $],Table1[Amount $],"<"&0,Table1[Category Type],"Expense",Table1[Date],Snapshot!AK26)*-1 -> 0 | AM26: =IF(AK26>TODAY(),NA(),SUM(AL$6:$AL26)) -> #N/A | AN26: =IF(OR(AK26=EOMONTH($AK$6,0),AK26=TODAY()),AM26,NA()) -> #N/A | AO26: =IF(MONTH(AO25)=MONTH(DATE(YEAR(AO25),MONTH(AO25),DAY(AO25)+1)),DATE(YEAR(AO25),MONTH(AO25),DAY(AO25)+1),NA()) -> #N/A | AP26: =SUMIFS(Table1[Amount $],Table1[Amount $],"<"&0,Table1[Category Type],"Expense",Table1[Date],Snapshot!AO26)*-1 -> 0 | AQ26: =IF(AO26<=EOMONTH($AO$6,0),SUM(AP$6:$AP26),NA()) -> #N/A | AR26: =IF(AO26=EOMONTH($AO$6,0),AQ26,NA()) -> #N/A | AU26: =IF(ISBLANK(AT26),"",SUMIFS(Table1[Amount $],Table1[Amount $],"<"&0,Table1[Merchant],Snapshot!AT26,Table1[Month],Snapshot!$W$4)*-1) | AV26: =IF(ISBLANK(AT26),"",COUNTIFS(Table1[Merchant],Snapshot!AT26,Table1[Month],Snapshot!$W$4)) | AW26: =IFERROR(RANK(AV26,$AV$6:$AV$200)+COUNTIF($AV$6:AV26,AV26)-1,"") | AX26: =IFERROR(RANK(AU26,$AU$6:$AU$200)+COUNTIF($AU$6:AU26,AU26)-1,"")
D27: Cumulative spending throughout month | V27: =IF(ISBLANK(W27),"--",TEXT(W27,"mmmm")&" "&TEXT(W27,"YYYY")) -> -- | AC27: =IF(Categories!E28="Expense",Categories!D28,"--") -> -- | AD27: =SUMIFS(Table1[Amount $],Table1[Category],Snapshot!AC27,Table1[Amount $],"<"&0,Table1[Month],Snapshot!$W$4)*-1 -> 0 | AE27: =RANK(AD27,$AD$6:$AD$35,0)+COUNTIF(AD$6:$AD27,AD27)-1 -> 22 | AJ27: =DATE(YEAR(AJ26),MONTH(AJ26),DAY(AJ26)+1) -> 36547 | AK27: =IF(MONTH(AK26)=MONTH(DATE(YEAR(AK26),MONTH(AK26),DAY(AK26)+1)),DATE(YEAR(AK26),MONTH(AK26),DAY(AK26)+1),NA()) -> #N/A | AL27: =SUMIFS(Table1[Amount $],Table1[Amount $],"<"&0,Table1[Category Type],"Expense",Table1[Date],Snapshot!AK27)*-1 -> 0 | AM27: =IF(AK27>TODAY(),NA(),SUM(AL$6:$AL27)) -> #N/A | AN27: =IF(OR(AK27=EOMONTH($AK$6,0),AK27=TODAY()),AM27,NA()) -> #N/A | AO27: =IF(MONTH(AO26)=MONTH(DATE(YEAR(AO26),MONTH(AO26),DAY(AO26)+1)),DATE(YEAR(AO26),MONTH(AO26),DAY(AO26)+1),NA()) -> #N/A | AP27: =SUMIFS(Table1[Amount $],Table1[Amount $],"<"&0,Table1[Category Type],"Expense",Table1[Date],Snapshot!AO27)*-1 -> 0 | AQ27: =IF(AO27<=EOMONTH($AO$6,0),SUM(AP$6:$AP27),NA()) -> #N/A | AR27: =IF(AO27=EOMONTH($AO$6,0),AQ27,NA()) -> #N/A | AU27: =IF(ISBLANK(AT27),"",SUMIFS(Table1[Amount $],Table1[Amount $],"<"&0,Table1[Merchant],Snapshot!AT27,Table1[Month],Snapshot!$W$4)*-1) | AV27: =IF(ISBLANK(AT27),"",COUNTIFS(Table1[Merchant],Snapshot!AT27,Table1[Month],Snapshot!$W$4)) | AW27: =IFERROR(RANK(AV27,$AV$6:$AV$200)+COUNTIF($AV$6:AV27,AV27)-1,"") | AX27: =IFERROR(RANK(AU27,$AU$6:$AU$200)+COUNTIF($AU$6:AU27,AU27)-1,"")
D28: =IFERROR(IF(AND(MONTH(W4)=MONTH(TODAY()),YEAR(W4)=YEAR(TODAY())),AK39,AK42),"") | V28: =IF(ISBLANK(W28),"--",TEXT(W28,"mmmm")&" "&TEXT(W28,"YYYY")) -> -- | AC28: =IF(Categories!E29="Expense",Categories!D29,"--") -> -- | AD28: =SUMIFS(Table1[Amount $],Table1[Category],Snapshot!AC28,Table1[Amount $],"<"&0,Table1[Month],Snapshot!$W$4)*-1 -> 0 | AE28: =RANK(AD28,$AD$6:$AD$35,0)+COUNTIF(AD$6:$AD28,AD28)-1 -> 23 | AJ28: =DATE(YEAR(AJ27),MONTH(AJ27),DAY(AJ27)+1) -> 36548 | AK28: =IF(MONTH(AK27)=MONTH(DATE(YEAR(AK27),MONTH(AK27),DAY(AK27)+1)),DATE(YEAR(AK27),MONTH(AK27),DAY(AK27)+1),NA()) -> #N/A | AL28: =SUMIFS(Table1[Amount $],Table1[Amount $],"<"&0,Table1[Category Type],"Expense",Table1[Date],Snapshot!AK28)*-1 -> 0 | AM28: =IF(AK28>TODAY(),NA(),SUM(AL$6:$AL28)) -> #N/A | AN28: =IF(OR(AK28=EOMONTH($AK$6,0),AK28=TODAY()),AM28,NA()) -> #N/A | AO28: =IF(MONTH(AO27)=MONTH(DATE(YEAR(AO27),MONTH(AO27),DAY(AO27)+1)),DATE(YEAR(AO27),MONTH(AO27),DAY(AO27)+1),NA()) -> #N/A | AP28: =SUMIFS(Table1[Amount $],Table1[Amount $],"<"&0,Table1[Category Type],"Expense",Table1[Date],Snapshot!AO28)*-1 -> 0 | AQ28: =IF(AO28<=EOMONTH($AO$6,0),SUM(AP$6:$AP28),NA()) -> #N/A | AR28: =IF(AO28=EOMONTH($AO$6,0),AQ28,NA()) -> #N/A | AU28: =IF(ISBLANK(AT28),"",SUMIFS(Table1[Amount $],Table1[Amount $],"<"&0,Table1[Merchant],Snapshot!AT28,Table1[Month],Snapshot!$W$4)*-1) | AV28: =IF(ISBLANK(AT28),"",COUNTIFS(Table1[Merchant],Snapshot!AT28,Table1[Month],Snapshot!$W$4)) | AW28: =IFERROR(RANK(AV28,$AV$6:$AV$200)+COUNTIF($AV$6:AV28,AV28)-1,"") | AX28: =IFERROR(RANK(AU28,$AU$6:$AU$200)+COUNTIF($AU$6:AU28,AU28)-1,"")
V29: =IF(ISBLANK(W29),"--",TEXT(W29,"mmmm")&" "&TEXT(W29,"YYYY")) -> -- | AC29: =IF(Categories!E30="Expense",Categories!D30,"--") -> -- | AD29: =SUMIFS(Table1[Amount $],Table1[Category],Snapshot!AC29,Table1[Amount $],"<"&0,Table1[Month],Snapshot!$W$4)*-1 -> 0 | AE29: =RANK(AD29,$AD$6:$AD$35,0)+COUNTIF(AD$6:$AD29,AD29)-1 -> 24 | AJ29: =DATE(YEAR(AJ28),MONTH(AJ28),DAY(AJ28)+1) -> 36549 | AK29: =IF(MONTH(AK28)=MONTH(DATE(YEAR(AK28),MONTH(AK28),DAY(AK28)+1)),DATE(YEAR(AK28),MONTH(AK28),DAY(AK28)+1),NA()) -> #N/A | AL29: =SUMIFS(Table1[Amount $],Table1[Amount $],"<"&0,Table1[Category Type],"Expense",Table1[Date],Snapshot!AK29)*-1 -> 0 | AM29: =IF(AK29>TODAY(),NA(),SUM(AL$6:$AL29)) -> #N/A | AN29: =IF(OR(AK29=EOMONTH($AK$6,0),AK29=TODAY()),AM29,NA()) -> #N/A | AO29: =IF(MONTH(AO28)=MONTH(DATE(YEAR(AO28),MONTH(AO28),DAY(AO28)+1)),DATE(YEAR(AO28),MONTH(AO28),DAY(AO28)+1),NA()) -> #N/A | AP29: =SUMIFS(Table1[Amount $],Table1[Amount $],"<"&0,Table1[Category Type],"Expense",Table1[Date],Snapshot!AO29)*-1 -> 0 | AQ29: =IF(AO29<=EOMONTH($AO$6,0),SUM(AP$6:$AP29),NA()) -> #N/A | AR29: =IF(AO29=EOMONTH($AO$6,0),AQ29,NA()) -> #N/A | AU29: =IF(ISBLANK(AT29),"",SUMIFS(Table1[Amount $],Table1[Amount $],"<"&0,Table1[Merchant],Snapshot!AT29,Table1[Month],Snapshot!$W$4)*-1) | AV29: =IF(ISBLANK(AT29),"",COUNTIFS(Table1[Merchant],Snapshot!AT29,Table1[Month],Snapshot!$W$4)) | AW29: =IFERROR(RANK(AV29,$AV$6:$AV$200)+COUNTIF($AV$6:AV29,AV29)-1,"") | AX29: =IFERROR(RANK(AU29,$AU$6:$AU$200)+COUNTIF($AU$6:AU29,AU29)-1,"")
V30: =IF(ISBLANK(W30),"--",TEXT(W30,"mmmm")&" "&TEXT(W30,"YYYY")) -> -- | AC30: =IF(Categories!E31="Expense",Categories!D31,"--") -> -- | AD30: =SUMIFS(Table1[Amount $],Table1[Category],Snapshot!AC30,Table1[Amount $],"<"&0,Table1[Month],Snapshot!$W$4)*-1 -> 0 | AE30: =RANK(AD30,$AD$6:$AD$35,0)+COUNTIF(AD$6:$AD30,AD30)-1 -> 25 | AJ30: =DATE(YEAR(AJ29),MONTH(AJ29),DAY(AJ29)+1) -> 36550 | AK30: =IF(MONTH(AK29)=MONTH(DATE(YEAR(AK29),MONTH(AK29),DAY(AK29)+1)),DATE(YEAR(AK29),MONTH(AK29),DAY(AK29)+1),NA()) -> #N/A | AL30: =SUMIFS(Table1[Amount $],Table1[Amount $],"<"&0,Table1[Category Type],"Expense",Table1[Date],Snapshot!AK30)*-1 -> 0 | AM30: =IF(AK30>TODAY(),NA(),SUM(AL$6:$AL30)) -> #N/A | AN30: =IF(OR(AK30=EOMONTH($AK$6,0),AK30=TODAY()),AM30,NA()) -> #N/A | AO30: =IF(MONTH(AO29)=MONTH(DATE(YEAR(AO29),MONTH(AO29),DAY(AO29)+1)),DATE(YEAR(AO29),MONTH(AO29),DAY(AO29)+1),NA()) -> #N/A | AP30: =SUMIFS(Table1[Amount $],Table1[Amount $],"<"&0,Table1[Category Type],"Expense",Table1[Date],Snapshot!AO30)*-1 -> 0 | AQ30: =IF(AO30<=EOMONTH($AO$6,0),SUM(AP$6:$AP30),NA()) -> #N/A | AR30: =IF(AO30=EOMONTH($AO$6,0),AQ30,NA()) -> #N/A | AU30: =IF(ISBLANK(AT30),"",SUMIFS(Table1[Amount $],Table1[Amount $],"<"&0,Table1[Merchant],Snapshot!AT30,Table1[Month],Snapshot!$W$4)*-1) | AV30: =IF(ISBLANK(AT30),"",COUNTIFS(Table1[Merchant],Snapshot!AT30,Table1[Month],Snapshot!$W$4)) | AW30: =IFERROR(RANK(AV30,$AV$6:$AV$200)+COUNTIF($AV$6:AV30,AV30)-1,"") | AX30: =IFERROR(RANK(AU30,$AU$6:$AU$200)+COUNTIF($AU$6:AU30,AU30)-1,"")
V31: =IF(ISBLANK(W31),"--",TEXT(W31,"mmmm")&" "&TEXT(W31,"YYYY")) -> -- | AC31: =IF(Categories!E32="Expense",Categories!D32,"--") -> -- | AD31: =SUMIFS(Table1[Amount $],Table1[Category],Snapshot!AC31,Table1[Amount $],"<"&0,Table1[Month],Snapshot!$W$4)*-1 -> 0 | AE31: =RANK(AD31,$AD$6:$AD$35,0)+COUNTIF(AD$6:$AD31,AD31)-1 -> 26 | AJ31: =DATE(YEAR(AJ30),MONTH(AJ30),DAY(AJ30)+1) -> 36551 | AK31: =IF(MONTH(AK30)=MONTH(DATE(YEAR(AK30),MONTH(AK30),DAY(AK30)+1)),DATE(YEAR(AK30),MONTH(AK30),DAY(AK30)+1),NA()) -> #N/A | AL31: =SUMIFS(Table1[Amount $],Table1[Amount $],"<"&0,Table1[Category Type],"Expense",Table1[Date],Snapshot!AK31)*-1 -> 0 | AM31: =IF(AK31>TODAY(),NA(),SUM(AL$6:$AL31)) -> #N/A | AN31: =IF(OR(AK31=EOMONTH($AK$6,0),AK31=TODAY()),AM31,NA()) -> #N/A | AO31: =IF(MONTH(AO30)=MONTH(DATE(YEAR(AO30),MONTH(AO30),DAY(AO30)+1)),DATE(YEAR(AO30),MONTH(AO30),DAY(AO30)+1),NA()) -> #N/A | AP31: =SUMIFS(Table1[Amount $],Table1[Amount $],"<"&0,Table1[Category Type],"Expense",Table1[Date],Snapshot!AO31)*-1 -> 0 | AQ31: =IF(AO31<=EOMONTH($AO$6,0),SUM(AP$6:$AP31),NA()) -> #N/A | AR31: =IF(AO31=EOMONTH($AO$6,0),AQ31,NA()) -> #N/A | AU31: =IF(ISBLANK(AT31),"",SUMIFS(Table1[Amount $],Table1[Amount $],"<"&0,Table1[Merchant],Snapshot!AT31,Table1[Month],Snapshot!$W$4)*-1) | AV31: =IF(ISBLANK(AT31),"",COUNTIFS(Table1[Merchant],Snapshot!AT31,Table1[Month],Snapshot!$W$4)) | AW31: =IFERROR(RANK(AV31,$AV$6:$AV$200)+COUNTIF($AV$6:AV31,AV31)-1,"") | AX31: =IFERROR(RANK(AU31,$AU$6:$AU$200)+COUNTIF($AU$6:AU31,AU31)-1,"")
V32: =IF(ISBLANK(W32),"--",TEXT(W32,"mmmm")&" "&TEXT(W32,"YYYY")) -> -- | AC32: =IF(Categories!E33="Expense",Categories!D33,"--") -> -- | AD32: =SUMIFS(Table1[Amount $],Table1[Category],Snapshot!AC32,Table1[Amount $],"<"&0,Table1[Month],Snapshot!$W$4)*-1 -> 0 | AE32: =RANK(AD32,$AD$6:$AD$35,0)+COUNTIF(AD$6:$AD32,AD32)-1 -> 27 | AJ32: =DATE(YEAR(AJ31),MONTH(AJ31),DAY(AJ31)+1) -> 36552 | AK32: =IF(MONTH(AK31)=MONTH(DATE(YEAR(AK31),MONTH(AK31),DAY(AK31)+1)),DATE(YEAR(AK31),MONTH(AK31),DAY(AK31)+1),NA()) -> #N/A | AL32: =SUMIFS(Table1[Amount $],Table1[Amount $],"<"&0,Table1[Category Type],"Expense",Table1[Date],Snapshot!AK32)*-1 -> 0 | AM32: =IF(AK32>TODAY(),NA(),SUM(AL$6:$AL32)) -> #N/A | AN32: =IF(OR(AK32=EOMONTH($AK$6,0),AK32=TODAY()),AM32,NA()) -> #N/A | AO32: =IF(MONTH(AO31)=MONTH(DATE(YEAR(AO31),MONTH(AO31),DAY(AO31)+1)),DATE(YEAR(AO31),MONTH(AO31),DAY(AO31)+1),NA()) -> #N/A | AP32: =SUMIFS(Table1[Amount $],Table1[Amount $],"<"&0,Table1[Category Type],"Expense",Table1[Date],Snapshot!AO32)*-1 -> 0 | AQ32: =IF(AO32<=EOMONTH($AO$6,0),SUM(AP$6:$AP32),NA()) -> #N/A | AR32: =IF(AO32=EOMONTH($AO$6,0),AQ32,NA()) -> #N/A | AU32: =IF(ISBLANK(AT32),"",SUMIFS(Table1[Amount $],Table1[Amount $],"<"&0,Table1[Merchant],Snapshot!AT32,Table1[Month],Snapshot!$W$4)*-1) | AV32: =IF(ISBLANK(AT32),"",COUNTIFS(Table1[Merchant],Snapshot!AT32,Table1[Month],Snapshot!$W$4)) | AW32: =IFERROR(RANK(AV32,$AV$6:$AV$200)+COUNTIF($AV$6:AV32,AV32)-1,"") | AX32: =IFERROR(RANK(AU32,$AU$6:$AU$200)+COUNTIF($AU$6:AU32,AU32)-1,"")
V33: =IF(ISBLANK(W33),"--",TEXT(W33,"mmmm")&" "&TEXT(W33,"YYYY")) -> -- | AC33: =IF(Categories!E34="Expense",Categories!D34,"--") -> -- | AD33: =SUMIFS(Table1[Amount $],Table1[Category],Snapshot!AC33,Table1[Amount $],"<"&0,Table1[Month],Snapshot!$W$4)*-1 -> 0 | AE33: =RANK(AD33,$AD$6:$AD$35,0)+COUNTIF(AD$6:$AD33,AD33)-1 -> 28 | AJ33: =DATE(YEAR(AJ32),MONTH(AJ32),DAY(AJ32)+1) -> 36553 | AK33: =IF(MONTH(AK32)=MONTH(DATE(YEAR(AK32),MONTH(AK32),DAY(AK32)+1)),DATE(YEAR(AK32),MONTH(AK32),DAY(AK32)+1),NA()) -> #N/A | AL33: =SUMIFS(Table1[Amount $],Table1[Amount $],"<"&0,Table1[Category Type],"Expense",Table1[Date],Snapshot!AK33)*-1 -> 0 | AM33: =IF(AK33>TODAY(),NA(),SUM(AL$6:$AL33)) -> #N/A | AN33: =IF(OR(AK33=EOMONTH($AK$6,0),AK33=TODAY()),AM33,NA()) -> #N/A | AO33: =IF(MONTH(AO32)=MONTH(DATE(YEAR(AO32),MONTH(AO32),DAY(AO32)+1)),DATE(YEAR(AO32),MONTH(AO32),DAY(AO32)+1),NA()) -> #N/A | AP33: =SUMIFS(Table1[Amount $],Table1[Amount $],"<"&0,Table1[Category Type],"Expense",Table1[Date],Snapshot!AO33)*-1 -> 0 | AQ33: =IF(AO33<=EOMONTH($AO$6,0),SUM(AP$6:$AP33),NA()) -> #N/A | AR33: =IF(AO33=EOMONTH($AO$6,0),AQ33,NA()) -> #N/A | AU33: =IF(ISBLANK(AT33),"",SUMIFS(Table1[Amount $],Table1[Amount $],"<"&0,Table1[Merchant],Snapshot!AT33,Table1[Month],Snapshot!$W$4)*-1) | AV33: =IF(ISBLANK(AT33),"",COUNTIFS(Table1[Merchant],Snapshot!AT33,Table1[Month],Snapshot!$W$4)) | AW33: =IFERROR(RANK(AV33,$AV$6:$AV$200)+COUNTIF($AV$6:AV33,AV33)-1,"") | AX33: =IFERROR(RANK(AU33,$AU$6:$AU$200)+COUNTIF($AU$6:AU33,AU33)-1,"")
V34: =IF(ISBLANK(W34),"--",TEXT(W34,"mmmm")&" "&TEXT(W34,"YYYY")) -> -- | AC34: =IF(Categories!E35="Expense",Categories!D35,"--") -> -- | AD34: =SUMIFS(Table1[Amount $],Table1[Category],Snapshot!AC34,Table1[Amount $],"<"&0,Table1[Month],Snapshot!$W$4)*-1 -> 0 | AE34: =RANK(AD34,$AD$6:$AD$35,0)+COUNTIF(AD$6:$AD34,AD34)-1 -> 29 | AJ34: =DATE(YEAR(AJ33),MONTH(AJ33),DAY(AJ33)+1) -> 36554 | AK34: =IF(MONTH(AK33)=MONTH(DATE(YEAR(AK33),MONTH(AK33),DAY(AK33)+1)),DATE(YEAR(AK33),MONTH(AK33),DAY(AK33)+1),NA()) -> #N/A | AL34: =SUMIFS(Table1[Amount $],Table1[Amount $],"<"&0,Table1[Category Type],"Expense",Table1[Date],Snapshot!AK34)*-1 -> 0 | AM34: =IF(AK34>TODAY(),NA(),SUM(AL$6:$AL34)) -> #N/A | AN34: =IF(OR(AK34=EOMONTH($AK$6,0),AK34=TODAY()),AM34,NA()) -> #N/A | AO34: =IF(MONTH(AO33)=MONTH(DATE(YEAR(AO33),MONTH(AO33),DAY(AO33)+1)),DATE(YEAR(AO33),MONTH(AO33),DAY(AO33)+1),NA()) -> #N/A | AP34: =SUMIFS(Table1[Amount $],Table1[Amount $],"<"&0,Table1[Category Type],"Expense",Table1[Date],Snapshot!AO34)*-1 -> 0 | AQ34: =IF(AO34<=EOMONTH($AO$6,0),SUM(AP$6:$AP34),NA()) -> #N/A | AR34: =IF(AO34=EOMONTH($AO$6,0),AQ34,NA()) -> #N/A | AU34: =IF(ISBLANK(AT34),"",SUMIFS(Table1[Amount $],Table1[Amount $],"<"&0,Table1[Merchant],Snapshot!AT34,Table1[Month],Snapshot!$W$4)*-1) | AV34: =IF(ISBLANK(AT34),"",COUNTIFS(Table1[Merchant],Snapshot!AT34,Table1[Month],Snapshot!$W$4)) | AW34: =IFERROR(RANK(AV34,$AV$6:$AV$200)+COUNTIF($AV$6:AV34,AV34)-1,"") | AX34: =IFERROR(RANK(AU34,$AU$6:$AU$200)+COUNTIF($AU$6:AU34,AU34)-1,"")
V35: =IF(ISBLANK(W35),"--",TEXT(W35,"mmmm")&" "&TEXT(W35,"YYYY")) -> -- | AC35: =IF(Categories!E36="Expense",Categories!D36,"--") -> -- | AD35: =SUMIFS(Table1[Amount $],Table1[Category],Snapshot!AC35,Table1[Amount $],"<"&0,Table1[Month],Snapshot!$W$4)*-1 -> 0 | AE35: =RANK(AD35,$AD$6:$AD$35,0)+COUNTIF(AD$6:$AD35,AD35)-1 -> 30 | AJ35: =DATE(YEAR(AJ34),MONTH(AJ34),DAY(AJ34)+1) -> 36555 | AK35: =IF(MONTH(AK34)=MONTH(DATE(YEAR(AK34),MONTH(AK34),DAY(AK34)+1)),DATE(YEAR(AK34),MONTH(AK34),DAY(AK34)+1),NA()) -> #N/A | AL35: =SUMIFS(Table1[Amount $],Table1[Amount $],"<"&0,Table1[Category Type],"Expense",Table1[Date],Snapshot!AK35)*-1 -> 0 | AM35: =IF(AK35>TODAY(),NA(),SUM(AL$6:$AL35)) -> #N/A | AN35: =IF(OR(AK35=EOMONTH($AK$6,0),AK35=TODAY()),AM35,NA()) -> #N/A | AO35: =IF(MONTH(AO34)=MONTH(DATE(YEAR(AO34),MONTH(AO34),DAY(AO34)+1)),DATE(YEAR(AO34),MONTH(AO34),DAY(AO34)+1),NA()) -> #N/A | AP35: =SUMIFS(Table1[Amount $],Table1[Amount $],"<"&0,Table1[Category Type],"Expense",Table1[Date],Snapshot!AO35)*-1 -> 0 | AQ35: =IF(AO35<=EOMONTH($AO$6,0),SUM(AP$6:$AP35),NA()) -> #N/A | AR35: =IF(AO35=EOMONTH($AO$6,0),AQ35,NA()) -> #N/A | AU35: =IF(ISBLANK(AT35),"",SUMIFS(Table1[Amount $],Table1[Amount $],"<"&0,Table1[Merchant],Snapshot!AT35,Table1[Month],Snapshot!$W$4)*-1) | AV35: =IF(ISBLANK(AT35),"",COUNTIFS(Table1[Merchant],Snapshot!AT35,Table1[Month],Snapshot!$W$4)) | AW35: =IFERROR(RANK(AV35,$AV$6:$AV$200)+COUNTIF($AV$6:AV35,AV35)-1,"") | AX35: =IFERROR(RANK(AU35,$AU$6:$AU$200)+COUNTIF($AU$6:AU35,AU35)-1,"")
V36: =IF(ISBLANK(W36),"--",TEXT(W36,"mmmm")&" "&TEXT(W36,"YYYY")) -> -- | AJ36: =DATE(YEAR(AJ35),MONTH(AJ35),DAY(AJ35)+1) -> 36556 | AK36: =IF(MONTH(AK35)=MONTH(DATE(YEAR(AK35),MONTH(AK35),DAY(AK35)+1)),DATE(YEAR(AK35),MONTH(AK35),DAY(AK35)+1),NA()) -> #N/A | AL36: =SUMIFS(Table1[Amount $],Table1[Amount $],"<"&0,Table1[Category Type],"Expense",Table1[Date],Snapshot!AK36)*-1 -> 0 | AM36: =IF(AK36>TODAY(),NA(),SUM(AL$6:$AL36)) -> #N/A | AN36: =IF(OR(AK36=EOMONTH($AK$6,0),AK36=TODAY()),AM36,NA()) -> #N/A | AO36: =IF(MONTH(AO35)=MONTH(DATE(YEAR(AO35),MONTH(AO35),DAY(AO35)+1)),DATE(YEAR(AO35),MONTH(AO35),DAY(AO35)+1),NA()) -> #N/A | AP36: =SUMIFS(Table1[Amount $],Table1[Amount $],"<"&0,Table1[Category Type],"Expense",Table1[Date],Snapshot!AO36)*-1 -> 0 | AQ36: =IF(AO36<=EOMONTH($AO$6,0),SUM(AP$6:$AP36),NA()) -> #N/A | AR36: =IF(AO36=EOMONTH($AO$6,0),AQ36,NA()) -> #N/A | AU36: =IF(ISBLANK(AT36),"",SUMIFS(Table1[Amount $],Table1[Amount $],"<"&0,Table1[Merchant],Snapshot!AT36,Table1[Month],Snapshot!$W$4)*-1) | AV36: =IF(ISBLANK(AT36),"",COUNTIFS(Table1[Merchant],Snapshot!AT36,Table1[Month],Snapshot!$W$4)) | AW36: =IFERROR(RANK(AV36,$AV$6:$AV$200)+COUNTIF($AV$6:AV36,AV36)-1,"") | AX36: =IFERROR(RANK(AU36,$AU$6:$AU$200)+COUNTIF($AU$6:AU36,AU36)-1,"")
V37: =IF(ISBLANK(W37),"--",TEXT(W37,"mmmm")&" "&TEXT(W37,"YYYY")) -> -- | AU37: =IF(ISBLANK(AT37),"",SUMIFS(Table1[Amount $],Table1[Amount $],"<"&0,Table1[Merchant],Snapshot!AT37,Table1[Month],Snapshot!$W$4)*-1) | AV37: =IF(ISBLANK(AT37),"",COUNTIFS(Table1[Merchant],Snapshot!AT37,Table1[Month],Snapshot!$W$4)) | AW37: =IFERROR(RANK(AV37,$AV$6:$AV$200)+COUNTIF($AV$6:AV37,AV37)-1,"") | AX37: =IFERROR(RANK(AU37,$AU$6:$AU$200)+COUNTIF($AU$6:AU37,AU37)-1,"")
V38: =IF(ISBLANK(W38),"--",TEXT(W38,"mmmm")&" "&TEXT(W38,"YYYY")) -> -- | AK38: =TODAY() -> 44069 | AM38: {=INDEX(AM6:AM36,MATCH(AK38,AK6:AK36,0),0)} -> #N/A | AO38: =DATE(YEAR(AK38),MONTH(AK38)-1,DAY(AK38)) -> 44038 | AQ38: {=INDEX(AQ6:AQ36,MATCH(AO38,AO6:AO36,0),0)} -> #N/A | AU38: =IF(ISBLANK(AT38),"",SUMIFS(Table1[Amount $],Table1[Amount $],"<"&0,Table1[Merchant],Snapshot!AT38,Table1[Month],Snapshot!$W$4)*-1) | AV38: =IF(ISBLANK(AT38),"",COUNTIFS(Table1[Merchant],Snapshot!AT38,Table1[Month],Snapshot!$W$4)) | AW38: =IFERROR(RANK(AV38,$AV$6:$AV$200)+COUNTIF($AV$6:AV38,AV38)-1,"") | AX38: =IFERROR(RANK(AU38,$AU$6:$AU$200)+COUNTIF($AU$6:AU38,AU38)-1,"")
V39: =IF(ISBLANK(W39),"--",TEXT(W39,"mmmm")&" "&TEXT(W39,"YYYY")) -> -- | AK39: =IF(AM38>AQ38,"Spent "&TEXT(AM38-AQ38,"$#,##0")&" more","Spent "&TEXT((AM38-AQ38)*-1,"$#,##0")&" less")&" than this time last month" -> #N/A | AU39: =IF(ISBLANK(AT39),"",SUMIFS(Table1[Amount $],Table1[Amount $],"<"&0,Table1[Merchant],Snapshot!AT39,Table1[Month],Snapshot!$W$4)*-1) | AV39: =IF(ISBLANK(AT39),"",COUNTIFS(Table1[Merchant],Snapshot!AT39,Table1[Month],Snapshot!$W$4)) | AW39: =IFERROR(RANK(AV39,$AV$6:$AV$200)+COUNTIF($AV$6:AV39,AV39)-1,"") | AX39: =IFERROR(RANK(AU39,$AU$6:$AU$200)+COUNTIF($AU$6:AU39,AU39)-1,"")
V40: =IF(ISBLANK(W40),"--",TEXT(W40,"mmmm")&" "&TEXT(W40,"YYYY")) -> -- | AU40: =IF(ISBLANK(AT40),"",SUMIFS(Table1[Amount $],Table1[Amount $],"<"&0,Table1[Merchant],Snapshot!AT40,Table1[Month],Snapshot!$W$4)*-1) | AV40: =IF(ISBLANK(AT40),"",COUNTIFS(Table1[Merchant],Snapshot!AT40,Table1[Month],Snapshot!$W$4)) | AW40: =IFERROR(RANK(AV40,$AV$6:$AV$200)+COUNTIF($AV$6:AV40,AV40)-1,"") | AX40: =IFERROR(RANK(AU40,$AU$6:$AU$200)+COUNTIF($AU$6:AU40,AU40)-1,"")
V41: =IF(ISBLANK(W41),"--",TEXT(W41,"mmmm")&" "&TEXT(W41,"YYYY")) -> -- | AK41: =IFERROR(MAX(AK6:AK36),IFERROR(AK35,IF(AK34,AK33))) -> #N/A | AM41: {=INDEX(AM6:AM36,MATCH(AK41,AK6:AK36,0),0)} -> #N/A | AO41: =IFERROR(MAX(AO6:AO36),IFERROR(AO35,IF(AO34,AO33))) -> #N/A | AQ41: {=INDEX(AQ6:AQ36,MATCH(AO41,AO6:AO36,0),0)} -> #N/A | AU41: =IF(ISBLANK(AT41),"",SUMIFS(Table1[Amount $],Table1[Amount $],"<"&0,Table1[Merchant],Snapshot!AT41,Table1[Month],Snapshot!$W$4)*-1) | AV41: =IF(ISBLANK(AT41),"",COUNTIFS(Table1[Merchant],Snapshot!AT41,Table1[Month],Snapshot!$W$4)) | AW41: =IFERROR(RANK(AV41,$AV$6:$AV$200)+COUNTIF($AV$6:AV41,AV41)-1,"") | AX41: =IFERROR(RANK(AU41,$AU$6:$AU$200)+COUNTIF($AU$6:AU41,AU41)-1,"")
V42: =IF(ISBLANK(W42),"--",TEXT(W42,"mmmm")&" "&TEXT(W42,"YYYY")) -> -- | AK42: ="Compared to "&TEXT(AO6,"mmmm")&", you "&IF(AM41>AQ41,"spent "&TEXT(AM41-AQ41,"$#,##0")&" more","spent "&TEXT((AM41-AQ41)*-1,"$#,##0")&" less") -> #N/A | AU42: =IF(ISBLANK(AT42),"",SUMIFS(Table1[Amount $],Table1[Amount $],"<"&0,Table1[Merchant],Snapshot!AT42,Table1[Month],Snapshot!$W$4)*-1) | AV42: =IF(ISBLANK(AT42),"",COUNTIFS(Table1[Merchant],Snapshot!AT42,Table1[Month],Snapshot!$W$4)) | AW42: =IFERROR(RANK(AV42,$AV$6:$AV$200)+COUNTIF($AV$6:AV42,AV42)-1,"") | AX42: =IFERROR(RANK(AU42,$AU$6:$AU$200)+COUNTIF($AU$6:AU42,AU42)-1,"")
V43: =IF(ISBLANK(W43),"--",TEXT(W43,"mmmm")&" "&TEXT(W43,"YYYY")) -> -- | AU43: =IF(ISBLANK(AT43),"",SUMIFS(Table1[Amount $],Table1[Amount $],"<"&0,Table1[Merchant],Snapshot!AT43,Table1[Month],Snapshot!$W$4)*-1) | AV43: =IF(ISBLANK(AT43),"",COUNTIFS(Table1[Merchant],Snapshot!AT43,Table1[Month],Snapshot!$W$4)) | AW43: =IFERROR(RANK(AV43,$AV$6:$AV$200)+COUNTIF($AV$6:AV43,AV43)-1,"") | AX43: =IFERROR(RANK(AU43,$AU$6:$AU$200)+COUNTIF($AU$6:AU43,AU43)-1,"")
D44: Frequented merchants | M44: Merchants where the most was spent | V44: =IF(ISBLANK(W44),"--",TEXT(W44,"mmmm")&" "&TEXT(W44,"YYYY")) -> -- | AU44: =IF(ISBLANK(AT44),"",SUMIFS(Table1[Amount $],Table1[Amount $],"<"&0,Table1[Merchant],Snapshot!AT44,Table1[Month],Snapshot!$W$4)*-1) | AV44: =IF(ISBLANK(AT44),"",COUNTIFS(Table1[Merchant],Snapshot!AT44,Table1[Month],Snapshot!$W$4)) | AW44: =IFERROR(RANK(AV44,$AV$6:$AV$200)+COUNTIF($AV$6:AV44,AV44)-1,"") | AX44: =IFERROR(RANK(AU44,$AU$6:$AU$200)+COUNTIF($AU$6:AU44,AU44)-1,"")
V45: =IF(ISBLANK(W45),"--",TEXT(W45,"mmmm")&" "&TEXT(W45,"YYYY")) -> -- | AU45: =IF(ISBLANK(AT45),"",SUMIFS(Table1[Amount $],Table1[Amount $],"<"&0,Table1[Merchant],Snapshot!AT45,Table1[Month],Snapshot!$W$4)*-1) | AV45: =IF(ISBLANK(AT45),"",COUNTIFS(Table1[Merchant],Snapshot!AT45,Table1[Month],Snapshot!$W$4)) | AW45: =IFERROR(RANK(AV45,$AV$6:$AV$200)+COUNTIF($AV$6:AV45,AV45)-1,"") | AX45: =IFERROR(RANK(AU45,$AU$6:$AU$200)+COUNTIF($AU$6:AU45,AU45)-1,"")
D46: Merchant | G46: Count | I46: Total cost | M46: Merchant | Q46: Category | S46: Total cost | V46: =IF(ISBLANK(W46),"--",TEXT(W46,"mmmm")&" "&TEXT(W46,"YYYY")) -> -- | AU46: =IF(ISBLANK(AT46),"",SUMIFS(Table1[Amount $],Table1[Amount $],"<"&0,Table1[Merchant],Snapshot!AT46,Table1[Month],Snapshot!$W$4)*-1) | AV46: =IF(ISBLANK(AT46),"",COUNTIFS(Table1[Merchant],Snapshot!AT46,Table1[Month],Snapshot!$W$4)) | AW46: =IFERROR(RANK(AV46,$AV$6:$AV$200)+COUNTIF($AV$6:AV46,AV46)-1,"") | AX46: =IFERROR(RANK(AU46,$AU$6:$AU$200)+COUNTIF($AU$6:AU46,AU46)-1,"")
B47: 1 | D47: {=IFERROR(INDEX($AT:$AT,MATCH($B47,$AW:$AW,0),0),"")} | G47: {=IF(IFERROR(INDEX($AV:$AV,MATCH($B47,$AW:$AW,0),0),"")=0,"",IFERROR(INDEX($AV:$AV,MATCH($B47,$AW:$AW,0),0),""))} | I47: {=IF(IFERROR(INDEX($AU:$AU,MATCH($B47,$AW:$AW,0),0),"")=0,"",IFERROR(INDEX($AU:$AU,MATCH($B47,$AW:$AW,0),0),""))} | M47: {=IFERROR(INDEX($AT:$AT,MATCH($B47,$AX:$AX,0),0),"")} | Q47: {=IFERROR(INDEX(Table1[Category],MATCH(Snapshot!M47,Table1[Merchant],0),0),"")} | S47: {=IF(IFERROR(INDEX($AU:$AU,MATCH($B47,$AX:$AX,0),0),"")=0,"",IFERROR(INDEX($AU:$AU,MATCH($B47,$AX:$AX,0),0),""))} | V47: =IF(ISBLANK(W47),"--",TEXT(W47,"mmmm")&" "&TEXT(W47,"YYYY")) -> -- | AU47: =IF(ISBLANK(AT47),"",SUMIFS(Table1[Amount $],Table1[Amount $],"<"&0,Table1[Merchant],Snapshot!AT47,Table1[Month],Snapshot!$W$4)*-1) | AV47: =IF(ISBLANK(AT47),"",COUNTIFS(Table1[Merchant],Snapshot!AT47,Table1[Month],Snapshot!$W$4)) | AW47: =IFERROR(RANK(AV47,$AV$6:$AV$200)+COUNTIF($AV$6:AV47,AV47)-1,"") | AX47: =IFERROR(RANK(AU47,$AU$6:$AU$200)+COUNTIF($AU$6:AU47,AU47)-1,"")
B48: =B47+1 -> 2 | D48: {=IFERROR(INDEX($AT:$AT,MATCH($B48,$AW:$AW,0),0),"")} | G48: {=IF(IFERROR(INDEX($AV:$AV,MATCH($B48,$AW:$AW,0),0),"")=0,"",IFERROR(INDEX($AV:$AV,MATCH($B48,$AW:$AW,0),0),""))} | I48: {=IF(IFERROR(INDEX($AU:$AU,MATCH($B48,$AW:$AW,0),0),"")=0,"",IFERROR(INDEX($AU:$AU,MATCH($B48,$AW:$AW,0),0),""))} | M48: {=IFERROR(INDEX($AT:$AT,MATCH($B48,$AX:$AX,0),0),"")} | Q48: {=IFERROR(INDEX(Table1[Category],MATCH(Snapshot!M48,Table1[Merchant],0),0),"")} | S48: {=IF(IFERROR(INDEX($AU:$AU,MATCH($B48,$AX:$AX,0),0),"")=0,"",IFERROR(INDEX($AU:$AU,MATCH($B48,$AX:$AX,0),0),""))} | V48: =IF(ISBLANK(W48),"--",TEXT(W48,"mmmm")&" "&TEXT(W48,"YYYY")) -> -- | AU48: =IF(ISBLANK(AT48),"",SUMIFS(Table1[Amount $],Table1[Amount $],"<"&0,Table1[Merchant],Snapshot!AT48,Table1[Month],Snapshot!$W$4)*-1) | AV48: =IF(ISBLANK(AT48),"",COUNTIFS(Table1[Merchant],Snapshot!AT48,Table1[Month],Snapshot!$W$4)) | AW48: =IFERROR(RANK(AV48,$AV$6:$AV$200)+COUNTIF($AV$6:AV48,AV48)-1,"") | AX48: =IFERROR(RANK(AU48,$AU$6:$AU$200)+COUNTIF($AU$6:AU48,AU48)-1,"")
B49: =B48+1 -> 3 | D49: {=IFERROR(INDEX($AT:$AT,MATCH($B49,$AW:$AW,0),0),"")} | G49: {=IF(IFERROR(INDEX($AV:$AV,MATCH($B49,$AW:$AW,0),0),"")=0,"",IFERROR(INDEX($AV:$AV,MATCH($B49,$AW:$AW,0),0),""))} | I49: {=IF(IFERROR(INDEX($AU:$AU,MATCH($B49,$AW:$AW,0),0),"")=0,"",IFERROR(INDEX($AU:$AU,MATCH($B49,$AW:$AW,0),0),""))} | M49: {=IFERROR(INDEX($AT:$AT,MATCH($B49,$AX:$AX,0),0),"")} | Q49: {=IFERROR(INDEX(Table1[Category],MATCH(Snapshot!M49,Table1[Merchant],0),0),"")} | S49: {=IF(IFERROR(INDEX($AU:$AU,MATCH($B49,$AX:$AX,0),0),"")=0,"",IFERROR(INDEX($AU:$AU,MATCH($B49,$AX:$AX,0),0),""))} | V49: =IF(ISBLANK(W49),"--",TEXT(W49,"mmmm")&" "&TEXT(W49,"YYYY")) -> -- | AU49: =IF(ISBLANK(AT49),"",SUMIFS(Table1[Amount $],Table1[Amount $],"<"&0,Table1[Merchant],Snapshot!AT49,Table1[Month],Snapshot!$W$4)*-1) | AV49: =IF(ISBLANK(AT49),"",COUNTIFS(Table1[Merchant],Snapshot!AT49,Table1[Month],Snapshot!$W$4)) | AW49: =IFERROR(RANK(AV49,$AV$6:$AV$200)+COUNTIF($AV$6:AV49,AV49)-1,"") | AX49: =IFERROR(RANK(AU49,$AU$6:$AU$200)+COUNTIF($AU$6:AU49,AU49)-1,"")
B50: =B49+1 -> 4 | D50: {=IFERROR(INDEX($AT:$AT,MATCH($B50,$AW:$AW,0),0),"")} | G50: {=IF(IFERROR(INDEX($AV:$AV,MATCH($B50,$AW:$AW,0),0),"")=0,"",IFERROR(INDEX($AV:$AV,MATCH($B50,$AW:$AW,0),0),""))} | I50: {=IF(IFERROR(INDEX($AU:$AU,MATCH($B50,$AW:$AW,0),0),"")=0,"",IFERROR(INDEX($AU:$AU,MATCH($B50,$AW:$AW,0),0),""))} | M50: {=IFERROR(INDEX($AT:$AT,MATCH($B50,$AX:$AX,0),0),"")} | Q50: {=IFERROR(INDEX(Table1[Category],MATCH(Snapshot!M50,Table1[Merchant],0),0),"")} | S50: {=IF(IFERROR(INDEX($AU:$AU,MATCH($B50,$AX:$AX,0),0),"")=0,"",IFERROR(INDEX($AU:$AU,MATCH($B50,$AX:$AX,0),0),""))} | V50: =IF(ISBLANK(W50),"--",TEXT(W50,"mmmm")&" "&TEXT(W50,"YYYY")) -> -- | AU50: =IF(ISBLANK(AT50),"",SUMIFS(Table1[Amount $],Table1[Amount $],"<"&0,Table1[Merchant],Snapshot!AT50,Table1[Month],Snapshot!$W$4)*-1) | AV50: =IF(ISBLANK(AT50),"",COUNTIFS(Table1[Merchant],Snapshot!AT50,Table1[Month],Snapshot!$W$4)) | AW50: =IFERROR(RANK(AV50,$AV$6:$AV$200)+COUNTIF($AV$6:AV50,AV50)-1,"") | AX50: =IFERROR(RANK(AU50,$AU$6:$AU$200)+COUNTIF($AU$6:AU50,AU50)-1,"")
B51: =B50+1 -> 5 | D51: {=IFERROR(INDEX($AT:$AT,MATCH($B51,$AW:$AW,0),0),"")} | G51: {=IF(IFERROR(INDEX($AV:$AV,MATCH($B51,$AW:$AW,0),0),"")=0,"",IFERROR(INDEX($AV:$AV,MATCH($B51,$AW:$AW,0),0),""))} | I51: {=IF(IFERROR(INDEX($AU:$AU,MATCH($B51,$AW:$AW,0),0),"")=0,"",IFERROR(INDEX($AU:$AU,MATCH($B51,$AW:$AW,0),0),""))} | M51: {=IFERROR(INDEX($AT:$AT,MATCH($B51,$AX:$AX,0),0),"")} | Q51: {=IFERROR(INDEX(Table1[Category],MATCH(Snapshot!M51,Table1[Merchant],0),0),"")} | S51: {=IF(IFERROR(INDEX($AU:$AU,MATCH($B51,$AX:$AX,0),0),"")=0,"",IFERROR(INDEX($AU:$AU,MATCH($B51,$AX:$AX,0),0),""))} | V51: =IF(ISBLANK(W51),"--",TEXT(W51,"mmmm")&" "&TEXT(W51,"YYYY")) -> -- | AU51: =IF(ISBLANK(AT51),"",SUMIFS(Table1[Amount $],Table1[Amount $],"<"&0,Table1[Merchant],Snapshot!AT51,Table1[Month],Snapshot!$W$4)*-1) | AV51: =IF(ISBLANK(AT51),"",COUNTIFS(Table1[Merchant],Snapshot!AT51,Table1[Month],Snapshot!$W$4)) | AW51: =IFERROR(RANK(AV51,$AV$6:$AV$200)+COUNTIF($AV$6:AV51,AV51)-1,"") | AX51: =IFERROR(RANK(AU51,$AU$6:$AU$200)+COUNTIF($AU$6:AU51,AU51)-1,"")
B52: =B51+1 -> 6 | D52: {=IFERROR(INDEX($AT:$AT,MATCH($B52,$AW:$AW,0),0),"")} | G52: {=IF(IFERROR(INDEX($AV:$AV,MATCH($B52,$AW:$AW,0),0),"")=0,"",IFERROR(INDEX($AV:$AV,MATCH($B52,$AW:$AW,0),0),""))} | I52: {=IF(IFERROR(INDEX($AU:$AU,MATCH($B52,$AW:$AW,0),0),"")=0,"",IFERROR(INDEX($AU:$AU,MATCH($B52,$AW:$AW,0),0),""))} | M52: {=IFERROR(INDEX($AT:$AT,MATCH($B52,$AX:$AX,0),0),"")} | Q52: {=IFERROR(INDEX(Table1[Category],MATCH(Snapshot!M52,Table1[Merchant],0),0),"")} | S52: {=IF(IFERROR(INDEX($AU:$AU,MATCH($B52,$AX:$AX,0),0),"")=0,"",IFERROR(INDEX($AU:$AU,MATCH($B52,$AX:$AX,0),0),""))} | V52: =IF(ISBLANK(W52),"--",TEXT(W52,"mmmm")&" "&TEXT(W52,"YYYY")) -> -- | AU52: =IF(ISBLANK(AT52),"",SUMIFS(Table1[Amount $],Table1[Amount $],"<"&0,Table1[Merchant],Snapshot!AT52,Table1[Month],Snapshot!$W$4)*-1) | AV52: =IF(ISBLANK(AT52),"",COUNTIFS(Table1[Merchant],Snapshot!AT52,Table1[Month],Snapshot!$W$4)) | AW52: =IFERROR(RANK(AV52,$AV$6:$AV$200)+COUNTIF($AV$6:AV52,AV52)-1,"") | AX52: =IFERROR(RANK(AU52,$AU$6:$AU$200)+COUNTIF($AU$6:AU52,AU52)-1,"")
B53: =B52+1 -> 7 | D53: {=IFERROR(INDEX($AT:$AT,MATCH($B53,$AW:$AW,0),0),"")} | G53: {=IF(IFERROR(INDEX($AV:$AV,MATCH($B53,$AW:$AW,0),0),"")=0,"",IFERROR(INDEX($AV:$AV,MATCH($B53,$AW:$AW,0),0),""))} | I53: {=IF(IFERROR(INDEX($AU:$AU,MATCH($B53,$AW:$AW,0),0),"")=0,"",IFERROR(INDEX($AU:$AU,MATCH($B53,$AW:$AW,0),0),""))} | M53: {=IFERROR(INDEX($AT:$AT,MATCH($B53,$AX:$AX,0),0),"")} | Q53: {=IFERROR(INDEX(Table1[Category],MATCH(Snapshot!M53,Table1[Merchant],0),0),"")} | S53: {=IF(IFERROR(INDEX($AU:$AU,MATCH($B53,$AX:$AX,0),0),"")=0,"",IFERROR(INDEX($AU:$AU,MATCH($B53,$AX:$AX,0),0),""))} | V53: =IF(ISBLANK(W53),"--",TEXT(W53,"mmmm")&" "&TEXT(W53,"YYYY")) -> -- | AU53: =IF(ISBLANK(AT53),"",SUMIFS(Table1[Amount $],Table1[Amount $],"<"&0,Table1[Merchant],Snapshot!AT53,Table1[Month],Snapshot!$W$4)*-1) | AV53: =IF(ISBLANK(AT53),"",COUNTIFS(Table1[Merchant],Snapshot!AT53,Table1[Month],Snapshot!$W$4)) | AW53: =IFERROR(RANK(AV53,$AV$6:$AV$200)+COUNTIF($AV$6:AV53,AV53)-1,"") | AX53: =IFERROR(RANK(AU53,$AU$6:$AU$200)+COUNTIF($AU$6:AU53,AU53)-1,"")
B54: =B53+1 -> 8 | D54: {=IFERROR(INDEX($AT:$AT,MATCH($B54,$AW:$AW,0),0),"")} | G54: {=IF(IFERROR(INDEX($AV:$AV,MATCH($B54,$AW:$AW,0),0),"")=0,"",IFERROR(INDEX($AV:$AV,MATCH($B54,$AW:$AW,0),0),""))} | I54: {=IF(IFERROR(INDEX($AU:$AU,MATCH($B54,$AW:$AW,0),0),"")=0,"",IFERROR(INDEX($AU:$AU,MATCH($B54,$AW:$AW,0),0),""))} | M54: {=IFERROR(INDEX($AT:$AT,MATCH($B54,$AX:$AX,0),0),"")} | Q54: {=IFERROR(INDEX(Table1[Category],MATCH(Snapshot!M54,Table1[Merchant],0),0),"")} | S54: {=IF(IFERROR(INDEX($AU:$AU,MATCH($B54,$AX:$AX,0),0),"")=0,"",IFERROR(INDEX($AU:$AU,MATCH($B54,$AX:$AX,0),0),""))} | V54: =IF(ISBLANK(W54),"--",TEXT(W54,"mmmm")&" "&TEXT(W54,"YYYY")) -> -- | AU54: =IF(ISBLANK(AT54),"",SUMIFS(Table1[Amount $],Table1[Amount $],"<"&0,Table1[Merchant],Snapshot!AT54,Table1[Month],Snapshot!$W$4)*-1) | AV54: =IF(ISBLANK(AT54),"",COUNTIFS(Table1[Merchant],Snapshot!AT54,Table1[Month],Snapshot!$W$4)) | AW54: =IFERROR(RANK(AV54,$AV$6:$AV$200)+COUNTIF($AV$6:AV54,AV54)-1,"") | AX54: =IFERROR(RANK(AU54,$AU$6:$AU$200)+COUNTIF($AU$6:AU54,AU54)-1,"")
B55: =B54+1 -> 9 | D55: {=IFERROR(INDEX($AT:$AT,MATCH($B55,$AW:$AW,0),0),"")} | G55: {=IF(IFERROR(INDEX($AV:$AV,MATCH($B55,$AW:$AW,0),0),"")=0,"",IFERROR(INDEX($AV:$AV,MATCH($B55,$AW:$AW,0),0),""))} | I55: {=IF(IFERROR(INDEX($AU:$AU,MATCH($B55,$AW:$AW,0),0),"")=0,"",IFERROR(INDEX($AU:$AU,MATCH($B55,$AW:$AW,0),0),""))} | M55: {=IFERROR(INDEX($AT:$AT,MATCH($B55,$AX:$AX,0),0),"")} | Q55: {=IFERROR(INDEX(Table1[Category],MATCH(Snapshot!M55,Table1[Merchant],0),0),"")} | S55: {=IF(IFERROR(INDEX($AU:$AU,MATCH($B55,$AX:$AX,0),0),"")=0,"",IFERROR(INDEX($AU:$AU,MATCH($B55,$AX:$AX,0),0),""))} | V55: =IF(ISBLANK(W55),"--",TEXT(W55,"mmmm")&" "&TEXT(W55,"YYYY")) -> -- | AU55: =IF(ISBLANK(AT55),"",SUMIFS(Table1[Amount $],Table1[Amount $],"<"&0,Table1[Merchant],Snapshot!AT55,Table1[Month],Snapshot!$W$4)*-1) | AV55: =IF(ISBLANK(AT55),"",COUNTIFS(Table1[Merchant],Snapshot!AT55,Table1[Month],Snapshot!$W$4)) | AW55: =IFERROR(RANK(AV55,$AV$6:$AV$200)+COUNTIF($AV$6:AV55,AV55)-1,"") | AX55: =IFERROR(RANK(AU55,$AU$6:$AU$200)+COUNTIF($AU$6:AU55,AU55)-1,"")
B56: =B55+1 -> 10 | D56: {=IFERROR(INDEX($AT:$AT,MATCH($B56,$AW:$AW,0),0),"")} | G56: {=IF(IFERROR(INDEX($AV:$AV,MATCH($B56,$AW:$AW,0),0),"")=0,"",IFERROR(INDEX($AV:$AV,MATCH($B56,$AW:$AW,0),0),""))} | I56: {=IF(IFERROR(INDEX($AU:$AU,MATCH($B56,$AW:$AW,0),0),"")=0,"",IFERROR(INDEX($AU:$AU,MATCH($B56,$AW:$AW,0),0),""))} | M56: {=IFERROR(INDEX($AT:$AT,MATCH($B56,$AX:$AX,0),0),"")} | Q56: {=IFERROR(INDEX(Table1[Category],MATCH(Snapshot!M56,Table1[Merchant],0),0),"")} | S56: {=IF(IFERROR(INDEX($AU:$AU,MATCH($B56,$AX:$AX,0),0),"")=0,"",IFERROR(INDEX($AU:$AU,MATCH($B56,$AX:$AX,0),0),""))} | V56: =IF(ISBLANK(W56),"--",TEXT(W56,"mmmm")&" "&TEXT(W56,"YYYY")) -> -- | AU56: =IF(ISBLANK(AT56),"",SUMIFS(Table1[Amount $],Table1[Amount $],"<"&0,Table1[Merchant],Snapshot!AT56,Table1[Month],Snapshot!$W$4)*-1) | AV56: =IF(ISBLANK(AT56),"",COUNTIFS(Table1[Merchant],Snapshot!AT56,Table1[Month],Snapshot!$W$4)) | AW56: =IFERROR(RANK(AV56,$AV$6:$AV$200)+COUNTIF($AV$6:AV56,AV56)-1,"") | AX56: =IFERROR(RANK(AU56,$AU$6:$AU$200)+COUNTIF($AU$6:AU56,AU56)-1,"")
V57: =IF(ISBLANK(W57),"--",TEXT(W57,"mmmm")&" "&TEXT(W57,"YYYY")) -> -- | AU57: =IF(ISBLANK(AT57),"",SUMIFS(Table1[Amount $],Table1[Amount $],"<"&0,Table1[Merchant],Snapshot!AT57,Table1[Month],Snapshot!$W$4)*-1) | AV57: =IF(ISBLANK(AT57),"",COUNTIFS(Table1[Merchant],Snapshot!AT57,Table1[Month],Snapshot!$W$4)) | AW57: =IFERROR(RANK(AV57,$AV$6:$AV$200)+COUNTIF($AV$6:AV57,AV57)-1,"") | AX57: =IFERROR(RANK(AU57,$AU$6:$AU$200)+COUNTIF($AU$6:AU57,AU57)-1,"")
V58: =IF(ISBLANK(W58),"--",TEXT(W58,"mmmm")&" "&TEXT(W58,"YYYY")) -> -- | AU58: =IF(ISBLANK(AT58),"",SUMIFS(Table1[Amount $],Table1[Amount $],"<"&0,Table1[Merchant],Snapshot!AT58,Table1[Month],Snapshot!$W$4)*-1) | AV58: =IF(ISBLANK(AT58),"",COUNTIFS(Table1[Merchant],Snapshot!AT58,Table1[Month],Snapshot!$W$4)) | AW58: =IFERROR(RANK(AV58,$AV$6:$AV$200)+COUNTIF($AV$6:AV58,AV58)-1,"") | AX58: =IFERROR(RANK(AU58,$AU$6:$AU$200)+COUNTIF($AU$6:AU58,AU58)-1,"")
V59: =IF(ISBLANK(W59),"--",TEXT(W59,"mmmm")&" "&TEXT(W59,"YYYY")) -> -- | AU59: =IF(ISBLANK(AT59),"",SUMIFS(Table1[Amount $],Table1[Amount $],"<"&0,Table1[Merchant],Snapshot!AT59,Table1[Month],Snapshot!$W$4)*-1) | AV59: =IF(ISBLANK(AT59),"",COUNTIFS(Table1[Merchant],Snapshot!AT59,Table1[Month],Snapshot!$W$4)) | AW59: =IFERROR(RANK(AV59,$AV$6:$AV$200)+COUNTIF($AV$6:AV59,AV59)-1,"") | AX59: =IFERROR(RANK(AU59,$AU$6:$AU$200)+COUNTIF($AU$6:AU59,AU59)-1,"")
V60: =IF(ISBLANK(W60),"--",TEXT(W60,"mmmm")&" "&TEXT(W60,"YYYY")) -> -- | AU60: =IF(ISBLANK(AT60),"",SUMIFS(Table1[Amount $],Table1[Amount $],"<"&0,Table1[Merchant],Snapshot!AT60,Table1[Month],Snapshot!$W$4)*-1) | AV60: =IF(ISBLANK(AT60),"",COUNTIFS(Table1[Merchant],Snapshot!AT60,Table1[Month],Snapshot!$W$4)) | AW60: =IFERROR(RANK(AV60,$AV$6:$AV$200)+COUNTIF($AV$6:AV60,AV60)-1,"") | AX60: =IFERROR(RANK(AU60,$AU$6:$AU$200)+COUNTIF($AU$6:AU60,AU60)-1,"")
V61: =IF(ISBLANK(W61),"--",TEXT(W61,"mmmm")&" "&TEXT(W61,"YYYY")) -> -- | AU61: =IF(ISBLANK(AT61),"",SUMIFS(Table1[Amount $],Table1[Amount $],"<"&0,Table1[Merchant],Snapshot!AT61,Table1[Month],Snapshot!$W$4)*-1) | AV61: =IF(ISBLANK(AT61),"",COUNTIFS(Table1[Merchant],Snapshot!AT61,Table1[Month],Snapshot!$W$4)) | AW61: =IFERROR(RANK(AV61,$AV$6:$AV$200)+COUNTIF($AV$6:AV61,AV61)-1,"") | AX61: =IFERROR(RANK(AU61,$AU$6:$AU$200)+COUNTIF($AU$6:AU61,AU61)-1,"")
V62: =IF(ISBLANK(W62),"--",TEXT(W62,"mmmm")&" "&TEXT(W62,"YYYY")) -> -- | AU62: =IF(ISBLANK(AT62),"",SUMIFS(Table1[Amount $],Table1[Amount $],"<"&0,Table1[Merchant],Snapshot!AT62,Table1[Month],Snapshot!$W$4)*-1) | AV62: =IF(ISBLANK(AT62),"",COUNTIFS(Table1[Merchant],Snapshot!AT62,Table1[Month],Snapshot!$W$4)) | AW62: =IFERROR(RANK(AV62,$AV$6:$AV$200)+COUNTIF($AV$6:AV62,AV62)-1,"") | AX62: =IFERROR(RANK(AU62,$AU$6:$AU$200)+COUNTIF($AU$6:AU62,AU62)-1,"")
V63: =IF(ISBLANK(W63),"--",TEXT(W63,"mmmm")&" "&TEXT(W63,"YYYY")) -> -- | AU63: =IF(ISBLANK(AT63),"",SUMIFS(Table1[Amount $],Table1[Amount $],"<"&0,Table1[Merchant],Snapshot!AT63,Table1[Month],Snapshot!$W$4)*-1) | AV63: =IF(ISBLANK(AT63),"",COUNTIFS(Table1[Merchant],Snapshot!AT63,Table1[Month],Snapshot!$W$4)) | AW63: =IFERROR(RANK(AV63,$AV$6:$AV$200)+COUNTIF($AV$6:AV63,AV63)-1,"") | AX63: =IFERROR(RANK(AU63,$AU$6:$AU$200)+COUNTIF($AU$6:AU63,AU63)-1,"")
V64: =IF(ISBLANK(W64),"--",TEXT(W64,"mmmm")&" "&TEXT(W64,"YYYY")) -> -- | AU64: =IF(ISBLANK(AT64),"",SUMIFS(Table1[Amount $],Table1[Amount $],"<"&0,Table1[Merchant],Snapshot!AT64,Table1[Month],Snapshot!$W$4)*-1) | AV64: =IF(ISBLANK(AT64),"",COUNTIFS(Table1[Merchant],Snapshot!AT64,Table1[Month],Snapshot!$W$4)) | AW64: =IFERROR(RANK(AV64,$AV$6:$AV$200)+COUNTIF($AV$6:AV64,AV64)-1,"") | AX64: =IFERROR(RANK(AU64,$AU$6:$AU$200)+COUNTIF($AU$6:AU64,AU64)-1,"")
V65: =IF(ISBLANK(W65),"--",TEXT(W65,"mmmm")&" "&TEXT(W65,"YYYY")) -> -- | AU65: =IF(ISBLANK(AT65),"",SUMIFS(Table1[Amount $],Table1[Amount $],"<"&0,Table1[Merchant],Snapshot!AT65,Table1[Month],Snapshot!$W$4)*-1) | AV65: =IF(ISBLANK(AT65),"",COUNTIFS(Table1[Merchant],Snapshot!AT65,Table1[Month],Snapshot!$W$4)) | AW65: =IFERROR(RANK(AV65,$AV$6:$AV$200)+COUNTIF($AV$6:AV65,AV65)-1,"") | AX65: =IFERROR(RANK(AU65,$AU$6:$AU$200)+COUNTIF($AU$6:AU65,AU65)-1,"")
V66: =IF(ISBLANK(W66),"--",TEXT(W66,"mmmm")&" "&TEXT(W66,"YYYY")) -> -- | AU66: =IF(ISBLANK(AT66),"",SUMIFS(Table1[Amount $],Table1[Amount $],"<"&0,Table1[Merchant],Snapshot!AT66,Table1[Month],Snapshot!$W$4)*-1) | AV66: =IF(ISBLANK(AT66),"",COUNTIFS(Table1[Merchant],Snapshot!AT66,Table1[Month],Snapshot!$W$4)) | AW66: =IFERROR(RANK(AV66,$AV$6:$AV$200)+COUNTIF($AV$6:AV66,AV66)-1,"") | AX66: =IFERROR(RANK(AU66,$AU$6:$AU$200)+COUNTIF($AU$6:AU66,AU66)-1,"")
V67: =IF(ISBLANK(W67),"--",TEXT(W67,"mmmm")&" "&TEXT(W67,"YYYY")) -> -- | AU67: =IF(ISBLANK(AT67),"",SUMIFS(Table1[Amount $],Table1[Amount $],"<"&0,Table1[Merchant],Snapshot!AT67,Table1[Month],Snapshot!$W$4)*-1) | AV67: =IF(ISBLANK(AT67),"",COUNTIFS(Table1[Merchant],Snapshot!AT67,Table1[Month],Snapshot!$W$4)) | AW67: =IFERROR(RANK(AV67,$AV$6:$AV$200)+COUNTIF($AV$6:AV67,AV67)-1,"") | AX67: =IFERROR(RANK(AU67,$AU$6:$AU$200)+COUNTIF($AU$6:AU67,AU67)-1,"")
V68: =IF(ISBLANK(W68),"--",TEXT(W68,"mmmm")&" "&TEXT(W68,"YYYY")) -> -- | AU68: =IF(ISBLANK(AT68),"",SUMIFS(Table1[Amount $],Table1[Amount $],"<"&0,Table1[Merchant],Snapshot!AT68,Table1[Month],Snapshot!$W$4)*-1) | AV68: =IF(ISBLANK(AT68),"",COUNTIFS(Table1[Merchant],Snapshot!AT68,Table1[Month],Snapshot!$W$4)) | AW68: =IFERROR(RANK(AV68,$AV$6:$AV$200)+COUNTIF($AV$6:AV68,AV68)-1,"") | AX68: =IFERROR(RANK(AU68,$AU$6:$AU$200)+COUNTIF($AU$6:AU68,AU68)-1,"")
... V200: =IF(ISBLANK(W200),"--",TEXT(W200,"mmmm")&" "&TEXT(W200,"YYYY")) -> -- | AU200: =IF(ISBLANK(AT200),"",SUMIFS(Table1[Amount $],Table1[Amount $],"<"&0,Table1[Merchant],Snapshot!AT200,Table1[Month],Snapshot!$W$4)*-1) | AV200: =IF(ISBLANK(AT200),"",COUNTIFS(Table1[Merchant],Snapshot!AT200,Table1[Month],Snapshot!$W$4)) | AW200: =IFERROR(RANK(AV200,$AV$6:$AV$200)+COUNTIF($AV$6:AV200,AV200)-1,"") | AX200: =IFERROR(RANK(AU200,$AU$6:$AU$200)+COUNTIF($AU$6:AU200,AU200)-1,"")

Sheet Transactions
B2: Transactions
B3: Transactions from your added accounts are automatically imported here. Click Update in the task pane to import more transactions. Edit the Merchant and Category columns to better reflect where and how you spend your money.
B6: Date | C6: Merchant | D6: Category | E6: Amount $ | F6: Account | G6: Account Number | H6: Institution | I6: Transaction_ID | J6: Account_ID | K6: Institution_ID | L6: Category Type | M6: Date_Day | N6: Date_Month | O6: Date_Year | P6: Beginning of Week | Q6: Month
L7: {=IFERROR(INDEX(Table2[Category Type],MATCH(Table1[[#This Row],[Category]],Table2[Category Name],0),0),"")} | M7: =DAY(Table1[[#This Row],[Date]]) -> 0 | N7: =MONTH(Table1[[#This Row],[Date]]) -> 1 | O7: =YEAR(Table1[[#This Row],[Date]]) -> 1900 | P7: =IF(ISBLANK(Table1[[#This Row],[Date]]),"",Table1[[#This Row],[Date]]-WEEKDAY(Table1[[#This Row],[Date]],2)+1) | Q7: =IF(ISBLANK(Table1[[#This Row],[Date]]),"",DATE(Table1[[#This Row],[Date_Year]],Table1[[#This Row],[Date_Month]],1))
L8: {=IFERROR(INDEX(Table2[Category Type],MATCH(Table1[[#This Row],[Category]],Table2[Category Name],0),0),"")}

Sheet Categories
B2: Categories
B3: Create and edit categories in the blue cells (below the default categories) to fit your specific financial needs. Make transactions glanceable across every sheet.
G5: Categories
C6: Id | D6: Category Name | E6: Category Type | G6: Yes / No | H6: Count | I6: Order | J6: Full Categories | K6: Clean Categories
B7: Default categories These categories cannot be edited. | D7: Income | E7: Income | G7: =IF(COUNTA(Table2[[#This Row],[Category Name]:[Category Type]])=2,"YES","") -> YES | H7: =IF(G7="","",COUNTIF($G$7:G7,"YES")) -> 1 | I7: =IF(ROW()-6>MAX($H$7:$H$44),"--",ROW()-6) -> 1 | J7: {=IFERROR(INDEX(Table2[Category Name],MATCH(I7,$H$7:$H$44,0),0),"--")} -> Income | K7: {=OFFSET(Categories!$J$7,0,0,COUNTIF(Categories!$J$7:$J$44,"<>"&"--"),1)} -> Income
D8: Refund | E8: Transfer | G8: =IF(COUNTA(Table2[[#This Row],[Category Name]:[Category Type]])=2,"YES","") -> YES | H8: =IF(G8="","",COUNTIF($G$7:G8,"YES")) -> 2 | I8: =IF(ROW()-6>MAX($H$7:$H$44),"--",ROW()-6) -> 2 | J8: {=IFERROR(INDEX(Table2[Category Name],MATCH(I8,$H$7:$H$44,0),0),"--")} -> Refund | K8: Refund
D9: Transfer | E9: Transfer | G9: =IF(COUNTA(Table2[[#This Row],[Category Name]:[Category Type]])=2,"YES","") -> YES | H9: =IF(G9="","",COUNTIF($G$7:G9,"YES")) -> 3 | I9: =IF(ROW()-6>MAX($H$7:$H$44),"--",ROW()-6) -> 3 | J9: {=IFERROR(INDEX(Table2[Category Name],MATCH(I9,$H$7:$H$44,0),0),"--")} -> Transfer | K9: Transfer
D10: Auto/Transport | E10: Expense | G10: =IF(COUNTA(Table2[[#This Row],[Category Name]:[Category Type]])=2,"YES","") -> YES | H10: =IF(G10="","",COUNTIF($G$7:G10,"YES")) -> 4 | I10: =IF(ROW()-6>MAX($H$7:$H$44),"--",ROW()-6) -> 4 | J10: {=IFERROR(INDEX(Table2[Category Name],MATCH(I10,$H$7:$H$44,0),0),"--")} -> Auto/Transport | K10: Auto/Transport
D11: Bills/Utilities | E11: Expense | G11: =IF(COUNTA(Table2[[#This Row],[Category Name]:[Category Type]])=2,"YES","") -> YES | H11: =IF(G11="","",COUNTIF($G$7:G11,"YES")) -> 5 | I11: =IF(ROW()-6>MAX($H$7:$H$44),"--",ROW()-6) -> 5 | J11: {=IFERROR(INDEX(Table2[Category Name],MATCH(I11,$H$7:$H$44,0),0),"--")} -> Bills/Utilities | K11: Bills/Utilities
D12: Entertainment | E12: Expense | G12: =IF(COUNTA(Table2[[#This Row],[Category Name]:[Category Type]])=2,"YES","") -> YES | H12: =IF(G12="","",COUNTIF($G$7:G12,"YES")) -> 6 | I12: =IF(ROW()-6>MAX($H$7:$H$44),"--",ROW()-6) -> 6 | J12: {=IFERROR(INDEX(Table2[Category Name],MATCH(I12,$H$7:$H$44,0),0),"--")} -> Entertainment | K12: Entertainment
D13: Fees/Charges | E13: Expense | G13: =IF(COUNTA(Table2[[#This Row],[Category Name]:[Category Type]])=2,"YES","") -> YES | H13: =IF(G13="","",COUNTIF($G$7:G13,"YES")) -> 7 | I13: =IF(ROW()-6>MAX($H$7:$H$44),"--",ROW()-6) -> 7 | J13: {=IFERROR(INDEX(Table2[Category Name],MATCH(I13,$H$7:$H$44,0),0),"--")} -> Fees/Charges | K13: Fees/Charges
D14: Groceries | E14: Expense | G14: =IF(COUNTA(Table2[[#This Row],[Category Name]:[Category Type]])=2,"YES","") -> YES | H14: =IF(G14="","",COUNTIF($G$7:G14,"YES")) -> 8 | I14: =IF(ROW()-6>MAX($H$7:$H$44),"--",ROW()-6) -> 8 | J14: {=IFERROR(INDEX(Table2[Category Name],MATCH(I14,$H$7:$H$44,0),0),"--")} -> Groceries | K14: Groceries
D15: Health/Fitness | E15: Expense | G15: =IF(COUNTA(Table2[[#This Row],[Category Name]:[Category Type]])=2,"YES","") -> YES | H15: =IF(G15="","",COUNTIF($G$7:G15,"YES")) -> 9 | I15: =IF(ROW()-6>MAX($H$7:$H$44),"--",ROW()-6) -> 9 | J15: {=IFERROR(INDEX(Table2[Category Name],MATCH(I15,$H$7:$H$44,0),0),"--")} -> Health/Fitness | K15: Health/Fitness
D16: Home | E16: Expense | G16: =IF(COUNTA(Table2[[#This Row],[Category Name]:[Category Type]])=2,"YES","") -> YES | H16: =IF(G16="","",COUNTIF($G$7:G16,"YES")) -> 10 | I16: =IF(ROW()-6>MAX($H$7:$H$44),"--",ROW()-6) -> 10 | J16: {=IFERROR(INDEX(Table2[Category Name],MATCH(I16,$H$7:$H$44,0),0),"--")} -> Home | K16: Home
D17: Misc | E17: Expense | G17: =IF(COUNTA(Table2[[#This Row],[Category Name]:[Category Type]])=2,"YES","") -> YES | H17: =IF(G17="","",COUNTIF($G$7:G17,"YES")) -> 11 | I17: =IF(ROW()-6>MAX($H$7:$H$44),"--",ROW()-6) -> 11 | J17: {=IFERROR(INDEX(Table2[Category Name],MATCH(I17,$H$7:$H$44,0),0),"--")} -> Misc | K17: Misc
D18: Mortgage/Rent | E18: Expense | G18: =IF(COUNTA(Table2[[#This Row],[Category Name]:[Category Type]])=2,"YES","") -> YES | H18: =IF(G18="","",COUNTIF($G$7:G18,"YES")) -> 12 | I18: =IF(ROW()-6>MAX($H$7:$H$44),"--",ROW()-6) -> 12 | J18: {=IFERROR(INDEX(Table2[Category Name],MATCH(I18,$H$7:$H$44,0),0),"--")} -> Mortgage/Rent | K18: Mortgage/Rent
D19: Payment | E19: Expense | G19: =IF(COUNTA(Table2[[#This Row],[Category Name]:[Category Type]])=2,"YES","") -> YES | H19: =IF(G19="","",COUNTIF($G$7:G19,"YES")) -> 13 | I19: =IF(ROW()-6>MAX($H$7:$H$44),"--",ROW()-6) -> 13 | J19: {=IFERROR(INDEX(Table2[Category Name],MATCH(I19,$H$7:$H$44,0),0),"--")} -> Payment | K19: Payment
... D24: Uncategorized | E24: Expense | G24: =IF(COUNTA(Table2[[#This Row],[Category Name]:[Category Type]])=2,"YES","") -> YES | H24: =IF(G24="","",COUNTIF($G$7:G24,"YES")) -> 18 | I24: =IF(ROW()-6>MAX($H$7:$H$44),"--",ROW()-6) -> 18 | J24: {=IFERROR(INDEX(Table2[Category Name],MATCH(I24,$H$7:$H$44,0),0),"--")} -> Uncategorized | K24: Uncategorized
B25: Custom categories Add your own categories in column D and set the category type in column E. We'll remove duplicate categories automatically. | G25: =IF(COUNTA(Table2[[#This Row],[Category Name]:[Category Type]])=2,"YES","") | H25: =IF(G25="","",COUNTIF($G$7:G25,"YES")) | I25: =IF(ROW()-6>MAX($H$7:$H$44),"--",ROW()-6) -> -- | J25: {=IFERROR(INDEX(Table2[Category Name],MATCH(I25,$H$7:$H$44,0),0),"--")} -> --
G26: =IF(COUNTA(Table2[[#This Row],[Category Name]:[Category Type]])=2,"YES","") | H26: =IF(G26="","",COUNTIF($G$7:G26,"YES")) | I26: =IF(ROW()-6>MAX($H$7:$H$44),"--",ROW()-6) -> -- | J26: {=IFERROR(INDEX(Table2[Category Name],MATCH(I26,$H$7:$H$44,0),0),"--")} -> --
G27: =IF(COUNTA(Table2[[#This Row],[Category Name]:[Category Type]])=2,"YES","") | H27: =IF(G27="","",COUNTIF($G$7:G27,"YES")) | I27: =IF(ROW()-6>MAX($H$7:$H$44),"--",ROW()-6) -> -- | J27: {=IFERROR(INDEX(Table2[Category Name],MATCH(I27,$H$7:$H$44,0),0),"--")} -> --
G28: =IF(COUNTA(Table2[[#This Row],[Category Name]:[Category Type]])=2,"YES","") | H28: =IF(G28="","",COUNTIF($G$7:G28,"YES")) | I28: =IF(ROW()-6>MAX($H$7:$H$44),"--",ROW()-6) -> -- | J28: {=IFERROR(INDEX(Table2[Category Name],MATCH(I28,$H$7:$H$44,0),0),"--")} -> --
G29: =IF(COUNTA(Table2[[#This Row],[Category Name]:[Category Type]])=2,"YES","") | H29: =IF(G29="","",COUNTIF($G$7:G29,"YES")) | I29: =IF(ROW()-6>MAX($H$7:$H$44),"--",ROW()-6) -> -- | J29: {=IFERROR(INDEX(Table2[Category Name],MATCH(I29,$H$7:$H$44,0),0),"--")} -> --
G30: =IF(COUNTA(Table2[[#This Row],[Category Name]:[Category Type]])=2,"YES","") | H30: =IF(G30="","",COUNTIF($G$7:G30,"YES")) | I30: =IF(ROW()-6>MAX($H$7:$H$44),"--",ROW()-6) -> -- | J30: {=IFERROR(INDEX(Table2[Category Name],MATCH(I30,$H$7:$H$44,0),0),"--")} -> --
G31: =IF(COUNTA(Table2[[#This Row],[Category Name]:[Category Type]])=2,"YES","") | H31: =IF(G31="","",COUNTIF($G$7:G31,"YES")) | I31: =IF(ROW()-6>MAX($H$7:$H$44),"--",ROW()-6) -> -- | J31: {=IFERROR(INDEX(Table2[Category Name],MATCH(I31,$H$7:$H$44,0),0),"--")} -> --
G32: =IF(COUNTA(Table2[[#This Row],[Category Name]:[Category Type]])=2,"YES","") | H32: =IF(G32="","",COUNTIF($G$7:G32,"YES")) | I32: =IF(ROW()-6>MAX($H$7:$H$44),"--",ROW()-6) -> -- | J32: {=IFERROR(INDEX(Table2[Category Name],MATCH(I32,$H$7:$H$44,0),0),"--")} -> --
G33: =IF(COUNTA(Table2[[#This Row],[Category Name]:[Category Type]])=2,"YES","") | H33: =IF(G33="","",COUNTIF($G$7:G33,"YES")) | I33: =IF(ROW()-6>MAX($H$7:$H$44),"--",ROW()-6) -> -- | J33: {=IFERROR(INDEX(Table2[Category Name],MATCH(I33,$H$7:$H$44,0),0),"--")} -> --
G34: =IF(COUNTA(Table2[[#This Row],[Category Name]:[Category Type]])=2,"YES","") | H34: =IF(G34="","",COUNTIF($G$7:G34,"YES")) | I34: =IF(ROW()-6>MAX($H$7:$H$44),"--",ROW()-6) -> -- | J34: {=IFERROR(INDEX(Table2[Category Name],MATCH(I34,$H$7:$H$44,0),0),"--")} -> --
G35: =IF(COUNTA(Table2[[#This Row],[Category Name]:[Category Type]])=2,"YES","") | H35: =IF(G35="","",COUNTIF($G$7:G35,"YES")) | I35: =IF(ROW()-6>MAX($H$7:$H$44),"--",ROW()-6) -> -- | J35: {=IFERROR(INDEX(Table2[Category Name],MATCH(I35,$H$7:$H$44,0),0),"--")} -> --
G36: =IF(COUNTA(Table2[[#This Row],[Category Name]:[Category Type]])=2,"YES","") | H36: =IF(G36="","",COUNTIF($G$7:G36,"YES")) | I36: =IF(ROW()-6>MAX($H$7:$H$44),"--",ROW()-6) -> -- | J36: {=IFERROR(INDEX(Table2[Category Name],MATCH(I36,$H$7:$H$44,0),0),"--")} -> --
G37: =IF(COUNTA(Table2[[#This Row],[Category Name]:[Category Type]])=2,"YES","") | H37: =IF(G37="","",COUNTIF($G$7:G37,"YES")) | I37: =IF(ROW()-6>MAX($H$7:$H$44),"--",ROW()-6) -> -- | J37: {=IFERROR(INDEX(Table2[Category Name],MATCH(I37,$H$7:$H$44,0),0),"--")} -> --
... G44: =IF(COUNTA(Table2[[#This Row],[Category Name]:[Category Type]])=2,"YES","") | H44: =IF(G44="","",COUNTIF($G$7:G44,"YES")) | I44: =IF(ROW()-6>MAX($H$7:$H$44),"--",ROW()-6) -> -- | J44: {=IFERROR(INDEX(Table2[Category Name],MATCH(I44,$H$7:$H$44,0),0),"--")} -> --
