Workbook

Sheet Output
C2: Aid Pioneers 'menu' of medical supplies available to send to Ukraine
C3: Note: A single forty-foot shipping container can hold ~700 boxes, collectively worth approx. $400K; each container costs us approx. $20K to send
H4: Please complete!
C5: HS Code | D5: Product code | E5: Description | F5: Quantity / box | G5: Average no. of boxes / shipment | H5: Quantity needed | I5: Priority (1 - highest, 3 - is lowest) | J5: Recipient hospital (if delivering to multiple hospitals)
C6: 101 | D6: 3926100000 | E6: Office Supplies, ALL | F6: Unknown | G6: 2
C7: 301 | D7: 6302210000 | E7: Bed Linens And Towels | F7: Unknown | G7: 11.888889
C8: 302 | D8: 6307909800 | E8: Surgical Caps And Hats, Shoe Covers | F8: 1550 | G8: 15
C9: 303 | D9: 6307.90.9995 | E9: Cloth Products Not Fitting In Other Items, Cubical Curtains | F9: Unknown | G9: 5
C10: 305.99 | D10: 3926201010 | E10: Gloves, Non-sterile | F10: 325 | G10: 43.333333
C11: 306 | D11: 3926201010 | E11: Gloves, Non-sterile | F11: Unknown | G11: 31.666667
C12: 306.99 | D12: 3926201010 | E12: Gloves, Sterile | F12: Unknown | G12: 10
C13: 307 | D13: 3926201010 | E13: Gloves, Sterile | F13: Unknown | G13: 6.6666667
C14: 307 | D14: 9004909000 | E14: Goggles and Face Protection | F14: Unknown | G14: 10
C15: 307 | D15: 9004909000 | E15: Masks, surgical | F15: Unknown | G15: 5
C16: 307.199 | D16: 9004909000 | E16: Masks, surgical | F16: Unknown | G16: 18
C17: 307.299 | D17: 9004909000 | E17: Goggles and Face Protection | F17: Unknown | G17: 22
C18: 307.3 | D18: 9004909000 | E18: Masks, Cloth | F18: Unknown | G18: 15
C19: 307.99 | D19: 9004909000 | E19: Goggles, Masks, and Face Protection | F19: 97.5 | G19: 16.25
C20: 308 | D20: 4823909000 | E20: Gowns, Isolation Level 1 and Level 2 | F20: Unknown | G20: 10
C21: 308 | D21: 4823909000 | E21: Gowns, Isolation or Biohazard, Level 3 and Level 4 | F21: Unknown | G21: 5
C22: 308 | D22: 4823909000 | E22: Gowns, Patient (incl. Cloth, Paper Protector, Cover- up) | F22: Unknown | G22: 26.666667
C23: 308 | D23: 9004909000 | E23: Goggles, Masks, and Face Protection | F23: Unknown | G23: 30
C24: 308.199 | D24: 4823909000 | E24: Gowns, Isolation Level 1 and Level 2 | F24: 97.5 | G24: 14
C25: 308.299 | D25: 4823909000 | E25: Gowns, Isolation or Biohazard, Level 3 and Level 4 | F25: 97.5 | G25: 20
C26: 308.99 | D26: 4823909000 | E26: Gowns, Patient (incl. Cloth, Paper Protector, Cover- up) | F26: 52.5 | G26: 16.25
C27: 309 | D27: 4823909000 | E27: Gowns, Patient (incl. Cloth, Paper Protector, Cover- up) | F27: 52.5 | G27: 10
C28: 309 | D28: 4823909000 | E28: Gowns, Surgical, Non-sterile | F28: 52.5 | G28: 21.25
C29: 310.99 | D29: 6211320000 | E29: Gowns, Surgical, Sterile | F29: Unknown | G29: 31.875
C30: 311 | D30: 6211320000 | E30: Gowns, Surgical, Sterile | F30: Unknown | G30: 30
C31: 311 | D31: 6211320000 | E31: Lab Coats And Tunics, Scrub Suits, Surgical | F31: Unknown | G31: 16.428571
C32: 311.1 | D32: 6211320000 | E32: Scrubs, FIG | F32: Unknown | G32: 10
C33: 312 | D33: 9004909000 | E33: BYD Masks | F33: Unknown | G33: 15
C34: 312.99 | D34: 9004909000 | E34: N-95 Masks | F34: 1050 | G34: 25
C35: 313 | D35: 9004909000 | E35: N-95 Masks | F35: Unknown | G35: 20
C36: 313.99 | D36: 6307.90.9889 | E36: KN95 - Masks | F36: Unknown | G36: 26.666667
C37: 314 | D37: 6307.90.9889 | E37: KN95 - Masks | F37: Unknown | G37: 5
C38: 401.99 | D38: 4421900000 | E38: Dental Supplies | F38: Unknown | G38: 10
C39: 501.99 | D39: 3006100100 | E39: 2x2, 4x4, Abd Sterile Dressings | F39: Unknown | G39: 9
C40: 502 | D40: 3006100100 | E40: 2x2, 4x4, Abd Sterile Dressings | F40: Unknown | G40: 5
C41: 504.99 | D41: 3005909900 | E41: Bandaids, Steristrips, Tape, Transparent Dressings (tegaderm) | F41: 214.5 | G41: 15
C42: 505 | D42: 3005909900 | E42: Bandaids, Steristrips, Tape, Transparent Dressings (tegaderm) | F42: Unknown | G42: 10
C43: 505.99 | D43: 3005590000 | E43: Dressing Change Kits, Laceration Trays, Wound Care Kits | F43: Unknown | G43: 3.5
C44: 506 | D44: 3005590000 | E44: Dressing Change Kits, Laceration Trays, Wound Care Kits | F44: Unknown | G44: 7.5
C45: 506.99 | D45: 3005900000 | E45: Gauze and All Other Non Sterile Dressings | F45: Unknown | G45: 4.8
C46: 507 | D46: 3005900000 | E46: Gauze and All Other Non Sterile Dressings | F46: Unknown | G46: 10
C47: 507.99 | D47: 3005909900 | E47: Kerlix/Kling Dressing | F47: Unknown | G47: 4.8
C48: 508 | D48: 3005909900 | E48: Kerlix/Kling Dressing | F48: Unknown | G48: 5
C49: 510 | D49: 3005909900 | E49: Trauma Dressing | F49: Unknown | G49: 1
C50: 511.99 | D50: 3006100100 | E50: Specialty Dressings (and All Other Dressings Not Fitting In Other Categories) | F50: Unknown | G50: 7.125
C51: 512 | D51: 3006100100 | E51: Specialty Dressings (and All Other Dressings Not Fitting In Other Categories) | F51: Unknown | G51: 6.6666667
C52: 601 | D52: 3006500000 | E52: Bags, Red, Spill Kits And Isolyszer | F52: Unknown | G52: 7.1111111
C53: 602.99 | D53: 3808940000 | E53: Disinfectant, Non-Patient; Also Sterilization Products & Sprays (Cidex, Etc) | F53: Unknown | G53: 13.333333
C54: 604 | D54: 3923100000 | E54: Liners, Trash Can, Laundry & Plastic Bags, Mopheads | F54: 65 | G54: 10
C55: 606 | D55: 3923100000 | E55: Sharps Containers, Send Only w/ Lids | F55: Unknown | G55: 8
C56: 608.99 | D56: 3006101000 | E56: Sterilization, Tapes, Indicators, Wraps & Pouches | F56: Unknown | G56: 7.4285714
C57: 609 | D57: 3006101000 | E57: Sterilization, Tapes, Indicators, Wraps & Pouches | F57: Unknown | G57: 5
C58: 701.99 | D58: 9018390000 | E58: Buffalo caps, prn adaptors and other iv infusion supplies, vial spikes and adaptators | F58: 390 | G58: 4.6666667
C59: 702 | D59: 9018390000 | E59: Buffalo caps, prn adaptors and other iv infusion supplies, vial spikes and adaptators | F59: Unknown | G59: 3.5
C60: 702.99 | D60: 9018390000 | E60: Central Percutaneous Lines | F60: Unknown | G60: 2.8
C61: 703 | D61: 9018390000 | E61: Central Percutaneous Lines | F61: Unknown | G61: 4
C62: 703.99 | D62: 9018390030 | E62: IV Catheters/ Including Huber, Butterfly, Fistula | F62: 135 | G62: 5
C63: 704 | D63: 9018390030 | E63: IV Catheters/ Including Huber, Butterfly, Fistula | F63: Unknown | G63: 8.3333333
C64: 704.99 | D64: 9018390000 | E64: IV Extension & Secondary Tubing | F64: 65 | G64: 10.5
C65: 705 | D65: 9018390000 | E65: IV Extension & Secondary Tubing | F65: Unknown | G65: 5
C66: 705.99 | D66: 9018390000 | E66: IV Primary Tubing, Including Blood Tubing | F66: 91 | G66: 13
C67: 706 | D67: 9018390000 | E67: IV Primary Tubing, Including Blood Tubing | F67: Unknown | G67: 6.6666667
C68: 706.99 | D68: 9018390000 | E68: IV Start Kits & Sets | F68: 1000 | G68: 2
C69: 707 | D69: 9018390000 | E69: IV Start Kits & Sets | F69: Unknown | G69: 2
C70: 708.99 | D70: 9018310040 | E70: Needles, Mixed Gauges | F70: 682.5 | G70: 22.5
C71: 709 | D71: 9018310040 | E71: Needles, Mixed Gauges | F71: Unknown | G71: 11.666667
C72: 709.99 | D72: 9018310040 | E72: Syringes, 1 cc/tb | F72: 500 | G72: 10.714286
C73: 710 | D73: 9018310040 | E73: Syringes, 1 cc/tb | F73: Unknown | G73: 5.6666667
C74: 710.99 | D74: 9018310040 | E74: Syringes, 3cc | F74: 500 | G74: 17.727273
C75: 711 | D75: 9018310040 | E75: Syringes, 3cc | F75: Unknown | G75: 5.6666667
C76: 711.99 | D76: 9018310040 | E76: Syringes, 5cc & 6cc | F76: 275 | G76: 10
C77: 712 | D77: 9018310040 | E77: Syringes, 5cc & 6cc | F77: Unknown | G77: 8.3333333
C78: 712.99 | D78: 9018310040 | E78: Syringes, 10cc & 12cc | F78: 120 | G78: 25.625
C79: 713 | D79: 9018310040 | E79: Syringes, 10cc & 12cc | F79: Unknown | G79: 8.3333333
C80: 713.99 | D80: 9018310040 | E80: Syringes, 20cc | F80: Unknown | G80: 7.5
C81: 714 | D81: 9018310040 | E81: Syringes, 20cc | F81: Unknown | G81: 3.5
C82: 714.99 | D82: 9018310040 | E82: Syringes, 30cc and 60cc | F82: Unknown | G82: 8.75
C83: 715 | D83: 9018310040 | E83: Syringes, 30cc and 60cc | F83: Unknown | G83: 6
C84: 716.99 | D84: 9018310040 | E84: Syringes, Insulin | F84: 591.5 | G84: 12
C85: 717 | D85: 9018310040 | E85: Syringes, Insulin | F85: Unknown | G85: 2
C86: 801.99 | D86: 9018900000 | E86: Blood Drawing Supplies (Vacutainer Holders & Needles, Butterflies, Lancets, Tourniquets) | F86: Unknown | G86: 4.6666667
C87: 802 | D87: 9018900000 | E87: Blood Drawing Supplies (Vacutainer Holders & Needles, Butterflies, Lancets, Tourniquets) | F87: Unknown | G87: 5
C88: 803.99 | D88: 3923100000 | E88: Containers and Labels, Lab | F88: 130 | G88: 4.25
C89: 804 | D89: 3923100000 | E89: Containers and Labels, Lab | F89: Unknown | G89: 7.5
C90: 901 | D90: 3926900000 | E90: Medication Cups, Spoons and Labels, Pill Crushers, Counters, Holders for Tubex Syringes | F90: Unknown | G90: 10
C91: 901.99 | D91: 3926900000 | E91: Medication Cups, Spoons and Labels, Pill Crushers, Counters, Holders for Tubex Syringes | F91: Unknown | G91: 2.6666667
C92: 1001.99 | D92: 9619008101 | E92: Baby and birthing supplies | F92: Unknown | G92: 5
C93: 1002 | D93: 9619008101 | E93: Baby and birthing supplies | F93: Unknown | G93: 5
C94: 1004 | D94: 9619009000 | E94: Diapers and Wipes | F94: Unknown | G94: 14.6
C95: 1006 | D95: 9619009000 | E95: Feminine Supplies - (including Pads, Belts, Perineal Wash, Sitz Baths) | F95: Unknown | G95: 10
C96: 1101 | D96: 3005900000 | E96: Activities Of Daily Living Aids (including Dressing Aids), Pt Supplies | F96: Unknown | G96: 5.4
C97: 1103.99 | D97: 3005909900 | E97: Casting Supplies, Stockinette, Web Roll, Plaster, Fiberglass, Cast Shoes, Cast Heels | F97: Unknown | G97: 9
C98: 1104 | D98: 3005909900 | E98: Casting Supplies, Stockinette, Web Roll, Plaster, Fiberglass, Cast Shoes, Cast Heels | F98: Unknown | G98: 10
C99: 1106 | D99: 9404909000 | E99: Pads, Wedges, Positioning Pillows | F99: 47.5 | G99: 11.125
C100: 1108 | D100: 9021109000 | E100: Splints, Wraps (including Ace), and Slings, Hose Ted (anti- embolism) | F100: Unknown
C101: 1108 | D101: 9021109000 | E101: Splints, Wraps (including Ace), and Slings, Hose Ted (anti-embolism) | F101: Unknown | G101: 21.545455
...

Sheet Analysis>>>

Sheet Pivot
A3: Product Code | B3: HS Code | C3: Description | D3: Quantity / box | E3: Average of Number Ordered
A4: 101 | B4: 3926100000 | C4: Office Supplies, ALL | D4: NA | E4: 2
A5: 301 | B5: 6302210000 | C5: Bed Linens And Towels | D5: NA | E5: 11.888889
A6: 302 | B6: 6307909800 | C6: Surgical Caps And Hats, Shoe Covers | D6: 1550 | E6: 15
A7: 303 | B7: 6307.90.9995 | C7: Cloth Products Not Fitting In Other Items, Cubical Curtains | D7: NA | E7: 5
A8: 305.99 | B8: 3926201010 | C8: Gloves, Non-sterile | D8: 325 | E8: 43.333333
A9: 306 | B9: 3926201010 | C9: Gloves, Non-sterile | D9: NA | E9: 31.666667
A10: 306.99 | B10: 3926201010 | C10: Gloves, Sterile | D10: NA | E10: 10
A11: 307 | B11: 3926201010 | C11: Gloves, Sterile | D11: NA | E11: 6.6666667
B12: 9004909000 | C12: Goggles and Face Protection | D12: NA | E12: 10
C13: Masks, surgical | D13: NA | E13: 5
A14: 307.199 | B14: 9004909000 | C14: Masks, surgical | D14: NA | E14: 18
A15: 307.299 | B15: 9004909000 | C15: Goggles and Face Protection | D15: NA | E15: 22
A16: 307.3 | B16: 9004909000 | C16: Masks, Cloth | D16: NA | E16: 15
A17: 307.99 | B17: 9004909000 | C17: Goggles, Masks, and Face Protection | D17: 97.5 | E17: 16.25
A18: 308 | B18: 4823909000 | C18: Gowns, Isolation Level 1 and Level 2 | D18: NA | E18: 10
C19: Gowns, Isolation or Biohazard, Level 3 and Level 4 | D19: NA | E19: 5
C20: Gowns, Patient (incl. Cloth, Paper Protector, Cover- up) | D20: NA | E20: 26.666667
B21: 9004909000 | C21: Goggles, Masks, and Face Protection | D21: NA | E21: 30
A22: 308.199 | B22: 4823909000 | C22: Gowns, Isolation Level 1 and Level 2 | D22: 97.5 | E22: 14
A23: 308.299 | B23: 4823909000 | C23: Gowns, Isolation or Biohazard, Level 3 and Level 4 | D23: 97.5 | E23: 20
A24: 308.99 | B24: 4823909000 | C24: Gowns, Patient (incl. Cloth, Paper Protector, Cover- up) | D24: 52.5 | E24: 16.25
A25: 309 | B25: 4823909000 | C25: Gowns, Patient (incl. Cloth, Paper Protector, Cover- up) | D25: 52.5 | E25: 10
C26: Gowns, Surgical, Non-sterile | D26: 52.5 | E26: 21.25
A27: 310.99 | B27: 6211320000 | C27: Gowns, Surgical, Sterile | D27: NA | E27: 31.875
A28: 311 | B28: 6211320000 | C28: Gowns, Surgical, Sterile | D28: NA | E28: 30
C29: Lab Coats And Tunics, Scrub Suits, Surgical | D29: NA | E29: 16.428571
A30: 311.1 | B30: 6211320000 | C30: Scrubs, FIG | D30: NA | E30: 10
A31: 312 | B31: 9004909000 | C31: BYD Masks | D31: NA | E31: 15
A32: 312.99 | B32: 9004909000 | C32: N-95 Masks | D32: 1050 | E32: 25
A33: 313 | B33: 9004909000 | C33: N-95 Masks | D33: NA | E33: 20
A34: 313.99 | B34: 6307.90.9889 | C34: KN95 - Masks | D34: NA | E34: 26.666667
A35: 314 | B35: 6307.90.9889 | C35: KN95 - Masks | D35: NA | E35: 5
A36: 401.99 | B36: 4421900000 | C36: Dental Supplies | D36: NA | E36: 10
A37: 501.99 | B37: 3006100100 | C37: 2x2, 4x4, Abd Sterile Dressings | D37: NA | E37: 9
A38: 502 | B38: 3006100100 | C38: 2x2, 4x4, Abd Sterile Dressings | D38: NA | E38: 5
A39: 504.99 | B39: 3005909900 | C39: Bandaids, Steristrips, Tape, Transparent Dressings (tegaderm) | D39: 214.5 | E39: 15
A40: 505 | B40: 3005909900 | C40: Bandaids, Steristrips, Tape, Transparent Dressings (tegaderm) | D40: NA | E40: 10
A41: 505.99 | B41: 3005590000 | C41: Dressing Change Kits, Laceration Trays, Wound Care Kits | D41: NA | E41: 3.5
A42: 506 | B42: 3005590000 | C42: Dressing Change Kits, Laceration Trays, Wound Care Kits | D42: NA | E42: 7.5
A43: 506.99 | B43: 3005900000 | C43: Gauze and All Other Non Sterile Dressings | D43: NA | E43: 4.8
A44: 507 | B44: 3005900000 | C44: Gauze and All Other Non Sterile Dressings | D44: NA | E44: 10
A45: 507.99 | B45: 3005909900 | C45: Kerlix/Kling Dressing | D45: NA | E45: 4.8
A46: 508 | B46: 3005909900 | C46: Kerlix/Kling Dressing | D46: NA | E46: 5
A47: 510 | B47: 3005909900 | C47: Trauma Dressing | D47: NA | E47: 1
A48: 511.99 | B48: 3006100100 | C48: Specialty Dressings (and All Other Dressings Not Fitting In Other Categories) | D48: NA | E48: 7.125
A49: 512 | B49: 3006100100 | C49: Specialty Dressings (and All Other Dressings Not Fitting In Other Categories) | D49: NA | E49: 6.6666667
A50: 601 | B50: 3006500000 | C50: Bags, Red, Spill Kits And Isolyszer | D50: NA | E50: 7.1111111
A51: 602.99 | B51: 3808940000 | C51: Disinfectant, Non-Patient; Also Sterilization Products & Sprays (Cidex, Etc) | D51: NA | E51: 13.333333
A52: 604 | B52: 3923100000 | C52: Liners, Trash Can, Laundry & Plastic Bags, Mopheads | D52: 65 | E52: 10
A53: 606 | B53: 3923100000 | C53: Sharps Containers, Send Only w/ Lids | D53: NA | E53: 8
A54: 608.99 | B54: 3006101000 | C54: Sterilization, Tapes, Indicators, Wraps & Pouches | D54: NA | E54: 7.4285714
A55: 609 | B55: 3006101000 | C55: Sterilization, Tapes, Indicators, Wraps & Pouches | D55: NA | E55: 5
A56: 701.99 | B56: 9018390000 | C56: Buffalo caps, prn adaptors and other iv infusion supplies, vial spikes and adaptators | D56: 390 | E56: 4.6666667
A57: 702 | B57: 9018390000 | C57: Buffalo caps, prn adaptors and other iv infusion supplies, vial spikes and adaptators | D57: NA | E57: 3.5
A58: 702.99 | B58: 9018390000 | C58: Central Percutaneous Lines | D58: NA | E58: 2.8
A59: 703 | B59: 9018390000 | C59: Central Percutaneous Lines | D59: NA | E59: 4
A60: 703.99 | B60: 9018390030 | C60: IV Catheters/ Including Huber, Butterfly, Fistula | D60: 135 | E60: 5
A61: 704 | B61: 9018390030 | C61: IV Catheters/ Including Huber, Butterfly, Fistula | D61: NA | E61: 8.3333333
A62: 704.99 | B62: 9018390000 | C62: IV Extension & Secondary Tubing | D62: 65 | E62: 10.5
A63: 705 | B63: 9018390000 | C63: IV Extension & Secondary Tubing | D63: NA | E63: 5
A64: 705.99 | B64: 9018390000 | C64: IV Primary Tubing, Including Blood Tubing | D64: 91 | E64: 13
A65: 706 | B65: 9018390000 | C65: IV Primary Tubing, Including Blood Tubing | D65: NA | E65: 6.6666667
A66: 706.99 | B66: 9018390000 | C66: IV Start Kits & Sets | D66: 1000 | E66: 2
A67: 707 | B67: 9018390000 | C67: IV Start Kits & Sets | D67: NA | E67: 2
A68: 708.99 | B68: 9018310040 | C68: Needles, Mixed Gauges | D68: 682.5 | E68: 22.5
A69: 709 | B69: 9018310040 | C69: Needles, Mixed Gauges | D69: NA | E69: 11.666667
A70: 709.99 | B70: 9018310040 | C70: Syringes, 1 cc/tb | D70: 500 | E70: 10.714286
A71: 710 | B71: 9018310040 | C71: Syringes, 1 cc/tb | D71: NA | E71: 5.6666667
A72: 710.99 | B72: 9018310040 | C72: Syringes, 3cc | D72: 500 | E72: 17.727273
A73: 711 | B73: 9018310040 | C73: Syringes, 3cc | D73: NA | E73: 5.6666667
A74: 711.99 | B74: 9018310040 | C74: Syringes, 5cc & 6cc | D74: 275 | E74: 10
A75: 712 | B75: 9018310040 | C75: Syringes, 5cc & 6cc | D75: NA | E75: 8.3333333
A76: 712.99 | B76: 9018310040 | C76: Syringes, 10cc & 12cc | D76: 120 | E76: 25.625
A77: 713 | B77: 9018310040 | C77: Syringes, 10cc & 12cc | D77: NA | E77: 8.3333333
A78: 713.99 | B78: 9018310040 | C78: Syringes, 20cc | D78: NA | E78: 7.5
A79: 714 | B79: 9018310040 | C79: Syringes, 20cc | D79: NA | E79: 3.5
A80: 714.99 | B80: 9018310040 | C80: Syringes, 30cc and 60cc | D80: NA | E80: 8.75
A81: 715 | B81: 9018310040 | C81: Syringes, 30cc and 60cc | D81: NA | E81: 6
A82: 716.99 | B82: 9018310040 | C82: Syringes, Insulin | D82: 591.5 | E82: 12
A83: 717 | B83: 9018310040 | C83: Syringes, Insulin | D83: NA | E83: 2
A84: 801.99 | B84: 9018900000 | C84: Blood Drawing Supplies (Vacutainer Holders & Needles, Butterflies, Lancets, Tourniquets) | D84: NA | E84: 4.6666667
A85: 802 | B85: 9018900000 | C85: Blood Drawing Supplies (Vacutainer Holders & Needles, Butterflies, Lancets, Tourniquets) | D85: NA | E85: 5
A86: 803.99 | B86: 3923100000 | C86: Containers and Labels, Lab | D86: 130 | E86: 4.25
A87: 804 | B87: 3923100000 | C87: Containers and Labels, Lab | D87: NA | E87: 7.5
A88: 901 | B88: 3926900000 | C88: Medication Cups, Spoons and Labels, Pill Crushers, Counters, Holders for Tubex Syringes | D88: NA | E88: 10
A89: 901.99 | B89: 3926900000 | C89: Medication Cups, Spoons and Labels, Pill Crushers, Counters, Holders for Tubex Syringes | D89: NA | E89: 2.6666667
A90: 1001.99 | B90: 9619008101 | C90: Baby and birthing supplies | D90: NA | E90: 5
A91: 1002 | B91: 9619008101 | C91: Baby and birthing supplies | D91: NA | E91: 5
A92: 1004 | B92: 9619009000 | C92: Diapers and Wipes | D92: NA | E92: 14.6
A93: 1006 | B93: 9619009000 | C93: Feminine Supplies - (including Pads, Belts, Perineal Wash, Sitz Baths) | D93: NA | E93: 10
A94: 1101 | B94: 3005900000 | C94: Activities Of Daily Living Aids (including Dressing Aids), Pt Supplies | D94: NA | E94: 5.4
A95: 1103.99 | B95: 3005909900 | C95: Casting Supplies, Stockinette, Web Roll, Plaster, Fiberglass, Cast Shoes, Cast Heels | D95: NA | E95: 9
A96: 1104 | B96: 3005909900 | C96: Casting Supplies, Stockinette, Web Roll, Plaster, Fiberglass, Cast Shoes, Cast Heels | D96: NA | E96: 10
A97: 1106 | B97: 9404909000 | C97: Pads, Wedges, Positioning Pillows | D97: 47.5 | E97: 11.125
A98: 1108 | B98: 9021109000 | C98: Splints, Wraps (including Ace), and Slings, Hose Ted (anti- embolism) | D98: NA
C99: Splints, Wraps (including Ace), and Slings, Hose Ted (anti-embolism) | D99: NA | E99: 21.545455
A100: 1109 | B100: 9021.10.99 | C100: Braces | D100: NA | E100: 2
A101: 1201 | B101: 7017900000 | C101: Admission Kits | D101: NA | E101: 3.5
A102: 1202.99 | B102: 3005905000 | C102: Applicator Swabs (Q-Tips), Tongue Depressors, Cotton Balls | D102: NA | E102: 3
...

Sheet Aggregated Data
A1: Shipment | B1: Unique ID | C1: Product Code | D1: HS Code | E1: Description | F1: Average quantity per shipment | G1: Quantity / box | H1: Number Ordered | I1: Pieces/ Cartons | J1: Total Quantity | K1: Net Weight (kg) | L1: Unit Value ($) | M1: Total Value ($) | N1: Country destination
A2: 22203 | B2: =C2&D2&E2 -> 3016302210000Bed Linens And Towels | C2: 301 | D2: 6302210000 | E2: Bed Linens And Towels | G2: {=IFERROR(INDEX('Quantity in each box'!$H$8:$H$153,MATCH('Aggregated Data'!C2,'Quantity in each box'!$E$8:$E$153,0)),"NA")} -> NA | H2: 10 | K2: 22203 | M2: 22203 | N2: Ukraine
A3: 22203 | B3: =C3&D3&E3 -> 3026307909800Surgical Caps And Hats, Shoe Covers | C3: 302 | D3: 6307909800 | E3: Surgical Caps And Hats, Shoe Covers | G3: {=IFERROR(INDEX('Quantity in each box'!$H$8:$H$153,MATCH('Aggregated Data'!C3,'Quantity in each box'!$E$8:$E$153,0)),"NA")} -> 1550 | H3: 5 | K3: 22214 | M3: 72224 | N3: Ukraine
A4: 22203 | B4: =C4&D4&E4 -> 3063926201010Gloves, Non-sterile | C4: 306 | D4: 3926201010 | E4: Gloves, Non-sterile | G4: {=IFERROR(INDEX('Quantity in each box'!$H$8:$H$153,MATCH('Aggregated Data'!C4,'Quantity in each box'!$E$8:$E$153,0)),"NA")} -> NA | H4: 30 | K4: 52216 | M4: 52216 | N4: Ukraine
A5: 22203 | B5: =C5&D5&E5 -> 3073926201010Gloves, Sterile | C5: 307 | D5: 3926201010 | E5: Gloves, Sterile | G5: {=IFERROR(INDEX('Quantity in each box'!$H$8:$H$153,MATCH('Aggregated Data'!C5,'Quantity in each box'!$E$8:$E$153,0)),"NA")} -> NA | H5: 5 | K5: 42218 | M5: 42215 | N5: Ukraine
A6: 22203 | B6: =C6&D6&E6 -> 3084823909000Gowns, Isolation Level 1 and Level 2 | C6: 308 | D6: 4823909000 | E6: Gowns, Isolation Level 1 and Level 2 | G6: {=IFERROR(INDEX('Quantity in each box'!$H$8:$H$153,MATCH('Aggregated Data'!C6,'Quantity in each box'!$E$8:$E$153,0)),"NA")} -> NA | H6: 10 | K6: 42215 | M6: 42218 | N6: Ukraine
A7: 22203 | B7: =C7&D7&E7 -> 3094823909000Gowns, Patient (incl. Cloth, Paper Protector, Cover- up) | C7: 309 | D7: 4823909000 | E7: Gowns, Patient (incl. Cloth, Paper Protector, Cover- up) | G7: {=IFERROR(INDEX('Quantity in each box'!$H$8:$H$153,MATCH('Aggregated Data'!C7,'Quantity in each box'!$E$8:$E$153,0)),"NA")} -> 52.5 | H7: 10 | K7: 72224 | M7: 22214 | N7: Ukraine
A8: 22203 | B8: =C8&D8&E8 -> 3094823909000Gowns, Surgical, Non-sterile | C8: 309 | D8: 4823909000 | E8: Gowns, Surgical, Non-sterile | G8: {=IFERROR(INDEX('Quantity in each box'!$H$8:$H$153,MATCH('Aggregated Data'!C8,'Quantity in each box'!$E$8:$E$153,0)),"NA")} -> 52.5 | H8: 10 | K8: 72236 | M8: 72228 | N8: Ukraine
A9: 22203 | B9: =C9&D9&E9 -> 3116211320000Gowns, Surgical, Sterile | C9: 311 | D9: 6211320000 | E9: Gowns, Surgical, Sterile | G9: {=IFERROR(INDEX('Quantity in each box'!$H$8:$H$153,MATCH('Aggregated Data'!C9,'Quantity in each box'!$E$8:$E$153,0)),"NA")} -> NA | H9: 30 | K9: 52222 | M9: 12259 | N9: Ukraine
A10: 22203 | B10: =C10&D10&E10 -> 3116211320000Lab Coats And Tunics, Scrub Suits, Surgical | C10: 311 | D10: 6211320000 | E10: Lab Coats And Tunics, Scrub Suits, Surgical | G10: {=IFERROR(INDEX('Quantity in each box'!$H$8:$H$153,MATCH('Aggregated Data'!C10,'Quantity in each box'!$E$8:$E$153,0)),"NA")} -> NA | H10: 5 | K10: 72228 | M10: 22226 | N10: Ukraine
A11: 22203 | B11: =C11&D11&E11 -> 50230061001002x2, 4x4, Abd Sterile Dressings | C11: 502 | D11: 3006100100 | E11: 2x2, 4x4, Abd Sterile Dressings | G11: {=IFERROR(INDEX('Quantity in each box'!$H$8:$H$153,MATCH('Aggregated Data'!C11,'Quantity in each box'!$E$8:$E$153,0)),"NA")} -> NA | H11: 5 | K11: Sample packing list | M11: 42226 | N11: Ukraine
A12: 22203 | B12: =C12&D12&E12 -> 5053005909900Bandaids, Steristrips, Tape, Transparent Dressings (tegaderm) | C12: 505 | D12: 3005909900 | E12: Bandaids, Steristrips, Tape, Transparent Dressings (tegaderm) | G12: {=IFERROR(INDEX('Quantity in each box'!$H$8:$H$153,MATCH('Aggregated Data'!C12,'Quantity in each box'!$E$8:$E$153,0)),"NA")} -> NA | H12: 15 | M12: 62219 | N12: Ukraine
A13: 22203 | B13: =C13&D13&E13 -> 5063005590000Dressing Change Kits, Laceration Trays, Wound Care Kits | C13: 506 | D13: 3005590000 | E13: Dressing Change Kits, Laceration Trays, Wound Care Kits | G13: {=IFERROR(INDEX('Quantity in each box'!$H$8:$H$153,MATCH('Aggregated Data'!C13,'Quantity in each box'!$E$8:$E$153,0)),"NA")} -> NA | H13: 5 | M13: Shipping donated by CURE | N13: Ukraine
A14: 22203 | B14: =C14&D14&E14 -> 5073005900000Gauze and All Other Non Sterile Dressings | C14: 507 | D14: 3005900000 | E14: Gauze and All Other Non Sterile Dressings | G14: {=IFERROR(INDEX('Quantity in each box'!$H$8:$H$153,MATCH('Aggregated Data'!C14,'Quantity in each box'!$E$8:$E$153,0)),"NA")} -> NA | H14: 5 | M14: 72236 | N14: Ukraine
A15: 22203 | B15: =C15&D15&E15 -> 5083005909900Kerlix/Kling Dressing | C15: 508 | D15: 3005909900 | E15: Kerlix/Kling Dressing | G15: {=IFERROR(INDEX('Quantity in each box'!$H$8:$H$153,MATCH('Aggregated Data'!C15,'Quantity in each box'!$E$8:$E$153,0)),"NA")} -> NA | H15: 5 | M15: 52222 | N15: Ukraine
A16: 22203 | B16: =C16&D16&E16 -> 5103005909900Trauma Dressing | C16: 510 | D16: 3005909900 | E16: Trauma Dressing | G16: {=IFERROR(INDEX('Quantity in each box'!$H$8:$H$153,MATCH('Aggregated Data'!C16,'Quantity in each box'!$E$8:$E$153,0)),"NA")} -> NA | H16: 1 | N16: Ukraine
A17: 22203 | B17: =C17&D17&E17 -> 5123006100100Specialty Dressings (and All Other Dressings Not Fitting In Other Categories) | C17: 512 | D17: 3006100100 | E17: Specialty Dressings (and All Other Dressings Not Fitting In Other Categories) | G17: {=IFERROR(INDEX('Quantity in each box'!$H$8:$H$153,MATCH('Aggregated Data'!C17,'Quantity in each box'!$E$8:$E$153,0)),"NA")} -> NA | H17: 5 | N17: Ukraine
A18: 22203 | B18: =C18&D18&E18 -> 6013006500000Bags, Red, Spill Kits And Isolyszer | C18: 601 | D18: 3006500000 | E18: Bags, Red, Spill Kits And Isolyszer | G18: {=IFERROR(INDEX('Quantity in each box'!$H$8:$H$153,MATCH('Aggregated Data'!C18,'Quantity in each box'!$E$8:$E$153,0)),"NA")} -> NA | H18: 2 | N18: Ukraine
A19: 22203 | B19: =C19&D19&E19 -> 6063923100000Sharps Containers, Send Only w/ Lids | C19: 606 | D19: 3923100000 | E19: Sharps Containers, Send Only w/ Lids | G19: {=IFERROR(INDEX('Quantity in each box'!$H$8:$H$153,MATCH('Aggregated Data'!C19,'Quantity in each box'!$E$8:$E$153,0)),"NA")} -> NA | H19: 2 | N19: Ukraine
A20: 22203 | B20: =C20&D20&E20 -> 7029018390000Buffalo caps, prn adaptors and other iv infusion supplies, vial spikes and adaptators | C20: 702 | D20: 9018390000 | E20: Buffalo caps, prn adaptors and other iv infusion supplies, vial spikes and adaptators | G20: {=IFERROR(INDEX('Quantity in each box'!$H$8:$H$153,MATCH('Aggregated Data'!C20,'Quantity in each box'!$E$8:$E$153,0)),"NA")} -> NA | H20: 5 | N20: Ukraine
A21: 22203 | B21: =C21&D21&E21 -> 7039018390000Central Percutaneous Lines | C21: 703 | D21: 9018390000 | E21: Central Percutaneous Lines | G21: {=IFERROR(INDEX('Quantity in each box'!$H$8:$H$153,MATCH('Aggregated Data'!C21,'Quantity in each box'!$E$8:$E$153,0)),"NA")} -> NA | H21: 5 | N21: Ukraine
A22: 22203 | B22: =C22&D22&E22 -> 7049018390030IV Catheters/ Including Huber, Butterfly, Fistula | C22: 704 | D22: 9018390030 | E22: IV Catheters/ Including Huber, Butterfly, Fistula | G22: {=IFERROR(INDEX('Quantity in each box'!$H$8:$H$153,MATCH('Aggregated Data'!C22,'Quantity in each box'!$E$8:$E$153,0)),"NA")} -> NA | H22: 15 | N22: Ukraine
A23: 22203 | B23: =C23&D23&E23 -> 7059018390000IV Extension & Secondary Tubing | C23: 705 | D23: 9018390000 | E23: IV Extension & Secondary Tubing | G23: {=IFERROR(INDEX('Quantity in each box'!$H$8:$H$153,MATCH('Aggregated Data'!C23,'Quantity in each box'!$E$8:$E$153,0)),"NA")} -> NA | H23: 5 | N23: Ukraine
A24: 22203 | B24: =C24&D24&E24 -> 7069018390000IV Primary Tubing, Including Blood Tubing | C24: 706 | D24: 9018390000 | E24: IV Primary Tubing, Including Blood Tubing | G24: {=IFERROR(INDEX('Quantity in each box'!$H$8:$H$153,MATCH('Aggregated Data'!C24,'Quantity in each box'!$E$8:$E$153,0)),"NA")} -> NA | H24: 10 | N24: Ukraine
A25: 22203 | B25: =C25&D25&E25 -> 7099018310040Needles, Mixed Gauges | C25: 709 | D25: 9018310040 | E25: Needles, Mixed Gauges | G25: {=IFERROR(INDEX('Quantity in each box'!$H$8:$H$153,MATCH('Aggregated Data'!C25,'Quantity in each box'!$E$8:$E$153,0)),"NA")} -> NA | H25: 20 | N25: Ukraine
A26: 22203 | B26: =C26&D26&E26 -> 7109018310040Syringes, 1 cc/tb | C26: 710 | D26: 9018310040 | E26: Syringes, 1 cc/tb | G26: {=IFERROR(INDEX('Quantity in each box'!$H$8:$H$153,MATCH('Aggregated Data'!C26,'Quantity in each box'!$E$8:$E$153,0)),"NA")} -> NA | H26: 2 | N26: Ukraine
A27: 22203 | B27: =C27&D27&E27 -> 7119018310040Syringes, 3cc | C27: 711 | D27: 9018310040 | E27: Syringes, 3cc | G27: {=IFERROR(INDEX('Quantity in each box'!$H$8:$H$153,MATCH('Aggregated Data'!C27,'Quantity in each box'!$E$8:$E$153,0)),"NA")} -> NA | H27: 2 | N27: Ukraine
... A74: 22203 | B74: =C74&D74&E74 -> 52379021101000Crutches | C74: 5237 | D74: 9021101000 | E74: Crutches | G74: {=IFERROR(INDEX('Quantity in each box'!$H$8:$H$153,MATCH('Aggregated Data'!C74,'Quantity in each box'!$E$8:$E$153,0)),"NA")} -> 1 | H74: 5 | N74: Ukraine
A75: 22203 | B75: =C75&D75&E75 -> 56019402.90.0020Gurney | C75: 5601 | D75: 9402.90.0020 | E75: Gurney | G75: {=IFERROR(INDEX('Quantity in each box'!$H$8:$H$153,MATCH('Aggregated Data'!C75,'Quantity in each box'!$E$8:$E$153,0)),"NA")} -> 1 | H75: 4 | N75: Ukraine
A76: 22203 | B76: =C76&D76&E76 -> 58029018390000IV Pole | C76: 5802 | D76: 9018390000 | E76: IV Pole | G76: {=IFERROR(INDEX('Quantity in each box'!$H$8:$H$153,MATCH('Aggregated Data'!C76,'Quantity in each box'!$E$8:$E$153,0)),"NA")} -> 1 | H76: 5 | N76: Ukraine
A77: 22203 | B77: =C77&D77&E77 -> 62019402900000Vinyl Bed Surface, ERB | C77: 6201 | D77: 9402900000 | E77: Vinyl Bed Surface, ERB | G77: {=IFERROR(INDEX('Quantity in each box'!$H$8:$H$153,MATCH('Aggregated Data'!C77,'Quantity in each box'!$E$8:$E$153,0)),"NA")} -> 1 | H77: 55 | N77: Ukraine
A78: 22203 | B78: =C78&D78&E78 -> 62039403208009Mayo Stand | C78: 6203 | D78: 9403208009 | E78: Mayo Stand | G78: {=IFERROR(INDEX('Quantity in each box'!$H$8:$H$153,MATCH('Aggregated Data'!C78,'Quantity in each box'!$E$8:$E$153,0)),"NA")} -> NA | H78: 1 | N78: Ukraine
A79: 22203 | B79: =C79&D79&E79 -> 65004819100000Paper, Exam Table Rolls in Boxes | C79: 6500 | D79: 4819100000 | E79: Paper, Exam Table Rolls in Boxes | G79: {=IFERROR(INDEX('Quantity in each box'!$H$8:$H$153,MATCH('Aggregated Data'!C79,'Quantity in each box'!$E$8:$E$153,0)),"NA")} -> NA | H79: 2 | N79: Ukraine
A80: 22203 | B80: =C80&D80&E80 -> 68169401300009Stool, Exam | C80: 6816 | D80: 9401300009 | E80: Stool, Exam | G80: {=IFERROR(INDEX('Quantity in each box'!$H$8:$H$153,MATCH('Aggregated Data'!C80,'Quantity in each box'!$E$8:$E$153,0)),"NA")} -> 1 | H80: 2 | N80: Ukraine
A81: 22203 | B81: =C81&D81&E81 -> 68229018908409Surgical Instrument Kit, Suture Set | C81: 6822 | D81: 9018908409 | E81: Surgical Instrument Kit, Suture Set | G81: {=IFERROR(INDEX('Quantity in each box'!$H$8:$H$153,MATCH('Aggregated Data'!C81,'Quantity in each box'!$E$8:$E$153,0)),"NA")} -> 1 | H81: 4 | N81: Ukraine
A82: 22203 | B82: =C82&D82&E82 -> 68259018908409Surgical Instrument Kit, General | C82: 6825 | D82: 9018908409 | E82: Surgical Instrument Kit, General | G82: {=IFERROR(INDEX('Quantity in each box'!$H$8:$H$153,MATCH('Aggregated Data'!C82,'Quantity in each box'!$E$8:$E$153,0)),"NA")} -> 1 | H82: 1 | N82: Ukraine
A83: 22203 | B83: =C83&D83&E83 -> 68359018900000Surgical Instrument Kit, Delivery | C83: 6835 | D83: 9018900000 | E83: Surgical Instrument Kit, Delivery | G83: {=IFERROR(INDEX('Quantity in each box'!$H$8:$H$153,MATCH('Aggregated Data'!C83,'Quantity in each box'!$E$8:$E$153,0)),"NA")} -> 1 | H83: 1 | N83: Ukraine
A84: 22203 | B84: =C84&D84&E84 -> 68389018908409Surgical Instrument Kit, Ortho | C84: 6838 | D84: 9018908409 | E84: Surgical Instrument Kit, Ortho | G84: {=IFERROR(INDEX('Quantity in each box'!$H$8:$H$153,MATCH('Aggregated Data'!C84,'Quantity in each box'!$E$8:$E$153,0)),"NA")} -> 1 | H84: 1 | N84: Ukraine
A85: 22203 | B85: =C85&D85&E85 -> 68479018908409Surgical Instrument Kit, Minor | C85: 6847 | D85: 9018908409 | E85: Surgical Instrument Kit, Minor | G85: {=IFERROR(INDEX('Quantity in each box'!$H$8:$H$153,MATCH('Aggregated Data'!C85,'Quantity in each box'!$E$8:$E$153,0)),"NA")} -> NA | H85: 1 | N85: Ukraine
A86: 22203 | B86: =C86&D86&E86 -> 69059402900000Table, Exam | C86: 6905 | D86: 9402900000 | E86: Table, Exam | G86: {=IFERROR(INDEX('Quantity in each box'!$H$8:$H$153,MATCH('Aggregated Data'!C86,'Quantity in each box'!$E$8:$E$153,0)),"NA")} -> 1 | H86: 4 | N86: Ukraine
A87: 22203 | B87: =C87&D87&E87 -> 72029021101000Walker, Adult | C87: 7202 | D87: 9021101000 | E87: Walker, Adult | G87: {=IFERROR(INDEX('Quantity in each box'!$H$8:$H$153,MATCH('Aggregated Data'!C87,'Quantity in each box'!$E$8:$E$153,0)),"NA")} -> 1 | H87: 5 | N87: Ukraine
... A120: 22214 | B120: =C120&D120&E120 -> 11089021109000Splints, Wraps (including Ace), and Slings, Hose Ted (anti-embolism) | C120: 1108 | D120: 9021109000 | E120: Splints, Wraps (including Ace), and Slings, Hose Ted (anti-embolism) | G120: {=IFERROR(INDEX('Quantity in each box'!$H$8:$H$153,MATCH('Aggregated Data'!C120,'Quantity in each box'!$E$8:$E$153,0)),"NA")} -> NA | H120: 2 | N120: Ukraine
A121: 22214 | B121: =C121&D121&E121 -> 11099021.10.99Braces | C121: 1109 | D121: 9021.10.99 | E121: Braces | G121: {=IFERROR(INDEX('Quantity in each box'!$H$8:$H$153,MATCH('Aggregated Data'!C121,'Quantity in each box'!$E$8:$E$153,0)),"NA")} -> NA | H121: 2 | N121: Ukraine
A122: 22214 | B122: =C122&D122&E122 -> 12079619008901Diapers, Adult | C122: 1207 | D122: 9619008901 | E122: Diapers, Adult | G122: {=IFERROR(INDEX('Quantity in each box'!$H$8:$H$153,MATCH('Aggregated Data'!C122,'Quantity in each box'!$E$8:$E$153,0)),"NA")} -> NA | H122: 60 | N122: Ukraine
A123: 22214 | B123: =C123&D123&E123 -> 12163006910000Ostomy (Colostomy, Ileostomy, Urostomy) Supplies, including Pouches, Adhesives, Etc) | C123: 1216 | D123: 3006910000 | E123: Ostomy (Colostomy, Ileostomy, Urostomy) Supplies, including Pouches, Adhesives, Etc) | G123: {=IFERROR(INDEX('Quantity in each box'!$H$8:$H$153,MATCH('Aggregated Data'!C123,'Quantity in each box'!$E$8:$E$153,0)),"NA")} -> NA | H123: 5 | N123: Ukraine
A124: 22214 | B124: =C124&D124&E124 -> 12183307900008Patient Supplies (Soaps, Shampoos, Mouthwash, Toothpaste, Belonging Bags),slippers | C124: 1218 | D124: 3307900008 | E124: Patient Supplies (Soaps, Shampoos, Mouthwash, Toothpaste, Belonging Bags),slippers | G124: {=IFERROR(INDEX('Quantity in each box'!$H$8:$H$153,MATCH('Aggregated Data'!C124,'Quantity in each box'!$E$8:$E$153,0)),"NA")} -> NA | H124: 60 | N124: Ukraine
A125: 22214 | B125: =C125&D125&E125 -> 12209018908409Rectal Supplies, including Enema Sets, Rectal Tubes, Long Swabs, Etc | C125: 1220 | D125: 9018908409 | E125: Rectal Supplies, including Enema Sets, Rectal Tubes, Long Swabs, Etc | G125: {=IFERROR(INDEX('Quantity in each box'!$H$8:$H$153,MATCH('Aggregated Data'!C125,'Quantity in each box'!$E$8:$E$153,0)),"NA")} -> NA | H125: 2 | N125: Ukraine
A126: 22214 | B126: =C126&D126&E126 -> 12239619008109Underpads, (Chux and Blue Pads) | C126: 1223 | D126: 9619008109 | E126: Underpads, (Chux and Blue Pads) | G126: {=IFERROR(INDEX('Quantity in each box'!$H$8:$H$153,MATCH('Aggregated Data'!C126,'Quantity in each box'!$E$8:$E$153,0)),"NA")} -> NA | H126: 10 | N126: Ukraine
A127: 22214 | B127: =C127&D127&E127 -> 14039018390000Nasal Cannulas | C127: 1403 | D127: 9018390000 | E127: Nasal Cannulas | G127: {=IFERROR(INDEX('Quantity in each box'!$H$8:$H$153,MATCH('Aggregated Data'!C127,'Quantity in each box'!$E$8:$E$153,0)),"NA")} -> NA | H127: 25 | N127: Ukraine
A128: 22214 | B128: =C128&D128&E128 -> 14049019200000Nebulizer Supplies | C128: 1404 | D128: 9019200000 | E128: Nebulizer Supplies | G128: {=IFERROR(INDEX('Quantity in each box'!$H$8:$H$153,MATCH('Aggregated Data'!C128,'Quantity in each box'!$E$8:$E$153,0)),"NA")} -> NA | H128: 15 | N128: Ukraine
A129: 22214 | B129: =C129&D129&E129 -> 140590200000Oxygen Masks and Tubing | C129: 1405 | D129: 90200000 | E129: Oxygen Masks and Tubing | G129: {=IFERROR(INDEX('Quantity in each box'!$H$8:$H$153,MATCH('Aggregated Data'!C129,'Quantity in each box'!$E$8:$E$153,0)),"NA")} -> NA | H129: 20 | N129: Ukraine
A130: 22214 | B130: =C130&D130&E130 -> 15023808940000Alcohol and Betadine Pads & Swabs | C130: 1502 | D130: 3808940000 | E130: Alcohol and Betadine Pads & Swabs | G130: {=IFERROR(INDEX('Quantity in each box'!$H$8:$H$153,MATCH('Aggregated Data'!C130,'Quantity in each box'!$E$8:$E$153,0)),"NA")} -> NA | H130: 30 | N130: Ukraine
A131: 22214 | B131: =C131&D131&E131 -> 15059603290000Scrub Brushes and Skin Prep Sets | C131: 1505 | D131: 9603290000 | E131: Scrub Brushes and Skin Prep Sets | G131: {=IFERROR(INDEX('Quantity in each box'!$H$8:$H$153,MATCH('Aggregated Data'!C131,'Quantity in each box'!$E$8:$E$153,0)),"NA")} -> NA | H131: 1 | N131: Ukraine
A132: 22214 | B132: =C132&D132&E132 -> 1601,999019200000Anesthesia Circuit Sets | C132: 1601.99 | D132: 9019200000 | E132: Anesthesia Circuit Sets | G132: {=IFERROR(INDEX('Quantity in each box'!$H$8:$H$153,MATCH('Aggregated Data'!C132,'Quantity in each box'!$E$8:$E$153,0)),"NA")} -> NA | H132: 50 | N132: Ukraine
A133: 22214 | B133: =C133&D133&E133 -> 1602,999018903000Anesthesia Facemasks | C133: 1602.99 | D133: 9018903000 | E133: Anesthesia Facemasks | G133: {=IFERROR(INDEX('Quantity in each box'!$H$8:$H$153,MATCH('Aggregated Data'!C133,'Quantity in each box'!$E$8:$E$153,0)),"NA")} -> NA | H133: 5 | N133: Ukraine
... A147: 22214 | B147: =C147&D147&E147 -> 1710,999018908409Staplers and Staple Removal Kits | C147: 1710.99 | D147: 9018908409 | E147: Staplers and Staple Removal Kits | G147: {=IFERROR(INDEX('Quantity in each box'!$H$8:$H$153,MATCH('Aggregated Data'!C147,'Quantity in each box'!$E$8:$E$153,0)),"NA")} -> NA | H147: 1 | N147: Ukraine
A148: 22214 | B148: =C148&D148&E148 -> 1801,993923.29.0000Urinary Bags (Leg and Bedside) And Urinary Supplies | C148: 1801.99 | D148: 3923.29.0000 | E148: Urinary Bags (Leg and Bedside) And Urinary Supplies | G148: {=IFERROR(INDEX('Quantity in each box'!$H$8:$H$153,MATCH('Aggregated Data'!C148,'Quantity in each box'!$E$8:$E$153,0)),"NA")} -> 97.5 | H148: 3 | N148: Ukraine
A149: 22214 | B149: =C149&D149&E149 -> 1802,999018390030Urinary Catheters, Trays & Insertion Sets | C149: 1802.99 | D149: 9018390030 | E149: Urinary Catheters, Trays & Insertion Sets | G149: {=IFERROR(INDEX('Quantity in each box'!$H$8:$H$153,MATCH('Aggregated Data'!C149,'Quantity in each box'!$E$8:$E$153,0)),"NA")} -> NA | H149: 4 | N149: Ukraine
A150: 22214 | B150: =C150&D150&E150 -> 20029019200000Bipap Unit | C150: 2002 | D150: 9019200000 | E150: Bipap Unit | G150: {=IFERROR(INDEX('Quantity in each box'!$H$8:$H$153,MATCH('Aggregated Data'!C150,'Quantity in each box'!$E$8:$E$153,0)),"NA")} -> NA | H150: 2 | N150: Ukraine
A151: 22214 | B151: =C151&D151&E151 -> 2002,01999019200000Bipap Supplies | C151: 2002.0199 | D151: 9019200000 | E151: Bipap Supplies | G151: {=IFERROR(INDEX('Quantity in each box'!$H$8:$H$153,MATCH('Aggregated Data'!C151,'Quantity in each box'!$E$8:$E$153,0)),"NA")} -> NA | H151: 2 | N151: Ukraine
A152: 22214 | B152: =C152&D152&E152 -> 2106,999018110080Cautery Grounding Pads | C152: 2106.99 | D152: 9018110080 | E152: Cautery Grounding Pads | G152: {=IFERROR(INDEX('Quantity in each box'!$H$8:$H$153,MATCH('Aggregated Data'!C152,'Quantity in each box'!$E$8:$E$153,0)),"NA")} -> NA | H152: 2 | N152: Ukraine
A153: 22214 | B153: =C153&D153&E153 -> 2107,999018.11.3000Cautery Pens | C153: 2107.99 | D153: 9018.11.3000 | E153: Cautery Pens | G153: {=IFERROR(INDEX('Quantity in each box'!$H$8:$H$153,MATCH('Aggregated Data'!C153,'Quantity in each box'!$E$8:$E$153,0)),"NA")} -> NA | H153: 2 | N153: Ukraine
A154: 22214 | B154: =C154&D154&E154 -> 21179019200000Concentrator, Oxygen | C154: 2117 | D154: 9019200000 | E154: Concentrator, Oxygen | G154: {=IFERROR(INDEX('Quantity in each box'!$H$8:$H$153,MATCH('Aggregated Data'!C154,'Quantity in each box'!$E$8:$E$153,0)),"NA")} -> 1 | H154: 20 | N154: Ukraine
A155: 22214 | B155: =C155&D155&E155 -> 26008513100000Head Lamp | C155: 2600 | D155: 8513100000 | E155: Head Lamp | G155: {=IFERROR(INDEX('Quantity in each box'!$H$8:$H$153,MATCH('Aggregated Data'!C155,'Quantity in each box'!$E$8:$E$153,0)),"NA")} -> 2 | H155: 1 | N155: Ukraine
A156: 22214 | B156: =C156&D156&E156 -> 30069018902000Laryngoscope | C156: 3006 | D156: 9018902000 | E156: Laryngoscope | G156: {=IFERROR(INDEX('Quantity in each box'!$H$8:$H$153,MATCH('Aggregated Data'!C156,'Quantity in each box'!$E$8:$E$153,0)),"NA")} -> NA | H156: 1 | N156: Ukraine
A157: 22214 | B157: =C157&D157&E157 -> 30207017900000Lab Supply Kits | C157: 3020 | D157: 7017900000 | E157: Lab Supply Kits | G157: {=IFERROR(INDEX('Quantity in each box'!$H$8:$H$153,MATCH('Aggregated Data'!C157,'Quantity in each box'!$E$8:$E$153,0)),"NA")} -> NA | H157: 2 | N157: Ukraine
A158: 22214 | B158: =C158&D158&E158 -> 3020,027017900000Lab Supply Kit, Vacutainer Tubes | C158: 3020.02 | D158: 7017900000 | E158: Lab Supply Kit, Vacutainer Tubes | G158: {=IFERROR(INDEX('Quantity in each box'!$H$8:$H$153,MATCH('Aggregated Data'!C158,'Quantity in each box'!$E$8:$E$153,0)),"NA")} -> NA | H158: 2 | N158: Ukraine
A159: 22214 | B159: =C159&D159&E159 -> 3020,037017900000Lab Supply Kit, Tubes | C159: 3020.03 | D159: 7017900000 | E159: Lab Supply Kit, Tubes | G159: {=IFERROR(INDEX('Quantity in each box'!$H$8:$H$153,MATCH('Aggregated Data'!C159,'Quantity in each box'!$E$8:$E$153,0)),"NA")} -> NA | H159: 1 | N159: Ukraine
A160: 22214 | B160: =C160&D160&E160 -> 3020,059018319009Lab Supply Kit, Abg Syringes & Culture Supplies | C160: 3020.05 | D160: 9018319009 | E160: Lab Supply Kit, Abg Syringes & Culture Supplies | G160: {=IFERROR(INDEX('Quantity in each box'!$H$8:$H$153,MATCH('Aggregated Data'!C160,'Quantity in each box'!$E$8:$E$153,0)),"NA")} -> NA | H160: 5 | N160: Ukraine
A161: 22214 | B161: =C161&D161&E161 -> 31069018199000Monitor, Clinical, 2 -4 function (NIBP, Pulse, optional TEMP & SPO2) | C161: 3106 | D161: 9018199000 | E161: Monitor, Clinical, 2 -4 function (NIBP, Pulse, optional TEMP & SPO2) | G161: {=IFERROR(INDEX('Quantity in each box'!$H$8:$H$153,MATCH('Aggregated Data'!C161,'Quantity in each box'!$E$8:$E$153,0)),"NA")} -> 1 | H161: 2 | N161: Ukraine
A162: 22214 | B162: =C162&D162&E162 -> 33089018908409Otoscope / Ophthalmoscope Wall Mounted AC Powered | C162: 3308 | D162: 9018908409 | E162: Otoscope / Ophthalmoscope Wall Mounted AC Powered | G162: {=IFERROR(INDEX('Quantity in each box'!$H$8:$H$153,MATCH('Aggregated Data'!C162,'Quantity in each box'!$E$8:$E$153,0)),"NA")} -> 25 | H162: 2 | N162: Ukraine
A163: 22214 | B163: =C163&D163&E163 -> 3309,19019200000Oximeter, Pulse, Battery Operated | C163: 3309.1 | D163: 9019200000 | E163: Oximeter, Pulse, Battery Operated | G163: {=IFERROR(INDEX('Quantity in each box'!$H$8:$H$153,MATCH('Aggregated Data'!C163,'Quantity in each box'!$E$8:$E$153,0)),"NA")} -> 1 | H163: 2 | N163: Ukraine
A164: 22214 | B164: =C164&D164&E164 -> 33129017308000Oxygen Tank Regulator | C164: 3312 | D164: 9017308000 | E164: Oxygen Tank Regulator | G164: {=IFERROR(INDEX('Quantity in each box'!$H$8:$H$153,MATCH('Aggregated Data'!C164,'Quantity in each box'!$E$8:$E$153,0)),"NA")} -> NA | H164: 5 | N164: Ukraine
A165: 22214 | B165: =C165&D165&E165 -> 37109018901000Sphygmomanometer Wall Mount Unit | C165: 3710 | D165: 9018901000 | E165: Sphygmomanometer Wall Mount Unit | G165: {=IFERROR(INDEX('Quantity in each box'!$H$8:$H$153,MATCH('Aggregated Data'!C165,'Quantity in each box'!$E$8:$E$153,0)),"NA")} -> 0 | H165: 4 | N165: Ukraine
... A179: 22214 | B179: =C179&D179&E179 -> 52409019200000C.U.R.E. Kits for Kids | C179: 5240 | D179: 9019200000 | E179: C.U.R.E. Kits for Kids | G179: {=IFERROR(INDEX('Quantity in each box'!$H$8:$H$153,MATCH('Aggregated Data'!C179,'Quantity in each box'!$E$8:$E$153,0)),"NA")} -> NA | H179: 5 | N179: Ukraine
A180: 22214 | B180: =C180&D180&E180 -> 5242MSD Postnatal Kits | C180: 5242 | E180: MSD Postnatal Kits | G180: {=IFERROR(INDEX('Quantity in each box'!$H$8:$H$153,MATCH('Aggregated Data'!C180,'Quantity in each box'!$E$8:$E$153,0)),"NA")} -> NA | H180: 10 | N180: Ukraine
A181: 22214 | B181: =C181&D181&E181 -> 5244,13006.50.0000Kit, First Aid | C181: 5244.1 | D181: 3006.50.0000 | E181: Kit, First Aid | G181: {=IFERROR(INDEX('Quantity in each box'!$H$8:$H$153,MATCH('Aggregated Data'!C181,'Quantity in each box'!$E$8:$E$153,0)),"NA")} -> NA | H181: 1 | N181: Ukraine
A182: 22214 | B182: =C182&D182&E182 -> 56019402.90.0020Gurney | C182: 5601 | D182: 9402.90.0020 | E182: Gurney | G182: {=IFERROR(INDEX('Quantity in each box'!$H$8:$H$153,MATCH('Aggregated Data'!C182,'Quantity in each box'!$E$8:$E$153,0)),"NA")} -> 1 | H182: 1 | N182: Ukraine
A183: 22214 | B183: =C183&D183&E183 -> 57019402900000Hoyer Lift | C183: 5701 | D183: 9402900000 | E183: Hoyer Lift | G183: {=IFERROR(INDEX('Quantity in each box'!$H$8:$H$153,MATCH('Aggregated Data'!C183,'Quantity in each box'!$E$8:$E$153,0)),"NA")} -> 1 | H183: 1 | N183: Ukraine
A184: 22214 | B184: =C184&D184&E184 -> 58029018390000IV Pole | C184: 5802 | D184: 9018390000 | E184: IV Pole | G184: {=IFERROR(INDEX('Quantity in each box'!$H$8:$H$153,MATCH('Aggregated Data'!C184,'Quantity in each box'!$E$8:$E$153,0)),"NA")} -> 1 | H184: 10 | N184: Ukraine
A185: 22214 | B185: =C185&D185&E185 -> 6201,19402900000Vinyl Bed Surface, ERB | C185: 6201.1 | D185: 9402900000 | E185: Vinyl Bed Surface, ERB | G185: {=IFERROR(INDEX('Quantity in each box'!$H$8:$H$153,MATCH('Aggregated Data'!C185,'Quantity in each box'!$E$8:$E$153,0)),"NA")} -> 1 | H185: 50 | N185: Ukraine
A186: 22214 | B186: =C186&D186&E186 -> 68149401300009Step Stool | C186: 6814 | D186: 9401300009 | E186: Step Stool | G186: {=IFERROR(INDEX('Quantity in each box'!$H$8:$H$153,MATCH('Aggregated Data'!C186,'Quantity in each box'!$E$8:$E$153,0)),"NA")} -> NA | H186: 1 | N186: Ukraine
A187: 22214 | B187: =C187&D187&E187 -> 68189402.90.0020Stretcher | C187: 6818 | D187: 9402.90.0020 | E187: Stretcher | G187: {=IFERROR(INDEX('Quantity in each box'!$H$8:$H$153,MATCH('Aggregated Data'!C187,'Quantity in each box'!$E$8:$E$153,0)),"NA")} -> NA | H187: 1 | N187: Ukraine
A188: 22214 | B188: =C188&D188&E188 -> 68229018908409Surgical Instrument Kit, Suture Set | C188: 6822 | D188: 9018908409 | E188: Surgical Instrument Kit, Suture Set | G188: {=IFERROR(INDEX('Quantity in each box'!$H$8:$H$153,MATCH('Aggregated Data'!C188,'Quantity in each box'!$E$8:$E$153,0)),"NA")} -> 1 | H188: 5 | N188: Ukraine
A189: 22214 | B189: =C189&D189&E189 -> 69059402900000Table, Exam | C189: 6905 | D189: 9402900000 | E189: Table, Exam | G189: {=IFERROR(INDEX('Quantity in each box'!$H$8:$H$153,MATCH('Aggregated Data'!C189,'Quantity in each box'!$E$8:$E$153,0)),"NA")} -> 1 | H189: 4 | N189: Ukraine
A190: 22214 | B190: =C190&D190&E190 -> 69109402900000Table, Over Bed | C190: 6910 | D190: 9402900000 | E190: Table, Over Bed | G190: {=IFERROR(INDEX('Quantity in each box'!$H$8:$H$153,MATCH('Aggregated Data'!C190,'Quantity in each box'!$E$8:$E$153,0)),"NA")} -> 1 | H190: 5 | N190: Ukraine
A191: 22214 | B191: =C191&D191&E191 -> 69149402900000Table, Treatment | C191: 6914 | D191: 9402900000 | E191: Table, Treatment | G191: {=IFERROR(INDEX('Quantity in each box'!$H$8:$H$153,MATCH('Aggregated Data'!C191,'Quantity in each box'!$E$8:$E$153,0)),"NA")} -> 1 | H191: 8 | N191: Ukraine
A192: 22214 | B192: =C192&D192&E192 -> 6925Transfer Board | C192: 6925 | E192: Transfer Board | G192: {=IFERROR(INDEX('Quantity in each box'!$H$8:$H$153,MATCH('Aggregated Data'!C192,'Quantity in each box'!$E$8:$E$153,0)),"NA")} -> 1 | H192: 1 | N192: Ukraine
A193: 22214 | B193: =C193&D193&E193 -> 69266307909200Trash / Biohazard Waste Cans | C193: 6926 | D193: 6307909200 | E193: Trash / Biohazard Waste Cans | G193: {=IFERROR(INDEX('Quantity in each box'!$H$8:$H$153,MATCH('Aggregated Data'!C193,'Quantity in each box'!$E$8:$E$153,0)),"NA")} -> 1 | H193: 2 | N193: Ukraine
A194: 52216 | B194: =C194&D194&E194 -> 3016302210000Bed Linens And Towels | C194: 301 | D194: 6302210000 | E194: Bed Linens And Towels | G194: {=IFERROR(INDEX('Quantity in each box'!$H$8:$H$153,MATCH('Aggregated Data'!C194,'Quantity in each box'!$E$8:$E$153,0)),"NA")} -> NA | H194: 25 | N194: Ukraine
A195: 52216 | B195: =C195&D195&E195 -> 3026307909800Surgical Caps And Hats, Shoe Covers | C195: 302 | D195: 6307909800 | E195: Surgical Caps And Hats, Shoe Covers | G195: {=IFERROR(INDEX('Quantity in each box'!$H$8:$H$153,MATCH('Aggregated Data'!C195,'Quantity in each box'!$E$8:$E$153,0)),"NA")} -> 1550 | H195: 5 | N195: Ukraine
A196: 52216 | B196: =C196&D196&E196 -> 3036307.90.9995Cloth Products Not Fitting In Other Items, Cubical Curtains | C196: 303 | D196: 6307.90.9995 | E196: Cloth Products Not Fitting In Other Items, Cubical Curtains | G196: {=IFERROR(INDEX('Quantity in each box'!$H$8:$H$153,MATCH('Aggregated Data'!C196,'Quantity in each box'!$E$8:$E$153,0)),"NA")} -> NA | H196: 5 | N196: Ukraine
A197: 52216 | B197: =C197&D197&E197 -> 305,993926201010Gloves, Non-sterile | C197: 305.99 | D197: 3926201010 | E197: Gloves, Non-sterile | G197: {=IFERROR(INDEX('Quantity in each box'!$H$8:$H$153,MATCH('Aggregated Data'!C197,'Quantity in each box'!$E$8:$E$153,0)),"NA")} -> 325 | H197: 5 | N197: Ukraine
A198: 52216 | B198: =C198&D198&E198 -> 307,1999004909000Masks, surgical | C198: 307.199 | D198: 9004909000 | E198: Masks, surgical | G198: {=IFERROR(INDEX('Quantity in each box'!$H$8:$H$153,MATCH('Aggregated Data'!C198,'Quantity in each box'!$E$8:$E$153,0)),"NA")} -> NA | H198: 10 | N198: Ukraine
A199: 52216 | B199: =C199&D199&E199 -> 307,2999004909000Goggles and Face Protection | C199: 307.299 | D199: 9004909000 | E199: Goggles and Face Protection | G199: {=IFERROR(INDEX('Quantity in each box'!$H$8:$H$153,MATCH('Aggregated Data'!C199,'Quantity in each box'!$E$8:$E$153,0)),"NA")} -> NA | H199: 15 | N199: Ukraine
A200: 52216 | B200: =C200&D200&E200 -> 307,999004909000Goggles, Masks, and Face Protection | C200: 307.99 | D200: 9004909000 | E200: Goggles, Masks, and Face Protection | G200: {=IFERROR(INDEX('Quantity in each box'!$H$8:$H$153,MATCH('Aggregated Data'!C200,'Quantity in each box'!$E$8:$E$153,0)),"NA")} -> 97.5 | H200: 5 | N200: Ukraine
A201: 52216 | B201: =C201&D201&E201 -> 308,1994823909000Gowns, Isolation Level 1 and Level 2 | C201: 308.199 | D201: 4823909000 | E201: Gowns, Isolation Level 1 and Level 2 | G201: {=IFERROR(INDEX('Quantity in each box'!$H$8:$H$153,MATCH('Aggregated Data'!C201,'Quantity in each box'!$E$8:$E$153,0)),"NA")} -> 97.5 | H201: 10 | N201: Ukraine
A202: 52216 | B202: =C202&D202&E202 -> 308,2994823909000Gowns, Isolation or Biohazard, Level 3 and Level 4 | C202: 308.299 | D202: 4823909000 | E202: Gowns, Isolation or Biohazard, Level 3 and Level 4 | G202: {=IFERROR(INDEX('Quantity in each box'!$H$8:$H$153,MATCH('Aggregated Data'!C202,'Quantity in each box'!$E$8:$E$153,0)),"NA")} -> 97.5 | H202: 30 | N202: Ukraine
A203: 52216 | B203: =C203&D203&E203 -> 308,994823909000Gowns, Patient (incl. Cloth, Paper Protector, Cover- up) | C203: 308.99 | D203: 4823909000 | E203: Gowns, Patient (incl. Cloth, Paper Protector, Cover- up) | G203: {=IFERROR(INDEX('Quantity in each box'!$H$8:$H$153,MATCH('Aggregated Data'!C203,'Quantity in each box'!$E$8:$E$153,0)),"NA")} -> 52.5 | H203: 30 | N203: Ukraine
A204: 52216 | B204: =C204&D204&E204 -> 3094823909000Gowns, Surgical, Non-sterile | C204: 309 | D204: 4823909000 | E204: Gowns, Surgical, Non-sterile | G204: {=IFERROR(INDEX('Quantity in each box'!$H$8:$H$153,MATCH('Aggregated Data'!C204,'Quantity in each box'!$E$8:$E$153,0)),"NA")} -> 52.5 | H204: 5 | N204: Ukraine
...

Sheet Clean Data (5 shipments)
A1: Shipment ID | B1: Product Code | C1: HS Code | D1: Description | E1: Unique Ids | F1: Number Ordered | G1: Pieces/ Cartons | H1: Total Quantity | I1: Net Weight (kg) | J1: Unit Value ($) | K1: Total Value ($)
A2: 62219 | B2: 301 | C2: 6302210000 | D2: Bed Linens And Towels | E2: =A2&+C2 -> 622196302210000 | F2: 10
A3: 62219 | B3: 302 | C3: 6307909800 | D3: Surgical Caps And Hats, Shoe Covers | E3: =A3&+C3 -> 622196307909800 | F3: 10
A4: 62219 | B4: 305.99 | C4: 3926201010 | D4: Gloves, Non-sterile | E4: =A4&+C4 -> 622193926201010 | F4: 40
A5: 62219 | B5: 310.99 | C5: 6211320000 | D5: Gowns, Surgical, Sterile | E5: =A5&+C5 -> 622196211320000 | F5: 30
A6: 62219 | B6: 311.1 | C6: 6211320000 | D6: Scrubs, FIG | E6: =A6&+C6 -> 622196211320000 | F6: 10
A7: 62219 | B7: 501.99 | C7: 3006100100 | D7: 2x2, 4x4, Abd Sterile Dressings | E7: =A7&+C7 -> 622193006100100 | F7: 15
A8: 62219 | B8: 506.99 | C8: 3005900000 | D8: Gauze and All Other Non Sterile Dressings | E8: =A8&+C8 -> 622193005900000 | F8: 2
A9: 62219 | B9: 507.99 | C9: 3005909900 | D9: Kerlix/Kling Dressing | E9: =A9&+C9 -> 622193005909900 | F9: 10
A10: 62219 | B10: 511.99 | C10: 3006100100 | D10: Specialty Dressings (and All Other Dressings Not Fitting In Other Categories) | E10: =A10&+C10 -> 622193006100100 | F10: 2
A11: 62219 | B11: 601 | C11: 3006500000 | D11: Bags, Red, Spill Kits And Isolyszer | E11: =A11&+C11 -> 622193006500000 | F11: 10
A12: 62219 | B12: 602.99 | C12: 3808940000 | D12: Disinfectant, Non-Patient; Also Sterilization Products & Sprays (Cidex, Etc) | E12: =A12&+C12 -> 622193808940000 | F12: 10
A13: 62219 | B13: 604 | C13: 3923100000 | D13: Liners, Trash Can, Laundry & Plastic Bags, Mopheads | E13: =A13&+C13 -> 622193923100000 | F13: 5
... A47: 62219 | B47: 1707.99 | C47: 9018390030 | D47: Suction Catheter, Tips, Tubings & Connectors | E47: =A47&+C47 -> 622199018390030 | F47: 5
A48: 62219 | B48: 1801.99 | C48: 3923.29.0000 | D48: Urinary Bags (Leg and Bedside) And Urinary Supplies | E48: =A48&+C48 -> 622193923.29.0000 | F48: 2
A49: 62219 | B49: 1802.99 | C49: 9018390030 | D49: Urinary Catheters, Trays & Insertion Sets | E49: =A49&+C49 -> 622199018390030 | F49: 5
A50: 62219 | B50: 1913 | C50: 8419200000 | D50: Autoclave, Sterilizer, Desktop | E50: =A50&+C50 -> 622198419200000 | F50: 1
A51: 62219 | B51: 2104 | C51: 9018900000 | D51: Cast Saw | E51: =A51&+C51 -> 622199018900000 | F51: 1
A52: 62219 | B52: 2113 | C52: 9019200000 | D52: Cold Therapy Unit / Portable | E52: =A52&+C52 -> 622199019200000 | F52: 2
A53: 62219 | B53: 2117.1 | C53: 9019200000 | D53: Concentrator, Oxygen | E53: =A53&+C53 -> 622199019200000 | F53: 23
A54: 62219 | B54: 2120.0199 | C54: 9019200000 | D54: CPAP Supplies | E54: =A54&+C54 -> 622199019200000 | F54: 1
A55: 62219 | B55: 2120.1 | C55: 9019200000 | D55: CPAP Unit W/ Humidifier | E55: =A55&+C55 -> 622199019200000 | F55: 1
A56: 62219 | B56: 3006 | C56: 9018902000 | D56: Laryngoscope | E56: =A56&+C56 -> 622199018902000 | F56: 4
A57: 62219 | B57: 3013 | C57: 9405204001 | D57: Light, Exam | E57: =A57&+C57 -> 622199405204001 | F57: 2
A58: 62219 | B58: 3110 | C58: 9018199000 | D58: Monitor, vital signs, 5 function (NIPB,Pulse, Optional TEMP,SPO2,ECG) | E58: =A58&+C58 -> 622199018199000 | F58: 1
A59: 62219 | B59: 3200 | C59: 9019200000 | D59: Nebulizer | E59: =A59&+C59 -> 622199019200000 | F59: 2
A60: 62219 | B60: 3308 | C60: 9018908409 | D60: Otoscope / Ophthalmoscope Wall Mounted AC Powered | E60: =A60&+C60 -> 622199018908409 | F60: 2
... A73: 62219 | B73: 5112 | C73: 9402900010 | D73: Bed, ICU | E73: =A73&+C73 -> 622199402900010 | F73: 2
A74: 62219 | B74: 5112.1 | C74: 9403.20.0010 | D74: Bed, ICU with Air Mattress | E74: =A74&+C74 -> 622199403.20.0010 | F74: 2
A75: 62219 | B75: 5203 | C75: 9403109809 | D75: Cabinet, Misc | E75: =A75&+C75 -> 622199403109809 | F75: 2
A76: 62219 | B76: 5206 | C76: 9021101000 | D76: Cane, Quad | E76: =A76&+C76 -> 622199021101000 | F76: 15
A77: 62219 | B77: 5213 | C77: 9402900000 | D77: Cart, Oxygen Cylinder | E77: =A77&+C77 -> 622199402900000 | F77: 1
A78: 62219 | B78: 5228 | C78: 9403208009 | D78: Commode, Bedside | E78: =A78&+C78 -> 622199403208009 | F78: 15
A79: 62219 | B79: 5237 | C79: 9021101000 | D79: Crutches | E79: =A79&+C79 -> 622199021101000 | F79: 15
A80: 62219 | B80: 5501 | C80: 9403109300 | D80: File Cabinet | E80: =A80&+C80 -> 622199403109300 | F80: 1
A81: 62219 | B81: 5601 | C81: 9402.90.0020 | D81: Gurney | E81: =A81&+C81 -> 622199402.90.0020 | F81: 4
A82: 62219 | B82: 5701 | C82: 9402900000 | D82: Hoyer Lift | E82: =A82&+C82 -> 622199402900000 | F82: 5
A83: 62219 | B83: 5802 | C83: 9018390000 | D83: IV Pole | E83: =A83&+C83 -> 622199018390000 | F83: 5
A84: 62219 | B84: 6201 | C84: 9402900000 | D84: Vinyl Bed Surface | E84: =A84&+C84 -> 622199402900000 | F84: 12
A85: 62219 | B85: 6201.1 | C85: 9402900000 | D85: Vinyl Bed Surface, ERB | E85: =A85&+C85 -> 622199402900000 | F85: 15
A86: 62219 | B86: 6203 | C86: 9403208009 | D86: Mayo Stand | E86: =A86&+C86 -> 622199403208009 | F86: 1
A87: 62219 | B87: 6800 | C87: 8423820000 | D87: Scale, Adult | E87: =A87&+C87 -> 622198423820000 | F87: 1
A88: 62219 | B88: 6803 | C88: 9016000000 | D88: Stacking Storage Bins | E88: =A88&+C88 -> 622199016000000 | F88: 5
A89: 62219 | B89: 6822 | C89: 9018908409 | D89: Surgical Instrument Kit, Suture Set | E89: =A89&+C89 -> 622199018908409 | F89: 1
A90: 62219 | B90: 6825 | C90: 9018908409 | D90: Surgical Instrument Kit, General | E90: =A90&+C90 -> 622199018908409 | F90: 2
A91: 62219 | B91: 6835 | C91: 9018900000 | D91: Surgical Instrument Kit, Delivery | E91: =A91&+C91 -> 622199018900000 | F91: 1
A92: 62219 | B92: 6905 | C92: 9402900000 | D92: Table, Exam | E92: =A92&+C92 -> 622199402900000 | F92: 6
A93: 62219 | B93: 6925 | D93: Transfer Board | E93: =A93&+C93 -> 62219 | F93: 1
A94: 62219 | B94: 6926 | C94: 6307909200 | D94: Trash / Biohazard Waste Cans | E94: =A94&+C94 -> 622196307909200 | F94: 2
A95: 62219 | B95: 7202 | C95: 9021101000 | D95: Walker, Adult | E95: =A95&+C95 -> 622199021101000 | F95: 2
A96: 62219 | B96: 7211 | C96: 8713109000 | D96: Wheelchair Transport Unit | E96: =A96&+C96 -> 622198713109000 | F96: 3
A97: 72204 | B97: 1108 | C97: 9021109000 | D97: Splints, Wraps (including Ace), and Slings, Hose Ted (anti- embolism) | E97: =A97&+C97 -> 722049021109000 | G97: 14 | H97: 328 | I97: 86.73 | J97: 10.3 | K97: 3378.4
A98: 72204 | B98: 1402.99 | C98: 9018390000 | D98: Nasal Cannulas | E98: =A98&+C98 -> 722049018390000 | G98: 45 | H98: 2424 | I98: 220.72 | J98: 1.03 | K98: 2496.72
A99: 72204 | B99: 1404.99 | C99: 90200000 | D99: Oxygen Masks and Tubing | E99: =A99&+C99 -> 7220490200000 | G99: 28 | H99: 1563 | I99: 112.94 | J99: 3.03 | K99: 4735.89
A100: 72204 | B100: 1603 | C100: 9018900000 | D100: Ambu Bags | E100: =A100&+C100 -> 722049018900000 | G100: 31 | H100: 908 | I100: 108.77 | J100: 25 | K100: 22700
A101: 72204 | B101: 1603.99 | C101: 9018900000 | D101: Ambu Bags | E101: =A101&+C101 -> 722049018900000 | G101: 18 | H101: 362 | I101: 91.58 | J101: 25 | K101: 9050
A102: 72204 | B102: 1607 | C102: 9018908409 | D102: Drains, Surgical, including Penrose and Suction Types | E102: =A102&+C102 -> 722049018908409 | G102: 2 | H102: 89 | I102: 10.16 | J102: 15.05 | K102: 1339.45
A103: 72204 | B103: 1607.99 | C103: 9018908409 | D103: Drains, Surgical, including Penrose and Suction Types | E103: =A103&+C103 -> 722049018908409 | G103: 1 | H103: 20 | I103: 3.4 | J103: 15.05 | K103: 301
A104: 72204 | B104: 1609 | C104: 9020000000 | D104: Endotracheal Tubes | E104: =A104&+C104 -> 722049020000000 | G104: 8 | H104: 679 | I104: 17.69 | J104: 3.48 | K104: 2362.92
A105: 72204 | B105: 1609.99 | C105: 9020000000 | D105: Endotracheal Tubes | E105: =A105&+C105 -> 722049020000000 | G105: 6 | H105: 466 | I105: 16.47 | J105: 3.48 | K105: 1621.68
A106: 72204 | B106: 1617 | C106: 9018908409 | D106: General Surgery Packs & Supplies | E106: =A106&+C106 -> 722049018908409 | G106: 4 | H106: 180 | I106: 23.54 | J106: 22.34 | K106: 4021.2
A107: 72204 | B107: 1620 | C107: 9021101000 | D107: Orthopedic Surgery Packs & Supplies | E107: =A107&+C107 -> 722049021101000 | G107: 1 | H107: 1 | I107: 7.21 | J107: 20.04 | K107: 20.04
A108: 72204 | B108: 1625.99 | C108: 901819 | D108: Tracheostomy & Cricothyroidotomy supplies, tubes and kits | E108: =A108&+C108 -> 72204901819 | G108: 5 | H108: 874 | I108: 18.42 | J108: 30.36 | K108: 26534.64
... A115: 72204 | B115: 6847 | C115: 9018908409 | D115: Surgical Instrument Kit, Minor | E115: =A115&+C115 -> 722049018908409 | G115: 2 | H115: 2 | I115: 11.34 | J115: 468 | K115: 936
A116: 42226 | B116: 302 | C116: 6307909800 | D116: Surgical Caps And Hats, Shoe Covers | E116: =A116&+C116 -> 422266307909800 | F116: 20
A117: 42226 | B117: 305.99 | C117: 3926201010 | D117: Gloves, Non-sterile | E117: =A117&+C117 -> 422263926201010 | F117: 40
A118: 42226 | B118: 308.99 | C118: 4823909000 | D118: Gowns, Patient (incl. Cloth, Paper Protector, Cover- up) | E118: =A118&+C118 -> 422264823909000 | F118: 10
A119: 42226 | B119: 310.99 | C119: 6211320000 | D119: Gowns, Surgical, Sterile | E119: =A119&+C119 -> 422266211320000 | F119: 25
A120: 42226 | B120: 311.1 | C120: 6211320000 | D120: Scrubs, FIG | E120: =A120&+C120 -> 422266211320000 | F120: 10
A121: 42226 | B121: 401.99 | C121: 4421900000 | D121: Dental Supplies | E121: =A121&+C121 -> 422264421900000 | F121: 10
A122: 42226 | B122: 501.99 | C122: 3006100100 | D122: 2x2, 4x4, Abd Sterile Dressings | E122: =A122&+C122 -> 422263006100100 | F122: 10
A123: 42226 | B123: 504.99 | C123: 3005909900 | D123: Bandaids, Steristrips, Tape, Transparent Dressings (tegaderm) | E123: =A123&+C123 -> 422263005909900 | F123: 5
A124: 42226 | B124: 505.99 | C124: 3005590000 | D124: Dressing Change Kits, Laceration Trays, Wound Care Kits | E124: =A124&+C124 -> 422263005590000 | F124: 10
A125: 42226 | B125: 507.99 | C125: 3005909900 | D125: Kerlix/Kling Dressing | E125: =A125&+C125 -> 422263005909900 | F125: 2
A126: 42226 | B126: 511.99 | C126: 3006100100 | D126: Specialty Dressings (and All Other Dressings Not Fitting In Other Categories) | E126: =A126&+C126 -> 422263006100100 | F126: 5
A127: 42226 | B127: 601 | C127: 3006500000 | D127: Bags, Red, Spill Kits And Isolyszer | E127: =A127&+C127 -> 422263006500000 | F127: 10
... A166: 42226 | B166: 1701 | C166: 3005909900 | D166: Drapes, Non-sterile | E166: =A166&+C166 -> 422263005909900 | F166: 10
A167: 42226 | B167: 1801.99 | C167: 3923.29.0000 | D167: Urinary Bags (Leg and Bedside) And Urinary Supplies | E167: =A167&+C167 -> 422263923.29.0000 | F167: 5
A168: 42226 | B168: 1802.99 | C168: 9018390030 | D168: Urinary Catheters, Trays & Insertion Sets | E168: =A168&+C168 -> 422269018390030 | F168: 5
A169: 42226 | B169: 2002.0199 | C169: 9019200000 | D169: Bipap Supplies | E169: =A169&+C169 -> 422269019200000 | F169: 1
A170: 42226 | B170: 2104 | C170: 9018900000 | D170: Cast Saw | E170: =A170&+C170 -> 422269018900000 | F170: 1
A171: 42226 | B171: 2114 | D171: Compression System, Chest | E171: =A171&+C171 -> 42226 | F171: 1
A172: 42226 | B172: 2117.1 | C172: 9019200000 | D172: Concentrator, Oxygen | E172: =A172&+C172 -> 422269019200000 | F172: 69
A173: 42226 | B173: 2120.0199 | C173: 9019200000 | D173: CPAP Supplies | E173: =A173&+C173 -> 422269019200000 | F173: 1
A174: 42226 | B174: 2120.1 | C174: 9019200000 | D174: CPAP Unit W/ Humidifier | E174: =A174&+C174 -> 422269019200000 | F174: 1
A175: 42226 | B175: 3006 | C175: 9018902000 | D175: Laryngoscope | E175: =A175&+C175 -> 422269018902000 | F175: 2
A176: 42226 | B176: 3013 | C176: 9405204001 | D176: Light, Exam | E176: =A176&+C176 -> 422269405204001 | F176: 2
A177: 42226 | B177: 3020 | C177: 7017900000 | D177: Lab Supply Kits | E177: =A177&+C177 -> 422267017900000 | F177: 1
A178: 42226 | B178: 3020.02 | C178: 7017900000 | D178: Lab Supply Kit, Vacutainer Tubes | E178: =A178&+C178 -> 422267017900000 | F178: 1
A179: 42226 | B179: 3020.03 | C179: 7017900000 | D179: Lab Supply Kit, Tubes | E179: =A179&+C179 -> 422267017900000 | F179: 1
A180: 42226 | B180: 3020.04 | C180: 7017900000 | D180: Lab Supply Kit, General Lab Supplies | E180: =A180&+C180 -> 422267017900000 | F180: 1
A181: 42226 | B181: 3020.05 | C181: 9018319009 | D181: Lab Supply Kit, Abg Syringes & Culture Supplies | E181: =A181&+C181 -> 422269018319009 | F181: 1
A182: 42226 | B182: 3106 | C182: 9018199000 | D182: Monitor, Clinical, 2 -4 function (NIBP, Pulse, optional TEMP & SPO2) | E182: =A182&+C182 -> 422269018199000 | F182: 2
A183: 42226 | B183: 3200 | C183: 9019200000 | D183: Nebulizer | E183: =A183&+C183 -> 422269019200000 | F183: 2
... A192: 42226 | B192: 3802.5 | C192: 9025198009 | D192: Thermometer, Patient Digital | E192: =A192&+C192 -> 422269025198009 | F192: 50
A193: 42226 | B193: 4112.1 | D193: WOUND VAC PUMP/SYSTEM, PREVENA | E193: =A193&+C193 -> 42226 | F193: 10
A194: 42226 | B194: 4112.2 | D194: Wound Vac Pump/System, Prevena Plus | E194: =A194&+C194 -> 42226 | F194: 10
A195: 42226 | B195: 5105 | C195: 9402900010 | D195: Bed, Home Healthcare | E195: =A195&+C195 -> 422269402900010 | F195: 4
A196: 42226 | B196: 5112 | C196: 9402900010 | D196: Bed, ICU | E196: =A196&+C196 -> 422269402900010 | F196: 2
A197: 42226 | B197: 5205 | C197: 9021100090 | D197: Cane, Forearm, Other | E197: =A197&+C197 -> 422269021100090 | F197: 20
...

Sheet Input data>>>

Sheet Quantity in each box
E7: Product Code | F7: HS Code | G7: Description | H7: Quantity per box
E8: 3416.0199 | F8: 90189099 | G8: Pump, IV Tubing | H8: 0
E9: 3600 | F9: 9018907500 | G9: Reflex Hammer | H9: 0
E10: 3710 | F10: 9018901000 | G10: Sphygmomanometer, Wall Mount | H10: 0
E11: 3815.45 | F11: 85043300 | G11: Transformer, 2,000 watt | H11: 0
E12: 2111 | F12: 8421192009 | G12: Centrifuge, Lab | H12: 1
E13: 2117 | F13: 9019200000 | G13: Concentrator, Oxygen | H13: 1
E14: 3013 | F14: 9405204001 | G14: Light, Exam | H14: 1
E15: 3106 | F15: 9018199000 | G15: Monitor, Clinical, 2 -4 function (NIBP, Pulse, optional TEMP & SPO2) | H15: 1
E16: 3309.1 | F16: 9019200000 | G16: Oximeter, Pulse, Battery Operated | H16: 1
E17: 3416 | F17: 90189099 | G17: Pump, IV | H17: 1
E18: 3708 | F18: 9018908409 | G18: Speculum, Non Disposable, Vaginal | H18: 1
E19: 3710.01 | F19: 9018901000 | G19: Sphygmomanometer Cuffs | H19: 1
... E33: 5108 | F33: 9402900020 | G33: Bed, Birthing | H33: 1
E34: 5108.2 | F34: 9402.90.0020 | G34: Birthing Gurney | H34: 1
E35: 5112 | F35: 9402900010 | G35: Bed, ICU | H35: 1
E36: 5115 | F36: 9402900010 | G36: Bed, Roll Out, Cot | H36: 1
E37: 5205 | F37: 9021100090 | G37: Cane, Forearm, Other | H37: 1
E38: 5206 | F38: 9021101000 | G38: Cane, Quad | H38: 1
E39: 5208 | F39: 3923100000 | G39: Cart, Crash | H39: 1
E40: 5210 | F40: 9403200000 | G40: Cart, Linen | H40: 1
E41: 5212 | F41: 3924900009 | G41: Cart, Misc / Utility | H41: 1
E42: 5221 | F42: 9401790009 | G42: Chair, Office | H42: 1
E43: 5225 | F43: 9401790009 | G43: Chair, Waiting Room | H43: 1
E44: 5228 | F44: 9403208009 | G44: Commode, Bedside | H44: 1
E45: 5236 | F45: 9402900000 | G45: Crib | H45: 1
E46: 5237 | F46: 9021101000 | G46: Crutches | H46: 1
E47: 5601 | F47: 9402.90.0020 | G47: Gurney | H47: 1
E48: 5701 | F48: 9402900000 | G48: Hoyer Lift | H48: 1
E49: 5802 | F49: 9018390000 | G49: IV Pole | H49: 1
E50: 6201 | F50: 9402900000 | G50: Vinyl Bed Surface | H50: 1
E51: 6201.1 | F51: 9402900000 | G51: Vinyl Bed Surface, ERB | H51: 1
E52: 6508 | F52: 9404900000 | G52: Pillow | H52: 1
E53: 6512 | F53: 9019200000 | G53: Privacy Curtain | H53: 1
E54: 6800.1 | F54: (blank) | G54: Scale, Adult, Electric | H54: 1
E55: 6816 | F55: 9401300009 | G55: Stool, Exam | H55: 1
E56: 6822 | F56: 9018908409 | G56: Surgical Instrument Kit, Suture Set | H56: 1
E57: 6825 | F57: 9018908409 | G57: Surgical Instrument Kit, General | H57: 1
E58: 6835 | F58: 9018900000 | G58: Surgical Instrument Kit, Delivery | H58: 1
E59: 6838 | F59: 9018908409 | G59: Surgical Instrument Kit, Ortho | H59: 1
E60: 6905 | F60: 9402900000 | G60: Table, Exam | H60: 1
E61: 6910 | F61: 9402900000 | G61: Table, Over Bed | H61: 1
E62: 6911 | F62: 9402900000 | G62: Table, Stainless Steel, Portable | H62: 1
E63: 6914 | F63: 9402900000 | G63: Table, Treatment | H63: 1
E64: 6925 | F64: (blank) | G64: Transfer Board | H64: 1
E65: 6926 | F65: 6307909200 | G65: Trash / Biohazard Waste Cans | H65: 1
E66: 7202 | F66: 9021101000 | G66: Walker, Adult | H66: 1
E67: 2600 | F67: 8513100000 | G67: Head Lamp | H67: 2
E68: 3715 | F68: 9018908409 | G68: Stethoscope | H68: 10
E69: 3308 | F69: 9018908409 | G69: Otoscope / Ophthalmoscope Wall Mounted AC Powered | H69: 25
E70: 1624.99 | F70: 6307906500 | G70: Drapes, Sterile | H70: 30
E71: 1106 | F71: 9404909000 | G71: Pads, Wedges, Positioning Pillows | H71: 47.5
E72: 1504.99 | F72: 9603290000 | G72: Scrub Brushes and Skin Prep Sets | H72: 50
E73: 308.99 | F73: 4823909000 | G73: Gowns, Patient (incl. Cloth, Paper Protector, Cover- up) | H73: 52.5
E74: 309 | F74: 4823909000 | G74: Gowns, Surgical, Non-sterile | H74: 52.5
E75: 1402.99 | F75: 9018390000 | G75: Nasal Cannulas | H75: 53
E76: 604 | F76: 3923100000 | G76: Liners, Trash Can, Laundry & Plastic Bags, Mopheads | H76: 65
... E85: 1708.99 | F85: 9018908409 | G85: Sutures and Suture Removal Kit | H85: 97.5
E86: 1801.99 | F86: 3923.29.0000 | G86: Urinary Bags (Leg and Bedside) And Urinary Supplies | H86: 97.5
E87: 1222.99 | F87: 9619008109 | G87: Underpads, (Chux and Blue Pads) | H87: 100
E88: 1609.99 | F88: 9020000000 | G88: Endotracheal Tubes | H88: 100
E89: 712.99 | F89: 9018310040 | G89: Syringes, 10cc & 12cc | H89: 120
E90: 803.99 | F90: 3923100000 | G90: Containers and Labels, Lab | H90: 130
E91: 703.99 | F91: 9018390030 | G91: IV Catheters/ Including Huber, Butterfly, Fistula | H91: 135
E92: 504.99 | F92: 3005909900 | G92: Bandaids, Steristrips, Tape, Transparent Dressings (tegaderm) | H92: 214.5
E93: 711.99 | F93: 9018310040 | G93: Syringes, 5cc & 6cc | H93: 275
E94: 305.99 | F94: 3926201010 | G94: Gloves, Non-sterile | H94: 325
E95: 701.99 | F95: 9018390000 | G95: Buffalo caps, prn adaptors and other iv infusion supplies, vial spikes and adaptators | H95: 390
E96: 709.99 | F96: 9018310040 | G96: Syringes, 1 cc/tb | H96: 500
E97: 710.99 | F97: 9018310040 | G97: Syringes, 3cc | H97: 500
E98: 716.99 | F98: 9018310040 | G98: Syringes, Insulin | H98: 591.5
... E103: 302 | F103: 6307909800 | G103: Surgical Caps And Hats, Shoe Covers | H103: 1550
E104: 6203 | F104: 9403208009 | G104: Mayo Stand | H104: NA
E105: 6500 | F105: 4819100000 | G105: Paper, Exam Table Rolls in Boxes | H105: NA
E106: 301 | F106: 6302210000 | G106: Bed Linens And Towels | H106: NA
E107: 306.99 | F107: 3926201010 | G107: Gloves, Sterile | H107: NA
E108: 307.199 | F108: 9004909000 | G108: Masks, surgical | H108: NA
E109: 310.99 | F109: 6211320000 | G109: Gowns, Surgical, Sterile | H109: NA
E110: 311 | F110: 6211320000 | G110: Lab Coats And Tunics, Scrub Suits, Surgical | H110: NA
E111: 311.1 | F111: 6211320000 | G111: Scrubs, FIG | H111: NA
E112: 501.99 | F112: 3006100100 | G112: 2x2, 4x4, Abd Sterile Dressings | H112: NA
E113: 511.99 | F113: 3006100100 | G113: Specialty Dressings (and All Other Dressings Not Fitting In Other Categories) | H113: NA
E114: 601 | F114: 3006500000 | G114: Bags, Red, Spill Kits And Isolyszer | H114: NA
E115: 602.99 | F115: 3808940000 | G115: Disinfectant, Non-Patient; Also Sterilization Products & Sprays (Cidex, Etc) | H115: NA
... E125: 1108 | F125: 9021109000 | G125: Splints, Wraps (including Ace), and Slings, Hose Ted (anti-embolism) | H125: NA
E126: 1109 | F126: 9021.10.99 | G126: Braces | H126: NA
E127: 1203 | F127: 9021101000 | G127: Bedpans And Urinals | H127: NA
E128: 1207 | F128: 9619008901 | G128: Diapers, Adult | H128: NA
E129: 1210.99 | F129: 9018900000 | G129: Feeding Tubes, Bags, Pump Set and Supplies | H129: NA
E130: 1216 | F130: 4818909000 | G130: Paper Supplies, Towels, Cups, Napkins, Toilet Paper, Dishes | H130: NA
E131: 1404.99 | F131: 90200000 | G131: Oxygen Masks and Tubing | H131: NA
E132: 1405.99 | F132: 9033000000 | G132: Respiratory Supplies, Other | H132: NA
E133: 1406.99 | F133: 9018390030 | G133: Suction Catheter & Glove Kit | H133: NA
E134: 1603.99 | F134: 9018900000 | G134: Ambu Bags | H134: NA
E135: 1617.99 | F135: 9018908409 | G135: General Surgery Packs and Supplies | H135: NA
E136: 1619.99 | F136: 90180000000 | G136: OB/GYN Surgery Packs & Supplies | H136: NA
E137: 1620.99 | F137: 9021101000 | G137: Orthopedic Surgery Packs and Supplies | H137: NA
E138: 1625.99 | F138: 901819 | G138: Tracheostomy & Cricothyroidotomy supplies, tubes and kits | H138: NA
... E153: 7217 | F153: 8713100000 | G153: Wheelchair, Adult | H153: NA

Sheet 12259
A1: Shipper: Project C.U.R.E. Project # 12259 Planned Manifest Country of Destination Ukraine
A2: Product Code | B2: HS Code | D2: Description | F2: Transformer Needed (only for 220-240V countries) | G2: Number Ordered
A3: Aid Pioneers - Ukraine Relief
A4: 301 | B4: 6302210000 | D4: Bed Linens And Towels | G4: 20
A5: 302 | B5: 6307909800 | D5: Surgical Caps And Hats, Shoe Covers | G5: 20
A6: 303 | B6: 6307.90.9995 | D6: Cloth Products Not Fitting In Other Items, Cubical Curtains | G6: 5
A7: 305.99 | B7: 3926201010 | D7: Gloves, Non-sterile | G7: 160
A8: 310.99 | B8: 6211320000 | D8: Gowns, Surgical, Sterile | G8: 50
A9: 501.99 | B9: 3006100100 | D9: 2x2, 4x4, Abd Sterile Dressings | G9: 10
A10: 504.99 | B10: 3005909900 | D10: Bandaids, Steristrips, Tape, Transparent Dressings (tegaderm) | G10: 15
A11: 507.99 | B11: 3005909900 | D11: Kerlix/Kling Dressing | G11: 5
A12: 511.99 | B12: 3006100100 | D12: Specialty Dressings (and All Other Dressings Not Fitting In Other Categories) | G12: 15
A13: 601 | B13: 3006500000 | D13: Bags, Red, Spill Kits And Isolyszer | G13: 15
A14: 606 | B14: 3923100000 | D14: Sharps Containers, Send Only w/ Lids | G14: 10
A15: 608.99 | B15: 3006101000 | D15: Sterilization, Tapes, Indicators, Wraps & Pouches | G15: 10
A16: 701.99 | B16: 9018390000 | D16: Buffalo caps, prn adaptors and other iv infusion supplies, vial spikes and adaptators | G16: 7
A17: 702.99 | B17: 9018390000 | D17: Central Percutaneous Lines | G17: 5
A18: 703.99 | B18: 9018390030 | D18: IV Catheters/ Including Huber, Butterfly, Fistula | G18: 5
... A30: 1006 | B30: 9619009000 | D30: Feminine Supplies - (including Pads, Belts, Perineal Wash, Sitz Baths) | G30: 5
A31: Product Code | B31: HS Code | D31: Description | F31: Transformer Needed (only for 220-240V countries) | G31: Number Ordered
A32: Aid Pioneers - Ukraine Relief
A33: 1103.99 | B33: 3005909900 | D33: Casting Supplies, Stockinette, Web Roll, Plaster, Fiberglass, Cast Shoes, Cast Heels | G33: 15
A34: 1108 | B34: 9021109000 | D34: Splints, Wraps (including Ace), and Slings, Hose Ted (anti-embolism) | G34: 20
A35: 1202.99 | B35: 3005905000 | D35: Applicator Swabs (Q-Tips), Tongue Depressors, Cotton Balls | G35: 5
A36: 1205 | B36: 7010901009 | D36: Containers, Basins, Emesis, Water Mugs, Pitchers, Glassware | G36: 5
A37: 1207 | B37: 9619008901 | D37: Diapers, Adult | G37: 40
A38: 1216 | B38: 4818909000 | D38: Paper Supplies, Towels, Cups, Napkins, Toilet Paper, Dishes | G38: 15
A39: 1217.99 | B39: 3307900008 | D39: Patient Supplies (Soaps, Shampoos, Mouthwash, Toothpaste, Belonging Bags),slippers | G39: 40
A40: 1222.99 | B40: 9619008109 | D40: Underpads, (Chux and Blue Pads) | G40: 20
A41: 1403.99 | B41: 9019200000 | D41: Nebulizer Supplies | G41: 5
A42: 1405.99 | B42: 9033000000 | D42: Respiratory Supplies, Other | G42: 2
A43: 1406.99 | B43: 9018390030 | D43: Suction Catheter & Glove Kit | G43: 20
A44: 1602.99 | B44: 9018903000 | D44: Anesthesia Facemasks | G44: 5
... A54: 1707.99 | B54: 9018390030 | D54: Suction Catheter, Tips, Tubings & Connectors | G54: 10
A55: 1801.99 | B55: 3923.29.0000 | D55: Urinary Bags (Leg and Bedside) And Urinary Supplies | G55: 2
A56: 1802.99 | B56: 9018390030 | D56: Urinary Catheters, Trays & Insertion Sets | G56: 5
A57: 2111 | B57: 8421192009 | D57: Centrifuge, Lab | F57: 3815.4 | G57: 1
A58: 2117.1 | B58: 9019200000 | D58: Concentrator, Oxygen | G58: 34
A59: 2120.0199 | B59: 9019200000 | D59: CPAP Supplies | F59: none | G59: 1
A60: 2120.1 | B60: 9019200000 | D60: CPAP Unit W/ Humidifier | F60: 3815.25 | G60: 1
A61: 2610 | B61: 8419000000 | D61: Heater | F61: 3815.42 | G61: 1
A62: 3106 | B62: 9018199000 | D62: Monitor, Clinical, 2 -4 function (NIBP, Pulse, optional TEMP & SPO2) | F62: 3815.2 | G62: 2
A63: Product Code | B63: HS Code | D63: Description | F63: Transformer Needed (only for 220-240V countries) | G63: Number Ordered
A64: Aid Pioneers - Ukraine Relief
A65: 3110 | B65: 9018199000 | D65: Monitor, vital signs, 5 function (NIPB,Pulse, Optional TEMP,SPO2,ECG) | F65: 3815.15 | G65: 2
A66: 3200 | B66: 9019200000 | D66: Nebulizer | F66: 3815.25 | G66: 2
A67: 3309 | B67: 8543700000 | D67: Oximeter, Pulse, eletrical plug | F67: 3815.2 | G67: 2
A68: 3309.0599 | B68: 9019200000 | D68: O2 Sensor, Other | F68: none | G68: 2
A69: 3309.1 | B69: 9019200000 | D69: Oximeter, Pulse, Battery Operated | F69: none | G69: 5
A70: 3312 | B70: 9017308000 | D70: Oxygen Tank Regulator | F70: none | G70: 5
A71: 3316 | B71: 9018.19.4000 | D71: Otoscope and Ophthalmoscope, Rechargable Nickel Battery-Powered | F71: 3815.15 | G71: 1
A72: 3407 | B72: 90189099 | D72: Pump, IV Pressure Infusor | F72: 3815.15 | G72: 1
A73: 3416 | B73: 90189099 | D73: Pump, IV | F73: 3815.15 | G73: 1
A74: 3416.0199 | B74: 90189099 | D74: Pump, IV Tubing | F74: none | G74: 1
A75: 3418 | B75: 90189099 | D75: Pump, Syringe, Infuser | F75: 3815.15 | G75: 2
A76: 3716 | B76: 9018901000 | D76: Adult Blood Pressure Cuff, Battery | F76: none | G76: 2
A77: 3718 | B77: 9018908409 | D77: Suction Machine / Low Pressure / Portable | F77: 3815.25 | G77: 1
A78: 3802.6 | B78: 9025190000 | D78: Hospital Grade Thermometer, Forehead,105801 | F78: none | G78: 15
A79: 5111 | B79: 9402900000 | D79: Bed, Electric | F79: 3815.42 | G79: 2
A80: 5112 | B80: 9402900010 | D80: Bed, ICU | F80: 3815.42 | G80: 2
A81: 5200 | B81: 9403100040 | D81: Cabinet, Bedside | F81: none | G81: 2
A82: 5205 | B82: 9021100090 | D82: Cane, Forearm, Other | F82: none | G82: 10
A83: 5210 | B83: 9403200000 | D83: Cart, Linen | F83: none | G83: 2
A84: 5213 | B84: 9402900000 | D84: Cart, Oxygen Cylinder | F84: none | G84: 5
A85: 5221 | B85: 9401790009 | D85: Chair, Office | F85: none | G85: 2
A86: 5224 | B86: 9402000000 | D86: Chair, Surgical, ENT, Procedure | F86: 3815.4 | G86: 1
A87: 5225 | B87: 9401790009 | D87: Chair, Waiting Room | F87: none | G87: 5
A88: 5228 | B88: 9403208009 | D88: Commode, Bedside | F88: none | G88: 8
A89: 5237 | B89: 9021101000 | D89: Crutches | F89: none | G89: 5
A90: 5240 | B90: 9019200000 | D90: C.U.R.E. Kits for Kids | F90: none | G90: 20
A91: 5501 | B91: 9403109300 | D91: File Cabinet | F91: none | G91: 1
A92: 5601 | B92: 9402.90.0020 | D92: Gurney | F92: none | G92: 4
A93: 5802 | B93: 9018390000 | D93: IV Pole | F93: none | G93: 5
A94: 6201 | B94: 9402900000 | D94: Vinyl Bed Surface | F94: none | G94: 4
A95: 6201.1 | B95: 9402900000 | D95: Vinyl Bed Surface, ERB | F95: none | G95: 32
A96: 6203 | B96: 9403208009 | D96: Mayo Stand | F96: none | G96: 1
A97: 6816 | B97: 9401300009 | D97: Stool, Exam | F97: none | G97: 2
A98: 6822 | B98: 9018908409 | D98: Surgical Instrument Kit, Suture Set | F98: none | G98: 1
A99: 6825 | B99: 9018908409 | D99: Surgical Instrument Kit, General | F99: none | G99: 1
A100: 6835 | B100: 9018900000 | D100: Surgical Instrument Kit, Delivery | F100: none | G100: 1
A101: Product Code | B101: HS Code | D101: Description | F101: Transformer Needed (only for 220-240V countries) | G101: Number Ordered
A102: Aid Pioneers - Ukraine Relief
A103: 6905 | B103: 9402900000 | D103: Table, Exam | F103: none | G103: 2
A104: 6916 | B104: 7311000000 | D104: Tank, Oxygen Size A thru D (5 - 16" Ht) | F104: none | G104: 5
A105: 6917 | B105: 7311000000 | D105: Tank, Oxygen Size E (25" Ht) | F105: none | G105: 5
A106: 6926 | B106: 6307909200 | D106: Trash / Biohazard Waste Cans | F106: none | G106: 5
A107: 7202 | B107: 9021101000 | D107: Walker, Adult | F107: none | G107: 10
A108: Transformer Size Reference
A109: Transformer # | C109: Transformer Size (Watts)
A110: 3815.1 | C110: Transformer, 50 Watt
A111: 3815.15 | C111: Transformer, 100 watt
A112: 3815.2 | C112: Transformer, 200 Watt
A113: 3815.25 | C113: Transformer, 300 watt
A114: 3815.3 | C114: Transformer, 500 Watt
A115: 3815.35 | C115: Transformer, 750 watt
A116: 3815.4 | C116: Transformer, 1,000 Watt
A117: 3815.42 | C117: Transformer, 1,500 watts
A118: 3815.45 | C118: Transformer, 2,000 watt
A119: 3815.5 | C119: Transformer, 3,000 Watt
A120: 3815.55 | C120: Transformer, 5,000 watt
...

Sheet 22226
A1: Shipper: Project C.U.R.E. Project # 22226 Planned Manifest Country of Destination Ukraine
A2: Product Code | B2: HS Code | D2: Description | F2: Transformer Needed (only for 220-240V countries) | G2: Number Ordered
A3: Aid Pioneers Ukraine Relief
A4: 302 | B4: 6307909800 | D4: Surgical Caps And Hats, Shoe Covers | G4: 20
A5: 305.99 | B5: 3926201010 | D5: Gloves, Non-sterile | G5: 75
A6: 306.99 | B6: 3926201010 | D6: Gloves, Sterile | G6: 10
A7: 308.99 | B7: 4823909000 | D7: Gowns, Patient (incl. Cloth, Paper Protector, Cover- up) | G7: 15
A8: 310.99 | B8: 6211320000 | D8: Gowns, Surgical, Sterile | G8: 35
A9: 311.1 | B9: 6211320000 | D9: Scrubs, FIG | F9: none | G9: 10
A10: 501.99 | B10: 3006100100 | D10: 2x2, 4x4, Abd Sterile Dressings | G10: 5
A11: 504.99 | B11: 3005909900 | D11: Bandaids, Steristrips, Tape, Transparent Dressings (tegaderm) | G11: 10
A12: 511.99 | B12: 3006100100 | D12: Specialty Dressings (and All Other Dressings Not Fitting In Other Categories) | G12: 5
A13: 602.99 | B13: 3808940000 | D13: Disinfectant, Non-Patient; Also Sterilization Products & Sprays (Cidex, Etc) | G13: 5
A14: 608.99 | B14: 3006101000 | D14: Sterilization, Tapes, Indicators, Wraps & Pouches | G14: 5
A15: 708.99 | B15: 9018310040 | D15: Needles, Mixed Gauges | G15: 20
A16: 710.99 | B16: 9018310040 | D16: Syringes, 3cc | G16: 20
A17: 801.99 | B17: 9018900000 | D17: Blood Drawing Supplies (Vacutainer Holders & Needles, Butterflies, Lancets, Tourniquets) | G17: 10
A18: 803.99 | B18: 3923100000 | D18: Containers and Labels, Lab | G18: 5
A19: 1004 | B19: 9619009000 | D19: Diapers and Wipes | G19: 20
A20: 1006 | B20: 9619009000 | D20: Feminine Supplies - (including Pads, Belts, Perineal Wash, Sitz Baths) | G20: 10
A21: 1103.99 | B21: 3005909900 | D21: Casting Supplies, Stockinette, Web Roll, Plaster, Fiberglass, Cast Shoes, Cast Heels | G21: 5
... A30: 1603.99 | B30: 9018900000 | D30: Ambu Bags | G30: 5
A31: Product Code | B31: HS Code | D31: Description | F31: Transformer Needed (only for 220-240V countries) | G31: Number Ordered
A32: Aid Pioneers Ukraine Relief
A33: 1607.99 | B33: 9018908409 | D33: Drains, Surgical, including Penrose and Suction Types | G33: 2
A34: 1609.99 | B34: 9020000000 | D34: Endotracheal Tubes | G34: 5
A35: 1610.99 | B35: 9018321000 | D35: Epidural / Spinal Needles and Kits | G35: 2
A36: 1619.99 | B36: 90180000000 | D36: OB/GYN Surgery Packs & Supplies | G36: 8
A37: 1620.99 | B37: 9021101000 | D37: Orthopedic Surgery Packs and Supplies | G37: 15
A38: 1624.99 | B38: 6307906500 | D38: Drapes, Sterile | G38: 10
A39: 1625.99 | B39: 901819 | D39: Tracheostomy & Cricothyroidotomy supplies, tubes and kits | G39: 2
A40: 1633.99 | B40: 9018903000 | D40: Anesthesia Laryngeal Mask Airway, lma | G40: 8
A41: 1706.99 | B41: 9018390000 | D41: Suction Canisters & Lids | G41: 2
A42: 1707.99 | B42: 9018390030 | D42: Suction Catheter, Tips, Tubings & Connectors | G42: 5
A43: 2117.1 | B43: 9019200000 | D43: Concentrator, Oxygen | G43: 46
A44: 2120.0199 | B44: 9019200000 | D44: CPAP Supplies | F44: none | G44: 1
A45: 2120.1 | B45: 9019200000 | D45: CPAP Unit W/ Humidifier | F45: 3815.25 | G45: 1
A46: 2602 | B46: 8479891000 | D46: Humidifier, Whole Room Air Mist | F46: 3815.15 | G46: 2
A47: 3006 | B47: 9018902000 | D47: Laryngoscope | F47: none | G47: 3
A48: 3013 | B48: 9405204001 | D48: Light, Exam | F48: 3815.15 | G48: 2
A49: 3106 | B49: 9018199000 | D49: Monitor, Clinical, 2 -4 function (NIBP, Pulse, optional TEMP & SPO2) | F49: 3815.2 | G49: 4
A50: 3200 | B50: 9019200000 | D50: Nebulizer | F50: 3815.25 | G50: 2
A51: 3307 | B51: 9018908409 | D51: Otoscope / Ophthalmoscope, Alkaline-Battery Operated | F51: 3815.15 | G51: 1
A52: 3307.01 | B52: 9018908409 | D52: Otoscope Covers/Tips | F52: none | G52: 1
A53: 3309.1 | B53: 9019200000 | D53: Oximeter, Pulse, Battery Operated | F53: none | G53: 5
A54: 3600 | B54: 9018907500 | D54: Reflex Hammer | F54: none | G54: 2
A55: 3711 | B55: 9018901000 | D55: Sphygmomanometer, Aneroid, Hand Held | F55: none | G55: 2
A56: 3715 | B56: 9018908409 | D56: Stethoscope | F56: none | G56: 2
A57: 3715.1 | B57: 9018908409 | D57: Stethoscope, Disposable | F57: none | G57: 2
A58: 3718 | B58: 9018908409 | D58: Suction Machine / Low Pressure / Portable | F58: 3815.25 | G58: 1
A59: 3802.7 | B59: 9025190000 | D59: Clinic Grade Thermometer, Forehead,105800 | F59: none | G59: 32
A60: 5110 | B60: 9402900010 | D60: Bed, Emergency Relief, Patient | F60: none | G60: 10
A61: 5112 | B61: 9402900010 | D61: Bed, ICU | F61: 3815.42 | G61: 4
A62: 5205 | B62: 9021100090 | D62: Cane, Forearm, Other | F62: none | G62: 5
A63: 5206 | B63: 9021101000 | D63: Cane, Quad | F63: none | G63: 7
A64: 5225 | B64: 9401790009 | D64: Chair, Waiting Room | F64: none | G64: 2
A65: 5228 | B65: 9403208009 | D65: Commode, Bedside | F65: none | G65: 5
A66: 5237 | B66: 9021101000 | D66: Crutches | F66: none | G66: 15
A67: 5242 | D67: MSD Postnatal Kits | F67: none | G67: 25
A68: Product Code | B68: HS Code | D68: Description | F68: Transformer Needed (only for 220-240V countries) | G68: Number Ordered
A69: Aid Pioneers Ukraine Relief
A70: 5260 | D70: Crutches, Forearm | F70: none | G70: 5
A71: 5300 | B71: 9403100000 | D71: Desk | F71: none | G71: 1
A72: 5601 | B72: 9402.90.0020 | D72: Gurney | F72: none | G72: 3
A73: 5701 | B73: 9402900000 | D73: Hoyer Lift | F73: none | G73: 2
A74: 5802 | B74: 9018390000 | D74: IV Pole | F74: none | G74: 8
A75: 6201 | B75: 9402900000 | D75: Vinyl Bed Surface | F75: none | G75: 4
A76: 6201.1 | B76: 9402900000 | D76: Vinyl Bed Surface, ERB | F76: none | G76: 48
A77: 6816 | B77: 9401300009 | D77: Stool, Exam | F77: none | G77: 2
A78: 6822 | B78: 9018908409 | D78: Surgical Instrument Kit, Suture Set | F78: none | G78: 3
A79: 6825 | B79: 9018908409 | D79: Surgical Instrument Kit, General | F79: none | G79: 2
A80: 6835 | B80: 9018900000 | D80: Surgical Instrument Kit, Delivery | F80: none | G80: 1
A81: 6838 | B81: 9018908409 | D81: Surgical Instrument Kit, Ortho | F81: none | G81: 2
A82: 6905 | B82: 9402900000 | D82: Table, Exam | F82: none | G82: 4
A83: 6910 | B83: 9402900000 | D83: Table, Over Bed | F83: none | G83: 2
A84: 7202 | B84: 9021101000 | D84: Walker, Adult | F84: none | G84: 20
A85: 7203 | B85: 9021100090 | D85: Walker, Pediatric / Infant | F85: none | G85: 2
A86: Transformer Size Reference
A87: Transformer # | C87: Transformer Size (Watts)
A88: 3815.1 | C88: Transformer, 50 Watt
A89: 3815.15 | C89: Transformer, 100 watt
A90: 3815.2 | C90: Transformer, 200 Watt
A91: 3815.25 | C91: Transformer, 300 watt
A92: 3815.3 | C92: Transformer, 500 Watt
A93: 3815.35 | C93: Transformer, 750 watt
A94: 3815.4 | C94: Transformer, 1,000 Watt
A95: 3815.42 | C95: Transformer, 1,500 watts
A96: 3815.45 | C96: Transformer, 2,000 watt
A97: 3815.5 | C97: Transformer, 3,000 Watt
A98: 3815.55 | C98: Transformer, 5,000 watt
A99: 3815.6 | C99: Transformer, 8,000 watt
... A101: 3815.7 | C101: Transformer, 20,000 watt

Sheet 42226
A1: Shipper: Project C.U.R.E. Project # 42226 Planned Manifest Country of Destination Ukraine
A2: Product Code | B2: HS Code | D2: Description | F2: Transformer Needed (only for 220-240V countries) | G2: Number Ordered
A3: Aid Pioneers - Ukraine Relief
A4: 302 | B4: 6307909800 | D4: Surgical Caps And Hats, Shoe Covers | G4: 20
A5: 305.99 | B5: 3926201010 | D5: Gloves, Non-sterile | G5: 40
A6: 308.99 | B6: 4823909000 | D6: Gowns, Patient (incl. Cloth, Paper Protector, Cover- up) | G6: 10
A7: 310.99 | B7: 6211320000 | D7: Gowns, Surgical, Sterile | G7: 25
A8: 311.1 | B8: 6211320000 | D8: Scrubs, FIG | F8: none | G8: 10
A9: 401.99 | B9: 4421900000 | D9: Dental Supplies | G9: 10
A10: 501.99 | B10: 3006100100 | D10: 2x2, 4x4, Abd Sterile Dressings | G10: 10
A11: 504.99 | B11: 3005909900 | D11: Bandaids, Steristrips, Tape, Transparent Dressings (tegaderm) | G11: 5
A12: 505.99 | B12: 3005590000 | D12: Dressing Change Kits, Laceration Trays, Wound Care Kits | G12: 10
A13: 507.99 | B13: 3005909900 | D13: Kerlix/Kling Dressing | G13: 2
A14: 511.99 | B14: 3006100100 | D14: Specialty Dressings (and All Other Dressings Not Fitting In Other Categories) | G14: 5
A15: 601 | B15: 3006500000 | D15: Bags, Red, Spill Kits And Isolyszer | G15: 10
A16: 604 | B16: 3923100000 | D16: Liners, Trash Can, Laundry & Plastic Bags, Mopheads | G16: 15
A17: 606 | B17: 3923100000 | D17: Sharps Containers, Send Only w/ Lids | G17: 15
A18: 608.99 | B18: 3006101000 | D18: Sterilization, Tapes, Indicators, Wraps & Pouches | G18: 5
A19: 701.99 | B19: 9018390000 | D19: Buffalo caps, prn adaptors and other iv infusion supplies, vial spikes and adaptators | G19: 2
A20: 702.99 | B20: 9018390000 | D20: Central Percutaneous Lines | G20: 2
... A31: 1001.99 | B31: 9619008101 | D31: Baby and birthing supplies | G31: 5
A32: Product Code | B32: HS Code | D32: Description | F32: Transformer Needed (only for 220-240V countries) | G32: Number Ordered
A33: Aid Pioneers - Ukraine Relief
A34: 1004 | B34: 9619009000 | D34: Diapers and Wipes | G34: 10
A35: 1006 | B35: 9619009000 | D35: Feminine Supplies - (including Pads, Belts, Perineal Wash, Sitz Baths) | G35: 5
A36: 1101 | B36: 3005900000 | D36: Activities Of Daily Living Aids (including Dressing Aids), Pt Supplies | G36: 5
A37: 1103.99 | B37: 3005909900 | D37: Casting Supplies, Stockinette, Web Roll, Plaster, Fiberglass, Cast Shoes, Cast Heels | G37: 15
A38: 1106 | B38: 9404909000 | D38: Pads, Wedges, Positioning Pillows | G38: 15
A39: 1108 | B39: 9021109000 | D39: Splints, Wraps (including Ace), and Slings, Hose Ted (anti-embolism) | G39: 40
A40: 1201 | B40: 7017900000 | D40: Admission Kits | G40: 2
A41: 1203 | B41: 9021101000 | D41: Bedpans And Urinals | G41: 10
A42: 1205 | B42: 7010901009 | D42: Containers, Basins, Emesis, Water Mugs, Pitchers, Glassware | G42: 2
A43: 1207 | B43: 9619008901 | D43: Diapers, Adult | G43: 30
A44: 1216 | B44: 4818909000 | D44: Paper Supplies, Towels, Cups, Napkins, Toilet Paper, Dishes | G44: 20
A45: 1222.99 | B45: 9619008109 | D45: Underpads, (Chux and Blue Pads) | G45: 15
... A56: 1701 | B56: 3005909900 | D56: Drapes, Non-sterile | G56: 10
A57: 1801.99 | B57: 3923.29.0000 | D57: Urinary Bags (Leg and Bedside) And Urinary Supplies | G57: 5
A58: 1802.99 | B58: 9018390030 | D58: Urinary Catheters, Trays & Insertion Sets | G58: 5
A59: 2002.0199 | B59: 9019200000 | D59: Bipap Supplies | F59: none | G59: 1
A60: 2104 | B60: 9018900000 | D60: Cast Saw | F60: 3815.4 | G60: 1
A61: 2114 | D61: Compression System, Chest | F61: 3815.15 | G61: 1
A62: 2117.1 | B62: 9019200000 | D62: Concentrator, Oxygen | G62: 69
A63: 2120.0199 | B63: 9019200000 | D63: CPAP Supplies | F63: none | G63: 1
A64: 2120.1 | B64: 9019200000 | D64: CPAP Unit W/ Humidifier | F64: 3815.25 | G64: 1
A65: 3006 | B65: 9018902000 | D65: Laryngoscope | F65: none | G65: 2
A66: Product Code | B66: HS Code | D66: Description | F66: Transformer Needed (only for 220-240V countries) | G66: Number Ordered
A67: Aid Pioneers - Ukraine Relief
A68: 3013 | B68: 9405204001 | D68: Light, Exam | F68: 3815.15 | G68: 2
A69: 3020 | B69: 7017900000 | D69: Lab Supply Kits | F69: none | G69: 1
A70: 3020.02 | B70: 7017900000 | D70: Lab Supply Kit, Vacutainer Tubes | F70: none | G70: 1
A71: 3020.03 | B71: 7017900000 | D71: Lab Supply Kit, Tubes | F71: none | G71: 1
A72: 3020.04 | B72: 7017900000 | D72: Lab Supply Kit, General Lab Supplies | F72: none | G72: 1
A73: 3020.05 | B73: 9018319009 | D73: Lab Supply Kit, Abg Syringes & Culture Supplies | F73: none | G73: 1
A74: 3106 | B74: 9018199000 | D74: Monitor, Clinical, 2 -4 function (NIBP, Pulse, optional TEMP & SPO2) | F74: 3815.2 | G74: 2
A75: 3200 | B75: 9019200000 | D75: Nebulizer | F75: 3815.25 | G75: 2
A76: 3309 | B76: 8543700000 | D76: Oximeter, Pulse, eletrical plug | F76: 3815.2 | G76: 2
A77: 3309.0599 | B77: 9019200000 | D77: O2 Sensor, Other | F77: none | G77: 2
A78: 3309.1 | B78: 9019200000 | D78: Oximeter, Pulse, Battery Operated | F78: none | G78: 70
A79: 3711 | B79: 9018901000 | D79: Sphygmomanometer, Aneroid, Hand Held | F79: none | G79: 2
A80: 3714 | B80: 8419200000 | D80: Disposable Speculum | G80: 5
A81: 3715 | B81: 9018908409 | D81: Stethoscope | F81: none | G81: 2
A82: 3715.1 | B82: 9018908409 | D82: Stethoscope, Disposable | F82: none | G82: 10
A83: 3718 | B83: 9018908409 | D83: Suction Machine / Low Pressure / Portable | F83: 3815.25 | G83: 2
A84: 3802.5 | B84: 9025198009 | D84: Thermometer, Patient Digital | F84: none | G84: 50
A85: 4112.1 | D85: WOUND VAC PUMP/SYSTEM, PREVENA | F85: none | G85: 10
A86: 4112.2 | D86: Wound Vac Pump/System, Prevena Plus | F86: none | G86: 10
A87: 5105 | B87: 9402900010 | D87: Bed, Home Healthcare | F87: 3815.3 | G87: 4
A88: 5112 | B88: 9402900010 | D88: Bed, ICU | F88: 3815.42 | G88: 2
A89: 5205 | B89: 9021100090 | D89: Cane, Forearm, Other | F89: none | G89: 20
A90: 5206 | B90: 9021101000 | D90: Cane, Quad | F90: none | G90: 5
A91: 5211 | B91: 9403200000 | D91: Cart, Medication | F91: none | G91: 1
A92: 5228 | B92: 9403208009 | D92: Commode, Bedside | F92: none | G92: 15
A93: 5237 | B93: 9021101000 | D93: Crutches | F93: none | G93: 20
A94: 5238 | B94: 9021101000 | D94: Crutches, Pediatric / Infant | F94: none | G94: 10
A95: 5240 | B95: 9019200000 | D95: C.U.R.E. Kits for Kids | F95: none | G95: 20
A96: 5601 | B96: 9402.90.0020 | D96: Gurney | F96: none | G96: 4
A97: 5802 | B97: 9018390000 | D97: IV Pole | F97: none | G97: 8
A98: 6201 | B98: 9402900000 | D98: Vinyl Bed Surface | F98: none | G98: 6
A99: 6201.1 | B99: 9402900000 | D99: Vinyl Bed Surface, ERB | F99: none | G99: 32
A100: 6820 | B100: 9018908409 | D100: Surgical Instrument Kit, Arthrex | F100: none | G100: 4
A101: 6822 | B101: 9018908409 | D101: Surgical Instrument Kit, Suture Set | F101: none | G101: 1
A102: 6825 | B102: 9018908409 | D102: Surgical Instrument Kit, General | F102: none | G102: 2
A103: 6838 | B103: 9018908409 | D103: Surgical Instrument Kit, Ortho | F103: none | G103: 1
A104: 6853 | D104: Surgical Instrument Kit, Surgical Staplers | F104: none | G104: 1
A105: Product Code | B105: HS Code | D105: Description | F105: Transformer Needed (only for 220-240V countries) | G105: Number Ordered
A106: Aid Pioneers - Ukraine Relief
A107: 6905 | B107: 9402900000 | D107: Table, Exam | F107: none | G107: 2
A108: 6926 | B108: 6307909200 | D108: Trash / Biohazard Waste Cans | F108: none | G108: 2
A109: 7202 | B109: 9021101000 | D109: Walker, Adult | F109: none | G109: 10
A110: 7211 | B110: 8713109000 | D110: Wheelchair Transport Unit | F110: none | G110: 4
A111: Transformer Size Reference
A112: Transformer # | C112: Transformer Size (Watts)
A113: 3815.1 | C113: Transformer, 50 Watt
A114: 3815.15 | C114: Transformer, 100 watt
A115: 3815.2 | C115: Transformer, 200 Watt
A116: 3815.25 | C116: Transformer, 300 watt
A117: 3815.3 | C117: Transformer, 500 Watt
A118: 3815.35 | C118: Transformer, 750 watt
A119: 3815.4 | C119: Transformer, 1,000 Watt
A120: 3815.42 | C120: Transformer, 1,500 watts
...

Sheet 72204
A1: Commercial Invoice
A2: Exporter Name and Address Project C.U.R.E. 10377 E. Geddes Ave Ste. 200 Centennial, CO 80112, USA Contact: Steven Wagener, Director of Logistics Phone: 303-792-0729, stevenwagener@projectcure.org | F2: Shipper Name and Address Project C.U.R.E. 10377 E. Geddes Ave Ste. 200 Centennial, CO 80112, USA Contact: Steven Wagener, Director of Logistics Phone: 303-792-0729, stevenwagener@projectcure.org
A3: Exporter Tax ID 84-1568566 | D3: Date Issued | F3: Invoice # 72204
A4: Freight Forwarder Name / Address Flexport , | F4: Final Destination Name / Address ,
A5: Commodity: Donated Medical Equipment and Supplies
A6: Consignee Name and Address "Heart for the Children of Ukraine" 2, Budivelnykiv Street Rivne City, Rivne Region 33004 Ukraine Tetiana Kidruk +380 63 995 1389 tetiana.kidruk@gmail.com | F6: Notify Party (if applicable) ,
A7: Vessel Name | D7: Voyage Number | F7: Port of Export | J7: Incoterms Handling Only to EXW Kansas City
A8: Carrier Name | D8: Container # | F8: Seal #
A9: Country of Destination Ukraine | D9: Bill of Lading # | F9: Project # 72204 | J9: Terms of Payment Pre-Paid
A10: Country of Origin / Export: U.S.A. | D10: Method of Transportation Ocean | F10: # of Packages 260 | J10: Weight of Goods (kg) 1495.76
A11: Product Code | B11: HS Code | C11: Description | E11: Transformer Needed (only for 220-240V countries) | G11: # Pieces/ Cartons | H11: Total Quantity | I11: Net Weight (kg) | K11: Unit Value ($) | L11: Total Value ($)
A12: 1108 | B12: 9021109000 | C12: Splints, Wraps (including Ace), and Slings, Hose Ted (anti- embolism) | G12: 14 | H12: 328 | I12: 86.73 | K12: 10.3 | L12: 3378.4
A13: 1402.99 | B13: 9018390000 | C13: Nasal Cannulas | G13: 45 | H13: 2424 | I13: 220.72 | K13: 1.03 | L13: 2496.72
A14: 1404.99 | B14: 90200000 | C14: Oxygen Masks and Tubing | G14: 28 | H14: 1563 | I14: 112.94 | K14: 3.03 | L14: 4735.89
A15: 1603 | B15: 9018900000 | C15: Ambu Bags | G15: 31 | H15: 908 | I15: 108.77 | K15: 25 | L15: 22700
A16: 1603.99 | B16: 9018900000 | C16: Ambu Bags | G16: 18 | H16: 362 | I16: 91.58 | K16: 25 | L16: 9050
A17: 1607 | B17: 9018908409 | C17: Drains, Surgical, including Penrose and Suction Types | G17: 2 | H17: 89 | I17: 10.16 | K17: 15.05 | L17: 1339.45
A18: 1607.99 | B18: 9018908409 | C18: Drains, Surgical, including Penrose and Suction Types | G18: 1 | H18: 20 | I18: 3.4 | K18: 15.05 | L18: 301
A19: 1609 | B19: 9020000000 | C19: Endotracheal Tubes | G19: 8 | H19: 679 | I19: 17.69 | K19: 3.48 | L19: 2362.92
A20: 1609.99 | B20: 9020000000 | C20: Endotracheal Tubes | G20: 6 | H20: 466 | I20: 16.47 | K20: 3.48 | L20: 1621.68
A21: 1617 | B21: 9018908409 | C21: General Surgery Packs & Supplies | G21: 4 | H21: 180 | I21: 23.54 | K21: 22.34 | L21: 4021.2
A22: 1620 | B22: 9021101000 | C22: Orthopedic Surgery Packs & Supplies | G22: 1 | H22: 1 | I22: 7.21 | K22: 20.04 | L22: 20.04
A23: 1625.99 | B23: 901819 | C23: Tracheostomy & Cricothyroidotomy supplies, tubes and kits | G23: 5 | H23: 874 | I23: 18.42 | K23: 30.36 | L23: 26534.64
A24: 6201.1 | B24: 9402900000 | C24: Vinyl Bed Surface, ERB | E24: none | G24: 60 | H24: 60 | I24: 598.74 | K24: 608 | L24: 36480
A25: 6820 | B25: 9018908409 | C25: Surgical Instrument Kit, Arthrex | E25: none | G25: 25 | H25: 25 | I25: 100.92 | K25: 1000 | L25: 25000
A26: 6822 | B26: 9018908409 | C26: Surgical Instrument Kit, Suture Set | E26: none | G26: 2 | H26: 2 | I26: 11.79 | K26: 261 | L26: 522
A27: 6825 | B27: 9018908409 | C27: Surgical Instrument Kit, General | E27: none | G27: 4 | H27: 4 | I27: 29.57 | K27: 658 | L27: 2632
A28: 6835 | B28: 9018900000 | C28: Surgical Instrument Kit, Delivery | E28: none | G28: 2 | H28: 2 | I28: 12.16 | K28: 406 | L28: 812
A29: 6838 | B29: 9018908409 | C29: Surgical Instrument Kit, Ortho | E29: none | G29: 2 | H29: 2 | I29: 13.61 | K29: 1652 | L29: 3304
A30: 6847 | B30: 9018908409 | C30: Surgical Instrument Kit, Minor | E30: none | G30: 2 | H30: 2 | I30: 11.34 | K30: 468 | L30: 936
A31: Total: 148247.94

Sheet 62219
A1: Shipper: Project C.U.R.E. Project # 62219 Planned Manifest Country of Destination Ukraine
A2: Product Code | B2: HS Code | D2: Description | F2: Transformer Needed (only for 220-240V countries) | G2: Number Ordered
A3: Aid Pioneers - Ukraine Relief
A4: 301 | B4: 6302210000 | D4: Bed Linens And Towels | G4: 10
A5: 302 | B5: 6307909800 | D5: Surgical Caps And Hats, Shoe Covers | G5: 10
A6: 305.99 | B6: 3926201010 | D6: Gloves, Non-sterile | G6: 40
A7: 310.99 | B7: 6211320000 | D7: Gowns, Surgical, Sterile | G7: 30
A8: 311.1 | B8: 6211320000 | D8: Scrubs, FIG | F8: none | G8: 10
A9: 501.99 | B9: 3006100100 | D9: 2x2, 4x4, Abd Sterile Dressings | G9: 15
A10: 506.99 | B10: 3005900000 | D10: Gauze and All Other Non Sterile Dressings | G10: 2
A11: 507.99 | B11: 3005909900 | D11: Kerlix/Kling Dressing | G11: 10
A12: 511.99 | B12: 3006100100 | D12: Specialty Dressings (and All Other Dressings Not Fitting In Other Categories) | G12: 2
A13: 601 | B13: 3006500000 | D13: Bags, Red, Spill Kits And Isolyszer | G13: 10
A14: 602.99 | B14: 3808940000 | D14: Disinfectant, Non-Patient; Also Sterilization Products & Sprays (Cidex, Etc) | G14: 10
A15: 604 | B15: 3923100000 | D15: Liners, Trash Can, Laundry & Plastic Bags, Mopheads | G15: 5
A16: 608.99 | B16: 3006101000 | D16: Sterilization, Tapes, Indicators, Wraps & Pouches | G16: 5
A17: 708.99 | B17: 9018310040 | D17: Needles, Mixed Gauges | G17: 30
A18: 709.99 | B18: 9018310040 | D18: Syringes, 1 cc/tb | G18: 10
A19: 710.99 | B19: 9018310040 | D19: Syringes, 3cc | G19: 25
A20: 714.99 | B20: 9018310040 | D20: Syringes, 30cc and 60cc | G20: 5
... A30: 1210.99 | B30: 9018900000 | D30: Feeding Tubes, Bags, Pump Set and Supplies | G30: 10
A31: Product Code | B31: HS Code | D31: Description | F31: Transformer Needed (only for 220-240V countries) | G31: Number Ordered
A32: Aid Pioneers - Ukraine Relief
A33: 1215.99 | B33: 3006910000 | D33: Ostomy (Colostomy, Ileostomy, Urostomy) Supplies, including Pouches, Adhesives, Etc) | G33: 10
A34: 1217.99 | B34: 3307900008 | D34: Patient Supplies (Soaps, Shampoos, Mouthwash, Toothpaste, Belonging Bags),slippers | G34: 15
A35: 1222.99 | B35: 9619008109 | D35: Underpads, (Chux and Blue Pads) | G35: 10
A36: 1402.99 | B36: 9018390000 | D36: Nasal Cannulas | G36: 5
A37: 1404.99 | B37: 90200000 | D37: Oxygen Masks and Tubing | G37: 10
A38: 1501.99 | B38: 3808940000 | D38: Alcohol and Betadine Pads & Swabs | G38: 20
A39: 1601.99 | B39: 9019200000 | D39: Anesthesia Circuit Sets | G39: 5
A40: 1602.99 | B40: 9018903000 | D40: Anesthesia Facemasks | G40: 5
A41: 1603.99 | B41: 9018900000 | D41: Ambu Bags | G41: 5
A42: 1606.99 | B42: 9018908409 | D42: Chest Tubes and Drainage Unites | G42: 10
A43: 1610.99 | B43: 9018321000 | D43: Epidural / Spinal Needles and Kits | G43: 2
A44: 1615.99 | B44: 9018908409 | D44: Ear, Nose & Throat Surgery Packs & Supplies | G44: 5
... A51: 1707.99 | B51: 9018390030 | D51: Suction Catheter, Tips, Tubings & Connectors | G51: 5
A52: 1801.99 | B52: 3923.29.0000 | D52: Urinary Bags (Leg and Bedside) And Urinary Supplies | G52: 2
A53: 1802.99 | B53: 9018390030 | D53: Urinary Catheters, Trays & Insertion Sets | G53: 5
A54: 1913 | B54: 8419200000 | D54: Autoclave, Sterilizer, Desktop | F54: 3815.42 | G54: 1
A55: 2104 | B55: 9018900000 | D55: Cast Saw | F55: 3815.4 | G55: 1
A56: 2113 | B56: 9019200000 | D56: Cold Therapy Unit / Portable | F56: 3815.15 | G56: 2
A57: 2117.1 | B57: 9019200000 | D57: Concentrator, Oxygen | G57: 23
A58: 2120.0199 | B58: 9019200000 | D58: CPAP Supplies | F58: none | G58: 1
A59: 2120.1 | B59: 9019200000 | D59: CPAP Unit W/ Humidifier | F59: 3815.25 | G59: 1
A60: 3006 | B60: 9018902000 | D60: Laryngoscope | F60: none | G60: 4
A61: 3013 | B61: 9405204001 | D61: Light, Exam | F61: 3815.15 | G61: 2
A62: 3110 | B62: 9018199000 | D62: Monitor, vital signs, 5 function (NIPB,Pulse, Optional TEMP,SPO2,ECG) | F62: 3815.15 | G62: 1
A63: 3200 | B63: 9019200000 | D63: Nebulizer | F63: 3815.25 | G63: 2
A64: 3308 | B64: 9018908409 | D64: Otoscope / Ophthalmoscope Wall Mounted AC Powered | F64: 3815.15 | G64: 2
A65: 3312 | B65: 9017308000 | D65: Oxygen Tank Regulator | F65: none | G65: 4
A66: Product Code | B66: HS Code | D66: Description | F66: Transformer Needed (only for 220-240V countries) | G66: Number Ordered
A67: Aid Pioneers - Ukraine Relief
A68: 3426 | B68: 90189099 | D68: Pump, Lymph Assist | F68: 3815.15 | G68: 2
A69: 3708 | B69: 9018908409 | D69: Speculum, Non Disposable, Vaginal | F69: none | G69: 2
A70: 3710 | B70: 9018901000 | D70: Sphygmomanometer, Wall Mount | F70: none | G70: 1
A71: 3710.01 | B71: 9018901000 | D71: Sphygmomanometer Cuffs | F71: none | G71: 1
A72: 3715 | B72: 9018908409 | D72: Stethoscope | F72: none | G72: 10
A73: 3715.1 | B73: 9018908409 | D73: Stethoscope, Disposable | F73: none | G73: 10
A74: 3718 | B74: 9018908409 | D74: Suction Machine / Low Pressure / Portable | F74: 3815.25 | G74: 1
A75: 3722 | B75: 9018906000 | D75: Surgical Shavers | F75: 3815.15 | G75: 1
A76: 3722.01 | B76: 9018906000 | D76: Surgical Shaver Heads | F76: none | G76: 1
A77: 3802.7 | B77: 9025190000 | D77: Clinic Grade Thermometer, Forehead,105800 | F77: none | G77: 12
A78: 5105 | B78: 9402900010 | D78: Bed, Home Healthcare | F78: 3815.3 | G78: 6
A79: 5112 | B79: 9402900010 | D79: Bed, ICU | F79: 3815.42 | G79: 2
A80: 5112.1 | B80: 9403.20.0010 | D80: Bed, ICU with Air Mattress | F80: 3815.42 | G80: 2
A81: 5203 | B81: 9403109809 | D81: Cabinet, Misc | F81: none | G81: 2
A82: 5206 | B82: 9021101000 | D82: Cane, Quad | F82: none | G82: 15
A83: 5213 | B83: 9402900000 | D83: Cart, Oxygen Cylinder | F83: none | G83: 1
A84: 5228 | B84: 9403208009 | D84: Commode, Bedside | F84: none | G84: 15
A85: 5237 | B85: 9021101000 | D85: Crutches | F85: none | G85: 15
A86: 5501 | B86: 9403109300 | D86: File Cabinet | F86: none | G86: 1
A87: 5601 | B87: 9402.90.0020 | D87: Gurney | F87: none | G87: 4
A88: 5701 | B88: 9402900000 | D88: Hoyer Lift | F88: none | G88: 5
A89: 5802 | B89: 9018390000 | D89: IV Pole | F89: none | G89: 5
A90: 6201 | B90: 9402900000 | D90: Vinyl Bed Surface | F90: none | G90: 12
A91: 6201.1 | B91: 9402900000 | D91: Vinyl Bed Surface, ERB | F91: none | G91: 15
A92: 6203 | B92: 9403208009 | D92: Mayo Stand | F92: none | G92: 1
A93: 6800 | B93: 8423820000 | D93: Scale, Adult | F93: none | G93: 1
A94: 6803 | B94: 9016000000 | D94: Stacking Storage Bins | F94: none | G94: 5
A95: 6822 | B95: 9018908409 | D95: Surgical Instrument Kit, Suture Set | F95: none | G95: 1
A96: 6825 | B96: 9018908409 | D96: Surgical Instrument Kit, General | F96: none | G96: 2
A97: 6835 | B97: 9018900000 | D97: Surgical Instrument Kit, Delivery | F97: none | G97: 1
A98: 6905 | B98: 9402900000 | D98: Table, Exam | F98: none | G98: 6
A99: 6925 | D99: Transfer Board | F99: none | G99: 1
A100: 6926 | B100: 6307909200 | D100: Trash / Biohazard Waste Cans | F100: none | G100: 2
A101: 7202 | B101: 9021101000 | D101: Walker, Adult | F101: none | G101: 2
A102: 7211 | B102: 8713109000 | D102: Wheelchair Transport Unit | F102: none | G102: 3
A103: Transformer Size Reference
A104: Transformer # | C104: Transformer Size (Watts)
A105: 3815.1 | C105: Transformer, 50 Watt
A106: 3815.15 | C106: Transformer, 100 watt
A107: 3815.2 | C107: Transformer, 200 Watt
A108: 3815.25 | C108: Transformer, 300 watt
A109: 3815.3 | C109: Transformer, 500 Watt
A110: 3815.35 | C110: Transformer, 750 watt
A111: 3815.4 | C111: Transformer, 1,000 Watt
A112: 3815.42 | C112: Transformer, 1,500 watts
A113: 3815.45 | C113: Transformer, 2,000 watt
A114: 3815.5 | C114: Transformer, 3,000 Watt
A115: 3815.55 | C115: Transformer, 5,000 watt
...
